import android.content.Context;
import java.util.Map;

public final class bay
  implements bdd
{
  private static final String f = cvl.a;
  final Context a;
  final long b;
  final long c;
  final Map<String, baz> d;
  public final bdk e;
  
  public bay(Context paramContext, long paramLong1, long paramLong2, Map<String, baz> paramMap)
  {
    a = paramContext;
    b = paramLong1;
    c = paramLong2;
    d = paramMap;
    e = new bdk();
  }
  
  public final void a(int paramInt) {}
  
  /* Error */
  public final void a(bdg parambdg)
  {
    // Byte code:
    //   0: aload_0
    //   1: getfield 39	bay:d	Ljava/util/Map;
    //   4: aload_1
    //   5: getfield 55	bdg:f	Ljava/lang/String;
    //   8: invokeinterface 61 2 0
    //   13: checkcast 63	baz
    //   16: astore_3
    //   17: aload_3
    //   18: ifnull +268 -> 286
    //   21: iconst_1
    //   22: istore_2
    //   23: iload_2
    //   24: ifne +14 -> 38
    //   27: aload_1
    //   28: getstatic 68	bda:a	Lbda;
    //   31: invokevirtual 71	bdg:b	(Lbda;)Z
    //   34: ifeq +4 -> 38
    //   37: return
    //   38: iload_2
    //   39: ifne +167 -> 206
    //   42: new 73	beb
    //   45: dup
    //   46: invokespecial 74	beb:<init>	()V
    //   49: astore_3
    //   50: aload_0
    //   51: getfield 44	bay:e	Lbdk;
    //   54: astore 4
    //   56: aload 4
    //   58: aload 4
    //   60: getfield 77	bdk:d	I
    //   63: iconst_1
    //   64: iadd
    //   65: putfield 77	bdk:d	I
    //   68: aload_3
    //   69: ifnull +211 -> 280
    //   72: aload_3
    //   73: aload_1
    //   74: aload_0
    //   75: getfield 35	bay:b	J
    //   78: aload_0
    //   79: getfield 37	bay:c	J
    //   82: invokestatic 82	aqt:a	(Lbeb;Lbdg;JJ)Z
    //   85: pop
    //   86: aload_3
    //   87: getfield 85	beb:X	Ljava/lang/String;
    //   90: invokestatic 91	android/text/TextUtils:isEmpty	(Ljava/lang/CharSequence;)Z
    //   93: ifeq +198 -> 291
    //   96: aload_3
    //   97: getfield 94	beb:Y	Ljava/lang/String;
    //   100: invokestatic 91	android/text/TextUtils:isEmpty	(Ljava/lang/CharSequence;)Z
    //   103: ifeq +188 -> 291
    //   106: aload_3
    //   107: getfield 97	beb:Z	Ljava/lang/String;
    //   110: invokestatic 91	android/text/TextUtils:isEmpty	(Ljava/lang/CharSequence;)Z
    //   113: ifeq +178 -> 291
    //   116: aload_3
    //   117: getfield 100	beb:aa	Ljava/lang/String;
    //   120: invokestatic 91	android/text/TextUtils:isEmpty	(Ljava/lang/CharSequence;)Z
    //   123: ifeq +168 -> 291
    //   126: aload_3
    //   127: getfield 103	beb:o	Ljava/lang/String;
    //   130: invokestatic 91	android/text/TextUtils:isEmpty	(Ljava/lang/CharSequence;)Z
    //   133: ifeq +158 -> 291
    //   136: aload_3
    //   137: getfield 106	beb:y	J
    //   140: lconst_0
    //   141: lcmp
    //   142: ifne +149 -> 291
    //   145: aload_3
    //   146: getfield 109	beb:n	J
    //   149: lconst_0
    //   150: lcmp
    //   151: ifeq +88 -> 239
    //   154: goto +137 -> 291
    //   157: iload_2
    //   158: ifeq +86 -> 244
    //   161: aload_3
    //   162: aload_0
    //   163: getfield 33	bay:a	Landroid/content/Context;
    //   166: invokestatic 114	baa:a	(Lbdv;Landroid/content/Context;)V
    //   169: iconst_1
    //   170: istore_2
    //   171: iload_2
    //   172: ifne +113 -> 285
    //   175: aload_0
    //   176: getfield 44	bay:e	Lbdk;
    //   179: astore_1
    //   180: aload_1
    //   181: aload_1
    //   182: getfield 116	bdk:f	I
    //   185: iconst_1
    //   186: iadd
    //   187: putfield 116	bdk:f	I
    //   190: return
    //   191: astore_1
    //   192: ldc 118
    //   194: aload_1
    //   195: ldc 120
    //   197: iconst_0
    //   198: anewarray 4	java/lang/Object
    //   201: invokestatic 125	cvm:e	(Ljava/lang/String;Ljava/lang/Throwable;Ljava/lang/String;[Ljava/lang/Object;)I
    //   204: pop
    //   205: return
    //   206: aload_0
    //   207: getfield 33	bay:a	Landroid/content/Context;
    //   210: aload_3
    //   211: getfield 126	baz:b	J
    //   214: invokestatic 129	beb:a	(Landroid/content/Context;J)Lbeb;
    //   217: astore_3
    //   218: aload_0
    //   219: getfield 44	bay:e	Lbdk;
    //   222: astore 4
    //   224: aload 4
    //   226: aload 4
    //   228: getfield 131	bdk:e	I
    //   231: iconst_1
    //   232: iadd
    //   233: putfield 131	bdk:e	I
    //   236: goto -168 -> 68
    //   239: iconst_0
    //   240: istore_2
    //   241: goto -84 -> 157
    //   244: getstatic 26	bay:f	Ljava/lang/String;
    //   247: ldc -123
    //   249: iconst_1
    //   250: anewarray 4	java/lang/Object
    //   253: dup
    //   254: iconst_0
    //   255: aload_3
    //   256: aastore
    //   257: invokestatic 136	cvm:f	(Ljava/lang/String;Ljava/lang/String;[Ljava/lang/Object;)I
    //   260: pop
    //   261: iconst_0
    //   262: istore_2
    //   263: goto -92 -> 171
    //   266: astore_1
    //   267: ldc 118
    //   269: aload_1
    //   270: ldc -118
    //   272: iconst_0
    //   273: anewarray 4	java/lang/Object
    //   276: invokestatic 125	cvm:e	(Ljava/lang/String;Ljava/lang/Throwable;Ljava/lang/String;[Ljava/lang/Object;)I
    //   279: pop
    //   280: iconst_0
    //   281: istore_2
    //   282: goto -111 -> 171
    //   285: return
    //   286: iconst_0
    //   287: istore_2
    //   288: goto -265 -> 23
    //   291: iconst_1
    //   292: istore_2
    //   293: goto -136 -> 157
    // Local variable table:
    //   start	length	slot	name	signature
    //   0	296	0	this	bay
    //   0	296	1	parambdg	bdg
    //   22	271	2	i	int
    //   16	240	3	localObject	Object
    //   54	173	4	localbdk	bdk
    // Exception table:
    //   from	to	target	type
    //   0	17	191	java/lang/Exception
    //   27	37	191	java/lang/Exception
    //   42	68	191	java/lang/Exception
    //   72	154	191	java/lang/Exception
    //   161	169	191	java/lang/Exception
    //   175	190	191	java/lang/Exception
    //   206	236	191	java/lang/Exception
    //   244	261	191	java/lang/Exception
    //   267	280	191	java/lang/Exception
    //   72	154	266	bdi
    //   161	169	266	bdi
    //   244	261	266	bdi
  }
}

/* Location:
 * Qualified Name:     bay
 * Java Class Version: 6 (50.0)
 * JD-Core Version:    0.7.1
 */