final class dte
  implements Runnable
{
  public dte(drp paramdrp) {}
  
  /* Error */
  public final void run()
  {
    // Byte code:
    //   0: bipush 10
    //   2: invokestatic 33	android/os/Process:setThreadPriority	(I)V
    //   5: aload_0
    //   6: getfield 12	dte:a	Ldrp;
    //   9: getfield 39	drp:B	Z
    //   12: ifeq +4 -> 16
    //   15: return
    //   16: getstatic 43	drp:b	Ljava/lang/String;
    //   19: iconst_3
    //   20: invokestatic 48	dri:a	(Ljava/lang/String;I)Z
    //   23: ifeq +183 -> 206
    //   26: invokestatic 54	android/os/SystemClock:elapsedRealtime	()J
    //   29: lstore_1
    //   30: aload_0
    //   31: getfield 12	dte:a	Ldrp;
    //   34: getfield 58	drp:K	Ljava/lang/Thread;
    //   37: ifnull +164 -> 201
    //   40: iconst_1
    //   41: istore_3
    //   42: aload_0
    //   43: getfield 12	dte:a	Ldrp;
    //   46: getfield 62	drp:G	Ljava/lang/Object;
    //   49: astore 4
    //   51: aload 4
    //   53: monitorenter
    //   54: getstatic 43	drp:b	Ljava/lang/String;
    //   57: iconst_3
    //   58: invokestatic 48	dri:a	(Ljava/lang/String;I)Z
    //   61: ifeq +44 -> 105
    //   64: invokestatic 54	android/os/SystemClock:elapsedRealtime	()J
    //   67: lload_1
    //   68: lsub
    //   69: lstore_1
    //   70: lload_1
    //   71: ldc2_w 63
    //   74: lcmp
    //   75: ifle +30 -> 105
    //   78: getstatic 43	drp:b	Ljava/lang/String;
    //   81: ldc 66
    //   83: iconst_2
    //   84: anewarray 4	java/lang/Object
    //   87: dup
    //   88: iconst_0
    //   89: lload_1
    //   90: invokestatic 72	java/lang/Long:valueOf	(J)Ljava/lang/Long;
    //   93: aastore
    //   94: dup
    //   95: iconst_1
    //   96: iload_3
    //   97: invokestatic 77	java/lang/Boolean:valueOf	(Z)Ljava/lang/Boolean;
    //   100: aastore
    //   101: invokestatic 80	dri:b	(Ljava/lang/String;Ljava/lang/String;[Ljava/lang/Object;)I
    //   104: pop
    //   105: aload_0
    //   106: getfield 12	dte:a	Ldrp;
    //   109: iconst_1
    //   110: putfield 39	drp:B	Z
    //   113: aload_0
    //   114: getfield 12	dte:a	Ldrp;
    //   117: new 82	dtd
    //   120: dup
    //   121: invokespecial 83	dtd:<init>	()V
    //   124: invokestatic 86	drp:a	(Ldrp;Ldtd;)Z
    //   127: pop
    //   128: getstatic 43	drp:b	Ljava/lang/String;
    //   131: ldc 88
    //   133: iconst_0
    //   134: anewarray 4	java/lang/Object
    //   137: invokestatic 90	dri:a	(Ljava/lang/String;Ljava/lang/String;[Ljava/lang/Object;)I
    //   140: pop
    //   141: aload 4
    //   143: monitorexit
    //   144: aload_0
    //   145: getfield 12	dte:a	Ldrp;
    //   148: iconst_0
    //   149: iconst_0
    //   150: invokevirtual 93	drp:a	(II)V
    //   153: aload_0
    //   154: getfield 12	dte:a	Ldrp;
    //   157: iconst_0
    //   158: putfield 39	drp:B	Z
    //   161: aload_0
    //   162: getfield 12	dte:a	Ldrp;
    //   165: iconst_1
    //   166: putfield 96	drp:af	Z
    //   169: aload_0
    //   170: getfield 12	dte:a	Ldrp;
    //   173: getfield 99	drp:J	Ljava/lang/Object;
    //   176: astore 4
    //   178: aload 4
    //   180: monitorenter
    //   181: aload_0
    //   182: getfield 12	dte:a	Ldrp;
    //   185: aconst_null
    //   186: putfield 58	drp:K	Ljava/lang/Thread;
    //   189: aload 4
    //   191: monitorexit
    //   192: return
    //   193: astore 5
    //   195: aload 4
    //   197: monitorexit
    //   198: aload 5
    //   200: athrow
    //   201: iconst_0
    //   202: istore_3
    //   203: goto -161 -> 42
    //   206: lconst_0
    //   207: lstore_1
    //   208: iconst_0
    //   209: istore_3
    //   210: goto -168 -> 42
    //   213: astore 5
    //   215: aload 4
    //   217: monitorexit
    //   218: aload 5
    //   220: athrow
    //   221: astore 4
    //   223: getstatic 43	drp:b	Ljava/lang/String;
    //   226: ldc 101
    //   228: iconst_1
    //   229: anewarray 4	java/lang/Object
    //   232: dup
    //   233: iconst_0
    //   234: aload 4
    //   236: invokevirtual 105	java/io/IOException:getMessage	()Ljava/lang/String;
    //   239: aastore
    //   240: invokestatic 108	dri:c	(Ljava/lang/String;Ljava/lang/String;[Ljava/lang/Object;)I
    //   243: pop
    //   244: aload_0
    //   245: getfield 12	dte:a	Ldrp;
    //   248: iconst_1
    //   249: iconst_0
    //   250: invokevirtual 93	drp:a	(II)V
    //   253: aload_0
    //   254: getfield 12	dte:a	Ldrp;
    //   257: iconst_0
    //   258: putfield 39	drp:B	Z
    //   261: aload_0
    //   262: getfield 12	dte:a	Ldrp;
    //   265: iconst_1
    //   266: putfield 96	drp:af	Z
    //   269: aload_0
    //   270: getfield 12	dte:a	Ldrp;
    //   273: getfield 99	drp:J	Ljava/lang/Object;
    //   276: astore 4
    //   278: aload 4
    //   280: monitorenter
    //   281: aload_0
    //   282: getfield 12	dte:a	Ldrp;
    //   285: aconst_null
    //   286: putfield 58	drp:K	Ljava/lang/Thread;
    //   289: aload 4
    //   291: monitorexit
    //   292: return
    //   293: astore 5
    //   295: aload 4
    //   297: monitorexit
    //   298: aload 5
    //   300: athrow
    //   301: astore 4
    //   303: getstatic 43	drp:b	Ljava/lang/String;
    //   306: ldc 110
    //   308: iconst_1
    //   309: anewarray 4	java/lang/Object
    //   312: dup
    //   313: iconst_0
    //   314: aload 4
    //   316: invokevirtual 111	dtf:getMessage	()Ljava/lang/String;
    //   319: aastore
    //   320: invokestatic 108	dri:c	(Ljava/lang/String;Ljava/lang/String;[Ljava/lang/Object;)I
    //   323: pop
    //   324: aload_0
    //   325: getfield 12	dte:a	Ldrp;
    //   328: bipush 16
    //   330: iconst_0
    //   331: invokevirtual 93	drp:a	(II)V
    //   334: aload_0
    //   335: getfield 12	dte:a	Ldrp;
    //   338: iconst_0
    //   339: putfield 39	drp:B	Z
    //   342: aload_0
    //   343: getfield 12	dte:a	Ldrp;
    //   346: iconst_1
    //   347: putfield 96	drp:af	Z
    //   350: aload_0
    //   351: getfield 12	dte:a	Ldrp;
    //   354: getfield 99	drp:J	Ljava/lang/Object;
    //   357: astore 4
    //   359: aload 4
    //   361: monitorenter
    //   362: aload_0
    //   363: getfield 12	dte:a	Ldrp;
    //   366: aconst_null
    //   367: putfield 58	drp:K	Ljava/lang/Thread;
    //   370: aload 4
    //   372: monitorexit
    //   373: return
    //   374: astore 5
    //   376: aload 4
    //   378: monitorexit
    //   379: aload 5
    //   381: athrow
    //   382: astore 4
    //   384: getstatic 43	drp:b	Ljava/lang/String;
    //   387: ldc 113
    //   389: iconst_1
    //   390: anewarray 4	java/lang/Object
    //   393: dup
    //   394: iconst_0
    //   395: aload 4
    //   397: invokevirtual 114	dsj:getMessage	()Ljava/lang/String;
    //   400: aastore
    //   401: invokestatic 108	dri:c	(Ljava/lang/String;Ljava/lang/String;[Ljava/lang/Object;)I
    //   404: pop
    //   405: aload_0
    //   406: getfield 12	dte:a	Ldrp;
    //   409: iconst_2
    //   410: iconst_0
    //   411: invokevirtual 93	drp:a	(II)V
    //   414: aload_0
    //   415: getfield 12	dte:a	Ldrp;
    //   418: iconst_0
    //   419: putfield 39	drp:B	Z
    //   422: aload_0
    //   423: getfield 12	dte:a	Ldrp;
    //   426: iconst_1
    //   427: putfield 96	drp:af	Z
    //   430: aload_0
    //   431: getfield 12	dte:a	Ldrp;
    //   434: getfield 99	drp:J	Ljava/lang/Object;
    //   437: astore 4
    //   439: aload 4
    //   441: monitorenter
    //   442: aload_0
    //   443: getfield 12	dte:a	Ldrp;
    //   446: aconst_null
    //   447: putfield 58	drp:K	Ljava/lang/Thread;
    //   450: aload 4
    //   452: monitorexit
    //   453: return
    //   454: astore 5
    //   456: aload 4
    //   458: monitorexit
    //   459: aload 5
    //   461: athrow
    //   462: astore 4
    //   464: getstatic 43	drp:b	Ljava/lang/String;
    //   467: ldc 116
    //   469: iconst_1
    //   470: anewarray 4	java/lang/Object
    //   473: dup
    //   474: iconst_0
    //   475: aload 4
    //   477: invokevirtual 117	dty:getMessage	()Ljava/lang/String;
    //   480: aastore
    //   481: invokestatic 108	dri:c	(Ljava/lang/String;Ljava/lang/String;[Ljava/lang/Object;)I
    //   484: pop
    //   485: aload_0
    //   486: getfield 12	dte:a	Ldrp;
    //   489: bipush 7
    //   491: iconst_2
    //   492: invokevirtual 93	drp:a	(II)V
    //   495: aload_0
    //   496: getfield 12	dte:a	Ldrp;
    //   499: iconst_0
    //   500: putfield 39	drp:B	Z
    //   503: aload_0
    //   504: getfield 12	dte:a	Ldrp;
    //   507: iconst_1
    //   508: putfield 96	drp:af	Z
    //   511: aload_0
    //   512: getfield 12	dte:a	Ldrp;
    //   515: getfield 99	drp:J	Ljava/lang/Object;
    //   518: astore 4
    //   520: aload 4
    //   522: monitorenter
    //   523: aload_0
    //   524: getfield 12	dte:a	Ldrp;
    //   527: aconst_null
    //   528: putfield 58	drp:K	Ljava/lang/Thread;
    //   531: aload 4
    //   533: monitorexit
    //   534: return
    //   535: astore 5
    //   537: aload 4
    //   539: monitorexit
    //   540: aload 5
    //   542: athrow
    //   543: astore 4
    //   545: getstatic 43	drp:b	Ljava/lang/String;
    //   548: aload 4
    //   550: ldc 119
    //   552: iconst_0
    //   553: anewarray 4	java/lang/Object
    //   556: invokestatic 122	dri:c	(Ljava/lang/String;Ljava/lang/Throwable;Ljava/lang/String;[Ljava/lang/Object;)I
    //   559: pop
    //   560: aload_0
    //   561: getfield 12	dte:a	Ldrp;
    //   564: iconst_3
    //   565: iconst_0
    //   566: invokevirtual 93	drp:a	(II)V
    //   569: aload_0
    //   570: getfield 12	dte:a	Ldrp;
    //   573: iconst_0
    //   574: putfield 39	drp:B	Z
    //   577: aload_0
    //   578: getfield 12	dte:a	Ldrp;
    //   581: iconst_1
    //   582: putfield 96	drp:af	Z
    //   585: aload_0
    //   586: getfield 12	dte:a	Ldrp;
    //   589: getfield 99	drp:J	Ljava/lang/Object;
    //   592: astore 4
    //   594: aload 4
    //   596: monitorenter
    //   597: aload_0
    //   598: getfield 12	dte:a	Ldrp;
    //   601: aconst_null
    //   602: putfield 58	drp:K	Ljava/lang/Thread;
    //   605: aload 4
    //   607: monitorexit
    //   608: return
    //   609: astore 5
    //   611: aload 4
    //   613: monitorexit
    //   614: aload 5
    //   616: athrow
    //   617: astore 5
    //   619: aload_0
    //   620: getfield 12	dte:a	Ldrp;
    //   623: iconst_0
    //   624: putfield 39	drp:B	Z
    //   627: aload_0
    //   628: getfield 12	dte:a	Ldrp;
    //   631: iconst_1
    //   632: putfield 96	drp:af	Z
    //   635: aload_0
    //   636: getfield 12	dte:a	Ldrp;
    //   639: getfield 99	drp:J	Ljava/lang/Object;
    //   642: astore 4
    //   644: aload 4
    //   646: monitorenter
    //   647: aload_0
    //   648: getfield 12	dte:a	Ldrp;
    //   651: aconst_null
    //   652: putfield 58	drp:K	Ljava/lang/Thread;
    //   655: aload 4
    //   657: monitorexit
    //   658: aload 5
    //   660: athrow
    //   661: astore 5
    //   663: aload 4
    //   665: monitorexit
    //   666: aload 5
    //   668: athrow
    // Local variable table:
    //   start	length	slot	name	signature
    //   0	669	0	this	dte
    //   29	179	1	l	long
    //   41	169	3	bool	boolean
    //   221	14	4	localIOException	java.io.IOException
    //   301	14	4	localdtf	dtf
    //   382	14	4	localdsj	dsj
    //   462	14	4	localdty	dty
    //   543	6	4	localdsl	dsl
    //   193	6	5	localObject7	Object
    //   213	6	5	localObject8	Object
    //   293	6	5	localObject9	Object
    //   374	6	5	localObject10	Object
    //   454	6	5	localObject11	Object
    //   535	6	5	localObject12	Object
    //   609	6	5	localObject13	Object
    //   617	42	5	localObject14	Object
    //   661	6	5	localObject15	Object
    // Exception table:
    //   from	to	target	type
    //   181	192	193	finally
    //   195	198	193	finally
    //   54	70	213	finally
    //   78	105	213	finally
    //   105	144	213	finally
    //   215	218	213	finally
    //   16	40	221	java/io/IOException
    //   42	54	221	java/io/IOException
    //   144	153	221	java/io/IOException
    //   218	221	221	java/io/IOException
    //   281	292	293	finally
    //   295	298	293	finally
    //   16	40	301	dtf
    //   42	54	301	dtf
    //   144	153	301	dtf
    //   218	221	301	dtf
    //   362	373	374	finally
    //   376	379	374	finally
    //   16	40	382	dsj
    //   42	54	382	dsj
    //   144	153	382	dsj
    //   218	221	382	dsj
    //   442	453	454	finally
    //   456	459	454	finally
    //   16	40	462	dty
    //   42	54	462	dty
    //   144	153	462	dty
    //   218	221	462	dty
    //   523	534	535	finally
    //   537	540	535	finally
    //   16	40	543	dsl
    //   42	54	543	dsl
    //   144	153	543	dsl
    //   218	221	543	dsl
    //   597	608	609	finally
    //   611	614	609	finally
    //   16	40	617	finally
    //   42	54	617	finally
    //   144	153	617	finally
    //   218	221	617	finally
    //   223	253	617	finally
    //   303	334	617	finally
    //   384	414	617	finally
    //   464	495	617	finally
    //   545	569	617	finally
    //   647	658	661	finally
    //   663	666	661	finally
  }
}

/* Location:
 * Qualified Name:     dte
 * Java Class Version: 6 (50.0)
 * JD-Core Version:    0.7.1
 */