import android.content.Context;

public final class eet
{
  private final Context a;
  
  public eet(Context paramContext)
  {
    a = ((Context)enz.a(paramContext));
  }
  
  /* Error */
  public final <R> R a(eex<R> parameex)
  {
    // Byte code:
    //   0: aconst_null
    //   1: astore 5
    //   3: aload_0
    //   4: getfield 20	eet:a	Landroid/content/Context;
    //   7: invokevirtual 30	android/content/Context:getPackageName	()Ljava/lang/String;
    //   10: astore 6
    //   12: new 32	android/content/Intent
    //   15: dup
    //   16: invokespecial 33	android/content/Intent:<init>	()V
    //   19: ldc 35
    //   21: invokevirtual 39	android/content/Intent:setPackage	(Ljava/lang/String;)Landroid/content/Intent;
    //   24: ldc 41
    //   26: invokevirtual 44	android/content/Intent:setAction	(Ljava/lang/String;)Landroid/content/Intent;
    //   29: ldc 46
    //   31: invokevirtual 49	android/content/Intent:addCategory	(Ljava/lang/String;)Landroid/content/Intent;
    //   34: getstatic 55	ecy:b	Ljava/lang/String;
    //   37: aload 6
    //   39: invokevirtual 59	android/content/Intent:putExtra	(Ljava/lang/String;Ljava/lang/String;)Landroid/content/Intent;
    //   42: astore 7
    //   44: invokestatic 65	android/os/Binder:clearCallingIdentity	()J
    //   47: lstore_2
    //   48: new 67	eph
    //   51: dup
    //   52: invokespecial 68	eph:<init>	()V
    //   55: astore 6
    //   57: invokestatic 73	eop:a	()Leop;
    //   60: astore 8
    //   62: aload_0
    //   63: getfield 20	eet:a	Landroid/content/Context;
    //   66: astore 9
    //   68: aload 8
    //   70: aload 9
    //   72: aload 9
    //   74: invokevirtual 77	java/lang/Object:getClass	()Ljava/lang/Class;
    //   77: invokevirtual 82	java/lang/Class:getName	()Ljava/lang/String;
    //   80: aload 7
    //   82: aload 6
    //   84: iconst_1
    //   85: invokevirtual 85	eop:a	(Landroid/content/Context;Ljava/lang/String;Landroid/content/Intent;Landroid/content/ServiceConnection;I)Z
    //   88: istore 4
    //   90: iload 4
    //   92: ifeq +166 -> 258
    //   95: aload 6
    //   97: invokevirtual 88	eph:a	()Landroid/os/IBinder;
    //   100: astore 7
    //   102: aload 7
    //   104: ifnonnull +30 -> 134
    //   107: aload_1
    //   108: aload 5
    //   110: invokeinterface 93 2 0
    //   115: astore_1
    //   116: invokestatic 73	eop:a	()Leop;
    //   119: aload_0
    //   120: getfield 20	eet:a	Landroid/content/Context;
    //   123: aload 6
    //   125: invokevirtual 96	eop:a	(Landroid/content/Context;Landroid/content/ServiceConnection;)V
    //   128: lload_2
    //   129: invokestatic 100	android/os/Binder:restoreCallingIdentity	(J)V
    //   132: aload_1
    //   133: areturn
    //   134: aload 7
    //   136: ldc 102
    //   138: invokeinterface 108 2 0
    //   143: astore 5
    //   145: aload 5
    //   147: ifnull +21 -> 168
    //   150: aload 5
    //   152: instanceof 110
    //   155: ifeq +13 -> 168
    //   158: aload 5
    //   160: checkcast 110	eft
    //   163: astore 5
    //   165: goto -58 -> 107
    //   168: new 112	efv
    //   171: dup
    //   172: aload 7
    //   174: invokespecial 115	efv:<init>	(Landroid/os/IBinder;)V
    //   177: astore 5
    //   179: goto -72 -> 107
    //   182: astore_1
    //   183: ldc 117
    //   185: new 119	java/lang/StringBuilder
    //   188: dup
    //   189: ldc 121
    //   191: invokespecial 124	java/lang/StringBuilder:<init>	(Ljava/lang/String;)V
    //   194: aload_1
    //   195: invokevirtual 127	java/lang/InterruptedException:getMessage	()Ljava/lang/String;
    //   198: invokevirtual 131	java/lang/StringBuilder:append	(Ljava/lang/String;)Ljava/lang/StringBuilder;
    //   201: invokevirtual 134	java/lang/StringBuilder:toString	()Ljava/lang/String;
    //   204: invokestatic 140	android/util/Log:w	(Ljava/lang/String;Ljava/lang/String;)I
    //   207: pop
    //   208: new 142	eev
    //   211: dup
    //   212: aload_1
    //   213: invokespecial 145	eev:<init>	(Ljava/lang/InterruptedException;)V
    //   216: athrow
    //   217: astore_1
    //   218: invokestatic 73	eop:a	()Leop;
    //   221: aload_0
    //   222: getfield 20	eet:a	Landroid/content/Context;
    //   225: aload 6
    //   227: invokevirtual 96	eop:a	(Landroid/content/Context;Landroid/content/ServiceConnection;)V
    //   230: aload_1
    //   231: athrow
    //   232: astore_1
    //   233: lload_2
    //   234: invokestatic 100	android/os/Binder:restoreCallingIdentity	(J)V
    //   237: aload_1
    //   238: athrow
    //   239: astore_1
    //   240: ldc 117
    //   242: ldc -109
    //   244: aload_1
    //   245: invokestatic 150	android/util/Log:w	(Ljava/lang/String;Ljava/lang/String;Ljava/lang/Throwable;)I
    //   248: pop
    //   249: new 152	eew
    //   252: dup
    //   253: aload_1
    //   254: invokespecial 155	eew:<init>	(Landroid/os/RemoteException;)V
    //   257: athrow
    //   258: lload_2
    //   259: invokestatic 100	android/os/Binder:restoreCallingIdentity	(J)V
    //   262: aconst_null
    //   263: areturn
    // Local variable table:
    //   start	length	slot	name	signature
    //   0	264	0	this	eet
    //   0	264	1	parameex	eex<R>
    //   47	212	2	l	long
    //   88	3	4	bool	boolean
    //   1	177	5	localObject1	Object
    //   10	216	6	localObject2	Object
    //   42	131	7	localObject3	Object
    //   60	9	8	localeop	eop
    //   66	7	9	localContext	Context
    // Exception table:
    //   from	to	target	type
    //   95	102	182	java/lang/InterruptedException
    //   107	116	182	java/lang/InterruptedException
    //   134	145	182	java/lang/InterruptedException
    //   150	165	182	java/lang/InterruptedException
    //   168	179	182	java/lang/InterruptedException
    //   95	102	217	finally
    //   107	116	217	finally
    //   134	145	217	finally
    //   150	165	217	finally
    //   168	179	217	finally
    //   183	217	217	finally
    //   240	258	217	finally
    //   48	90	232	finally
    //   116	128	232	finally
    //   218	232	232	finally
    //   95	102	239	android/os/RemoteException
    //   107	116	239	android/os/RemoteException
    //   134	145	239	android/os/RemoteException
    //   150	165	239	android/os/RemoteException
    //   168	179	239	android/os/RemoteException
  }
}

/* Location:
 * Qualified Name:     eet
 * Java Class Version: 6 (50.0)
 * JD-Core Version:    0.7.1
 */