import android.os.IBinder;
import android.os.Parcel;
import com.google.android.gms.drive.internal.OnLoadRealtimeResponse;

final class fch
  implements fcf
{
  private IBinder a;
  
  fch(IBinder paramIBinder)
  {
    a = paramIBinder;
  }
  
  public final void a()
  {
    Parcel localParcel1 = Parcel.obtain();
    Parcel localParcel2 = Parcel.obtain();
    try
    {
      localParcel1.writeInterfaceToken("com.google.android.gms.drive.internal.IDriveServiceCallbacks");
      a.transact(7, localParcel1, localParcel2, 0);
      localParcel2.readException();
      return;
    }
    finally
    {
      localParcel2.recycle();
      localParcel1.recycle();
    }
  }
  
  /* Error */
  public final void a(com.google.android.gms.common.api.Status paramStatus)
  {
    // Byte code:
    //   0: invokestatic 22	android/os/Parcel:obtain	()Landroid/os/Parcel;
    //   3: astore_2
    //   4: invokestatic 22	android/os/Parcel:obtain	()Landroid/os/Parcel;
    //   7: astore_3
    //   8: aload_2
    //   9: ldc 24
    //   11: invokevirtual 28	android/os/Parcel:writeInterfaceToken	(Ljava/lang/String;)V
    //   14: aload_1
    //   15: ifnull +42 -> 57
    //   18: aload_2
    //   19: iconst_1
    //   20: invokevirtual 45	android/os/Parcel:writeInt	(I)V
    //   23: aload_1
    //   24: aload_2
    //   25: iconst_0
    //   26: invokevirtual 51	com/google/android/gms/common/api/Status:writeToParcel	(Landroid/os/Parcel;I)V
    //   29: aload_0
    //   30: getfield 15	fch:a	Landroid/os/IBinder;
    //   33: bipush 6
    //   35: aload_2
    //   36: aload_3
    //   37: iconst_0
    //   38: invokeinterface 34 5 0
    //   43: pop
    //   44: aload_3
    //   45: invokevirtual 37	android/os/Parcel:readException	()V
    //   48: aload_3
    //   49: invokevirtual 40	android/os/Parcel:recycle	()V
    //   52: aload_2
    //   53: invokevirtual 40	android/os/Parcel:recycle	()V
    //   56: return
    //   57: aload_2
    //   58: iconst_0
    //   59: invokevirtual 45	android/os/Parcel:writeInt	(I)V
    //   62: goto -33 -> 29
    //   65: astore_1
    //   66: aload_3
    //   67: invokevirtual 40	android/os/Parcel:recycle	()V
    //   70: aload_2
    //   71: invokevirtual 40	android/os/Parcel:recycle	()V
    //   74: aload_1
    //   75: athrow
    // Local variable table:
    //   start	length	slot	name	signature
    //   0	76	0	this	fch
    //   0	76	1	paramStatus	com.google.android.gms.common.api.Status
    //   3	68	2	localParcel1	Parcel
    //   7	60	3	localParcel2	Parcel
    // Exception table:
    //   from	to	target	type
    //   8	14	65	finally
    //   18	29	65	finally
    //   29	48	65	finally
    //   57	62	65	finally
  }
  
  /* Error */
  public final void a(com.google.android.gms.drive.ChangeSequenceNumber paramChangeSequenceNumber)
  {
    // Byte code:
    //   0: invokestatic 22	android/os/Parcel:obtain	()Landroid/os/Parcel;
    //   3: astore_2
    //   4: invokestatic 22	android/os/Parcel:obtain	()Landroid/os/Parcel;
    //   7: astore_3
    //   8: aload_2
    //   9: ldc 24
    //   11: invokevirtual 28	android/os/Parcel:writeInterfaceToken	(Ljava/lang/String;)V
    //   14: aload_1
    //   15: ifnull +42 -> 57
    //   18: aload_2
    //   19: iconst_1
    //   20: invokevirtual 45	android/os/Parcel:writeInt	(I)V
    //   23: aload_1
    //   24: aload_2
    //   25: iconst_0
    //   26: invokevirtual 55	com/google/android/gms/drive/ChangeSequenceNumber:writeToParcel	(Landroid/os/Parcel;I)V
    //   29: aload_0
    //   30: getfield 15	fch:a	Landroid/os/IBinder;
    //   33: bipush 17
    //   35: aload_2
    //   36: aload_3
    //   37: iconst_0
    //   38: invokeinterface 34 5 0
    //   43: pop
    //   44: aload_3
    //   45: invokevirtual 37	android/os/Parcel:readException	()V
    //   48: aload_3
    //   49: invokevirtual 40	android/os/Parcel:recycle	()V
    //   52: aload_2
    //   53: invokevirtual 40	android/os/Parcel:recycle	()V
    //   56: return
    //   57: aload_2
    //   58: iconst_0
    //   59: invokevirtual 45	android/os/Parcel:writeInt	(I)V
    //   62: goto -33 -> 29
    //   65: astore_1
    //   66: aload_3
    //   67: invokevirtual 40	android/os/Parcel:recycle	()V
    //   70: aload_2
    //   71: invokevirtual 40	android/os/Parcel:recycle	()V
    //   74: aload_1
    //   75: athrow
    // Local variable table:
    //   start	length	slot	name	signature
    //   0	76	0	this	fch
    //   0	76	1	paramChangeSequenceNumber	com.google.android.gms.drive.ChangeSequenceNumber
    //   3	68	2	localParcel1	Parcel
    //   7	60	3	localParcel2	Parcel
    // Exception table:
    //   from	to	target	type
    //   8	14	65	finally
    //   18	29	65	finally
    //   29	48	65	finally
    //   57	62	65	finally
  }
  
  /* Error */
  public final void a(com.google.android.gms.drive.internal.GetPermissionsResponse paramGetPermissionsResponse)
  {
    // Byte code:
    //   0: invokestatic 22	android/os/Parcel:obtain	()Landroid/os/Parcel;
    //   3: astore_2
    //   4: invokestatic 22	android/os/Parcel:obtain	()Landroid/os/Parcel;
    //   7: astore_3
    //   8: aload_2
    //   9: ldc 24
    //   11: invokevirtual 28	android/os/Parcel:writeInterfaceToken	(Ljava/lang/String;)V
    //   14: aload_1
    //   15: ifnull +42 -> 57
    //   18: aload_2
    //   19: iconst_1
    //   20: invokevirtual 45	android/os/Parcel:writeInt	(I)V
    //   23: aload_1
    //   24: aload_2
    //   25: iconst_0
    //   26: invokevirtual 59	com/google/android/gms/drive/internal/GetPermissionsResponse:writeToParcel	(Landroid/os/Parcel;I)V
    //   29: aload_0
    //   30: getfield 15	fch:a	Landroid/os/IBinder;
    //   33: bipush 20
    //   35: aload_2
    //   36: aload_3
    //   37: iconst_0
    //   38: invokeinterface 34 5 0
    //   43: pop
    //   44: aload_3
    //   45: invokevirtual 37	android/os/Parcel:readException	()V
    //   48: aload_3
    //   49: invokevirtual 40	android/os/Parcel:recycle	()V
    //   52: aload_2
    //   53: invokevirtual 40	android/os/Parcel:recycle	()V
    //   56: return
    //   57: aload_2
    //   58: iconst_0
    //   59: invokevirtual 45	android/os/Parcel:writeInt	(I)V
    //   62: goto -33 -> 29
    //   65: astore_1
    //   66: aload_3
    //   67: invokevirtual 40	android/os/Parcel:recycle	()V
    //   70: aload_2
    //   71: invokevirtual 40	android/os/Parcel:recycle	()V
    //   74: aload_1
    //   75: athrow
    // Local variable table:
    //   start	length	slot	name	signature
    //   0	76	0	this	fch
    //   0	76	1	paramGetPermissionsResponse	com.google.android.gms.drive.internal.GetPermissionsResponse
    //   3	68	2	localParcel1	Parcel
    //   7	60	3	localParcel2	Parcel
    // Exception table:
    //   from	to	target	type
    //   8	14	65	finally
    //   18	29	65	finally
    //   29	48	65	finally
    //   57	62	65	finally
  }
  
  /* Error */
  public final void a(com.google.android.gms.drive.internal.OnChangesResponse paramOnChangesResponse)
  {
    // Byte code:
    //   0: invokestatic 22	android/os/Parcel:obtain	()Landroid/os/Parcel;
    //   3: astore_2
    //   4: invokestatic 22	android/os/Parcel:obtain	()Landroid/os/Parcel;
    //   7: astore_3
    //   8: aload_2
    //   9: ldc 24
    //   11: invokevirtual 28	android/os/Parcel:writeInterfaceToken	(Ljava/lang/String;)V
    //   14: aload_1
    //   15: ifnull +42 -> 57
    //   18: aload_2
    //   19: iconst_1
    //   20: invokevirtual 45	android/os/Parcel:writeInt	(I)V
    //   23: aload_1
    //   24: aload_2
    //   25: iconst_0
    //   26: invokevirtual 63	com/google/android/gms/drive/internal/OnChangesResponse:writeToParcel	(Landroid/os/Parcel;I)V
    //   29: aload_0
    //   30: getfield 15	fch:a	Landroid/os/IBinder;
    //   33: bipush 18
    //   35: aload_2
    //   36: aload_3
    //   37: iconst_0
    //   38: invokeinterface 34 5 0
    //   43: pop
    //   44: aload_3
    //   45: invokevirtual 37	android/os/Parcel:readException	()V
    //   48: aload_3
    //   49: invokevirtual 40	android/os/Parcel:recycle	()V
    //   52: aload_2
    //   53: invokevirtual 40	android/os/Parcel:recycle	()V
    //   56: return
    //   57: aload_2
    //   58: iconst_0
    //   59: invokevirtual 45	android/os/Parcel:writeInt	(I)V
    //   62: goto -33 -> 29
    //   65: astore_1
    //   66: aload_3
    //   67: invokevirtual 40	android/os/Parcel:recycle	()V
    //   70: aload_2
    //   71: invokevirtual 40	android/os/Parcel:recycle	()V
    //   74: aload_1
    //   75: athrow
    // Local variable table:
    //   start	length	slot	name	signature
    //   0	76	0	this	fch
    //   0	76	1	paramOnChangesResponse	com.google.android.gms.drive.internal.OnChangesResponse
    //   3	68	2	localParcel1	Parcel
    //   7	60	3	localParcel2	Parcel
    // Exception table:
    //   from	to	target	type
    //   8	14	65	finally
    //   18	29	65	finally
    //   29	48	65	finally
    //   57	62	65	finally
  }
  
  /* Error */
  public final void a(com.google.android.gms.drive.internal.OnContentsResponse paramOnContentsResponse)
  {
    // Byte code:
    //   0: invokestatic 22	android/os/Parcel:obtain	()Landroid/os/Parcel;
    //   3: astore_2
    //   4: invokestatic 22	android/os/Parcel:obtain	()Landroid/os/Parcel;
    //   7: astore_3
    //   8: aload_2
    //   9: ldc 24
    //   11: invokevirtual 28	android/os/Parcel:writeInterfaceToken	(Ljava/lang/String;)V
    //   14: aload_1
    //   15: ifnull +41 -> 56
    //   18: aload_2
    //   19: iconst_1
    //   20: invokevirtual 45	android/os/Parcel:writeInt	(I)V
    //   23: aload_1
    //   24: aload_2
    //   25: iconst_0
    //   26: invokevirtual 67	com/google/android/gms/drive/internal/OnContentsResponse:writeToParcel	(Landroid/os/Parcel;I)V
    //   29: aload_0
    //   30: getfield 15	fch:a	Landroid/os/IBinder;
    //   33: iconst_5
    //   34: aload_2
    //   35: aload_3
    //   36: iconst_0
    //   37: invokeinterface 34 5 0
    //   42: pop
    //   43: aload_3
    //   44: invokevirtual 37	android/os/Parcel:readException	()V
    //   47: aload_3
    //   48: invokevirtual 40	android/os/Parcel:recycle	()V
    //   51: aload_2
    //   52: invokevirtual 40	android/os/Parcel:recycle	()V
    //   55: return
    //   56: aload_2
    //   57: iconst_0
    //   58: invokevirtual 45	android/os/Parcel:writeInt	(I)V
    //   61: goto -32 -> 29
    //   64: astore_1
    //   65: aload_3
    //   66: invokevirtual 40	android/os/Parcel:recycle	()V
    //   69: aload_2
    //   70: invokevirtual 40	android/os/Parcel:recycle	()V
    //   73: aload_1
    //   74: athrow
    // Local variable table:
    //   start	length	slot	name	signature
    //   0	75	0	this	fch
    //   0	75	1	paramOnContentsResponse	com.google.android.gms.drive.internal.OnContentsResponse
    //   3	67	2	localParcel1	Parcel
    //   7	59	3	localParcel2	Parcel
    // Exception table:
    //   from	to	target	type
    //   8	14	64	finally
    //   18	29	64	finally
    //   29	47	64	finally
    //   56	61	64	finally
  }
  
  /* Error */
  public final void a(com.google.android.gms.drive.internal.OnDeviceUsagePreferenceResponse paramOnDeviceUsagePreferenceResponse)
  {
    // Byte code:
    //   0: invokestatic 22	android/os/Parcel:obtain	()Landroid/os/Parcel;
    //   3: astore_2
    //   4: invokestatic 22	android/os/Parcel:obtain	()Landroid/os/Parcel;
    //   7: astore_3
    //   8: aload_2
    //   9: ldc 24
    //   11: invokevirtual 28	android/os/Parcel:writeInterfaceToken	(Ljava/lang/String;)V
    //   14: aload_1
    //   15: ifnull +42 -> 57
    //   18: aload_2
    //   19: iconst_1
    //   20: invokevirtual 45	android/os/Parcel:writeInt	(I)V
    //   23: aload_1
    //   24: aload_2
    //   25: iconst_0
    //   26: invokevirtual 71	com/google/android/gms/drive/internal/OnDeviceUsagePreferenceResponse:writeToParcel	(Landroid/os/Parcel;I)V
    //   29: aload_0
    //   30: getfield 15	fch:a	Landroid/os/IBinder;
    //   33: bipush 14
    //   35: aload_2
    //   36: aload_3
    //   37: iconst_0
    //   38: invokeinterface 34 5 0
    //   43: pop
    //   44: aload_3
    //   45: invokevirtual 37	android/os/Parcel:readException	()V
    //   48: aload_3
    //   49: invokevirtual 40	android/os/Parcel:recycle	()V
    //   52: aload_2
    //   53: invokevirtual 40	android/os/Parcel:recycle	()V
    //   56: return
    //   57: aload_2
    //   58: iconst_0
    //   59: invokevirtual 45	android/os/Parcel:writeInt	(I)V
    //   62: goto -33 -> 29
    //   65: astore_1
    //   66: aload_3
    //   67: invokevirtual 40	android/os/Parcel:recycle	()V
    //   70: aload_2
    //   71: invokevirtual 40	android/os/Parcel:recycle	()V
    //   74: aload_1
    //   75: athrow
    // Local variable table:
    //   start	length	slot	name	signature
    //   0	76	0	this	fch
    //   0	76	1	paramOnDeviceUsagePreferenceResponse	com.google.android.gms.drive.internal.OnDeviceUsagePreferenceResponse
    //   3	68	2	localParcel1	Parcel
    //   7	60	3	localParcel2	Parcel
    // Exception table:
    //   from	to	target	type
    //   8	14	65	finally
    //   18	29	65	finally
    //   29	48	65	finally
    //   57	62	65	finally
  }
  
  /* Error */
  public final void a(com.google.android.gms.drive.internal.OnDownloadProgressResponse paramOnDownloadProgressResponse)
  {
    // Byte code:
    //   0: invokestatic 22	android/os/Parcel:obtain	()Landroid/os/Parcel;
    //   3: astore_2
    //   4: invokestatic 22	android/os/Parcel:obtain	()Landroid/os/Parcel;
    //   7: astore_3
    //   8: aload_2
    //   9: ldc 24
    //   11: invokevirtual 28	android/os/Parcel:writeInterfaceToken	(Ljava/lang/String;)V
    //   14: aload_1
    //   15: ifnull +41 -> 56
    //   18: aload_2
    //   19: iconst_1
    //   20: invokevirtual 45	android/os/Parcel:writeInt	(I)V
    //   23: aload_1
    //   24: aload_2
    //   25: iconst_0
    //   26: invokevirtual 75	com/google/android/gms/drive/internal/OnDownloadProgressResponse:writeToParcel	(Landroid/os/Parcel;I)V
    //   29: aload_0
    //   30: getfield 15	fch:a	Landroid/os/IBinder;
    //   33: iconst_1
    //   34: aload_2
    //   35: aload_3
    //   36: iconst_0
    //   37: invokeinterface 34 5 0
    //   42: pop
    //   43: aload_3
    //   44: invokevirtual 37	android/os/Parcel:readException	()V
    //   47: aload_3
    //   48: invokevirtual 40	android/os/Parcel:recycle	()V
    //   51: aload_2
    //   52: invokevirtual 40	android/os/Parcel:recycle	()V
    //   55: return
    //   56: aload_2
    //   57: iconst_0
    //   58: invokevirtual 45	android/os/Parcel:writeInt	(I)V
    //   61: goto -32 -> 29
    //   64: astore_1
    //   65: aload_3
    //   66: invokevirtual 40	android/os/Parcel:recycle	()V
    //   69: aload_2
    //   70: invokevirtual 40	android/os/Parcel:recycle	()V
    //   73: aload_1
    //   74: athrow
    // Local variable table:
    //   start	length	slot	name	signature
    //   0	75	0	this	fch
    //   0	75	1	paramOnDownloadProgressResponse	com.google.android.gms.drive.internal.OnDownloadProgressResponse
    //   3	67	2	localParcel1	Parcel
    //   7	59	3	localParcel2	Parcel
    // Exception table:
    //   from	to	target	type
    //   8	14	64	finally
    //   18	29	64	finally
    //   29	47	64	finally
    //   56	61	64	finally
  }
  
  /* Error */
  public final void a(com.google.android.gms.drive.internal.OnDriveIdResponse paramOnDriveIdResponse)
  {
    // Byte code:
    //   0: invokestatic 22	android/os/Parcel:obtain	()Landroid/os/Parcel;
    //   3: astore_2
    //   4: invokestatic 22	android/os/Parcel:obtain	()Landroid/os/Parcel;
    //   7: astore_3
    //   8: aload_2
    //   9: ldc 24
    //   11: invokevirtual 28	android/os/Parcel:writeInterfaceToken	(Ljava/lang/String;)V
    //   14: aload_1
    //   15: ifnull +41 -> 56
    //   18: aload_2
    //   19: iconst_1
    //   20: invokevirtual 45	android/os/Parcel:writeInt	(I)V
    //   23: aload_1
    //   24: aload_2
    //   25: iconst_0
    //   26: invokevirtual 79	com/google/android/gms/drive/internal/OnDriveIdResponse:writeToParcel	(Landroid/os/Parcel;I)V
    //   29: aload_0
    //   30: getfield 15	fch:a	Landroid/os/IBinder;
    //   33: iconst_3
    //   34: aload_2
    //   35: aload_3
    //   36: iconst_0
    //   37: invokeinterface 34 5 0
    //   42: pop
    //   43: aload_3
    //   44: invokevirtual 37	android/os/Parcel:readException	()V
    //   47: aload_3
    //   48: invokevirtual 40	android/os/Parcel:recycle	()V
    //   51: aload_2
    //   52: invokevirtual 40	android/os/Parcel:recycle	()V
    //   55: return
    //   56: aload_2
    //   57: iconst_0
    //   58: invokevirtual 45	android/os/Parcel:writeInt	(I)V
    //   61: goto -32 -> 29
    //   64: astore_1
    //   65: aload_3
    //   66: invokevirtual 40	android/os/Parcel:recycle	()V
    //   69: aload_2
    //   70: invokevirtual 40	android/os/Parcel:recycle	()V
    //   73: aload_1
    //   74: athrow
    // Local variable table:
    //   start	length	slot	name	signature
    //   0	75	0	this	fch
    //   0	75	1	paramOnDriveIdResponse	com.google.android.gms.drive.internal.OnDriveIdResponse
    //   3	67	2	localParcel1	Parcel
    //   7	59	3	localParcel2	Parcel
    // Exception table:
    //   from	to	target	type
    //   8	14	64	finally
    //   18	29	64	finally
    //   29	47	64	finally
    //   56	61	64	finally
  }
  
  /* Error */
  public final void a(com.google.android.gms.drive.internal.OnDrivePreferencesResponse paramOnDrivePreferencesResponse)
  {
    // Byte code:
    //   0: invokestatic 22	android/os/Parcel:obtain	()Landroid/os/Parcel;
    //   3: astore_2
    //   4: invokestatic 22	android/os/Parcel:obtain	()Landroid/os/Parcel;
    //   7: astore_3
    //   8: aload_2
    //   9: ldc 24
    //   11: invokevirtual 28	android/os/Parcel:writeInterfaceToken	(Ljava/lang/String;)V
    //   14: aload_1
    //   15: ifnull +42 -> 57
    //   18: aload_2
    //   19: iconst_1
    //   20: invokevirtual 45	android/os/Parcel:writeInt	(I)V
    //   23: aload_1
    //   24: aload_2
    //   25: iconst_0
    //   26: invokevirtual 83	com/google/android/gms/drive/internal/OnDrivePreferencesResponse:writeToParcel	(Landroid/os/Parcel;I)V
    //   29: aload_0
    //   30: getfield 15	fch:a	Landroid/os/IBinder;
    //   33: bipush 13
    //   35: aload_2
    //   36: aload_3
    //   37: iconst_0
    //   38: invokeinterface 34 5 0
    //   43: pop
    //   44: aload_3
    //   45: invokevirtual 37	android/os/Parcel:readException	()V
    //   48: aload_3
    //   49: invokevirtual 40	android/os/Parcel:recycle	()V
    //   52: aload_2
    //   53: invokevirtual 40	android/os/Parcel:recycle	()V
    //   56: return
    //   57: aload_2
    //   58: iconst_0
    //   59: invokevirtual 45	android/os/Parcel:writeInt	(I)V
    //   62: goto -33 -> 29
    //   65: astore_1
    //   66: aload_3
    //   67: invokevirtual 40	android/os/Parcel:recycle	()V
    //   70: aload_2
    //   71: invokevirtual 40	android/os/Parcel:recycle	()V
    //   74: aload_1
    //   75: athrow
    // Local variable table:
    //   start	length	slot	name	signature
    //   0	76	0	this	fch
    //   0	76	1	paramOnDrivePreferencesResponse	com.google.android.gms.drive.internal.OnDrivePreferencesResponse
    //   3	68	2	localParcel1	Parcel
    //   7	60	3	localParcel2	Parcel
    // Exception table:
    //   from	to	target	type
    //   8	14	65	finally
    //   18	29	65	finally
    //   29	48	65	finally
    //   57	62	65	finally
  }
  
  /* Error */
  public final void a(com.google.android.gms.drive.internal.OnFetchThumbnailResponse paramOnFetchThumbnailResponse)
  {
    // Byte code:
    //   0: invokestatic 22	android/os/Parcel:obtain	()Landroid/os/Parcel;
    //   3: astore_2
    //   4: invokestatic 22	android/os/Parcel:obtain	()Landroid/os/Parcel;
    //   7: astore_3
    //   8: aload_2
    //   9: ldc 24
    //   11: invokevirtual 28	android/os/Parcel:writeInterfaceToken	(Ljava/lang/String;)V
    //   14: aload_1
    //   15: ifnull +42 -> 57
    //   18: aload_2
    //   19: iconst_1
    //   20: invokevirtual 45	android/os/Parcel:writeInt	(I)V
    //   23: aload_1
    //   24: aload_2
    //   25: iconst_0
    //   26: invokevirtual 87	com/google/android/gms/drive/internal/OnFetchThumbnailResponse:writeToParcel	(Landroid/os/Parcel;I)V
    //   29: aload_0
    //   30: getfield 15	fch:a	Landroid/os/IBinder;
    //   33: bipush 16
    //   35: aload_2
    //   36: aload_3
    //   37: iconst_0
    //   38: invokeinterface 34 5 0
    //   43: pop
    //   44: aload_3
    //   45: invokevirtual 37	android/os/Parcel:readException	()V
    //   48: aload_3
    //   49: invokevirtual 40	android/os/Parcel:recycle	()V
    //   52: aload_2
    //   53: invokevirtual 40	android/os/Parcel:recycle	()V
    //   56: return
    //   57: aload_2
    //   58: iconst_0
    //   59: invokevirtual 45	android/os/Parcel:writeInt	(I)V
    //   62: goto -33 -> 29
    //   65: astore_1
    //   66: aload_3
    //   67: invokevirtual 40	android/os/Parcel:recycle	()V
    //   70: aload_2
    //   71: invokevirtual 40	android/os/Parcel:recycle	()V
    //   74: aload_1
    //   75: athrow
    // Local variable table:
    //   start	length	slot	name	signature
    //   0	76	0	this	fch
    //   0	76	1	paramOnFetchThumbnailResponse	com.google.android.gms.drive.internal.OnFetchThumbnailResponse
    //   3	68	2	localParcel1	Parcel
    //   7	60	3	localParcel2	Parcel
    // Exception table:
    //   from	to	target	type
    //   8	14	65	finally
    //   18	29	65	finally
    //   29	48	65	finally
    //   57	62	65	finally
  }
  
  /* Error */
  public final void a(com.google.android.gms.drive.internal.OnListEntriesResponse paramOnListEntriesResponse)
  {
    // Byte code:
    //   0: invokestatic 22	android/os/Parcel:obtain	()Landroid/os/Parcel;
    //   3: astore_2
    //   4: invokestatic 22	android/os/Parcel:obtain	()Landroid/os/Parcel;
    //   7: astore_3
    //   8: aload_2
    //   9: ldc 24
    //   11: invokevirtual 28	android/os/Parcel:writeInterfaceToken	(Ljava/lang/String;)V
    //   14: aload_1
    //   15: ifnull +41 -> 56
    //   18: aload_2
    //   19: iconst_1
    //   20: invokevirtual 45	android/os/Parcel:writeInt	(I)V
    //   23: aload_1
    //   24: aload_2
    //   25: iconst_0
    //   26: invokevirtual 91	com/google/android/gms/drive/internal/OnListEntriesResponse:writeToParcel	(Landroid/os/Parcel;I)V
    //   29: aload_0
    //   30: getfield 15	fch:a	Landroid/os/IBinder;
    //   33: iconst_2
    //   34: aload_2
    //   35: aload_3
    //   36: iconst_0
    //   37: invokeinterface 34 5 0
    //   42: pop
    //   43: aload_3
    //   44: invokevirtual 37	android/os/Parcel:readException	()V
    //   47: aload_3
    //   48: invokevirtual 40	android/os/Parcel:recycle	()V
    //   51: aload_2
    //   52: invokevirtual 40	android/os/Parcel:recycle	()V
    //   55: return
    //   56: aload_2
    //   57: iconst_0
    //   58: invokevirtual 45	android/os/Parcel:writeInt	(I)V
    //   61: goto -32 -> 29
    //   64: astore_1
    //   65: aload_3
    //   66: invokevirtual 40	android/os/Parcel:recycle	()V
    //   69: aload_2
    //   70: invokevirtual 40	android/os/Parcel:recycle	()V
    //   73: aload_1
    //   74: athrow
    // Local variable table:
    //   start	length	slot	name	signature
    //   0	75	0	this	fch
    //   0	75	1	paramOnListEntriesResponse	com.google.android.gms.drive.internal.OnListEntriesResponse
    //   3	67	2	localParcel1	Parcel
    //   7	59	3	localParcel2	Parcel
    // Exception table:
    //   from	to	target	type
    //   8	14	64	finally
    //   18	29	64	finally
    //   29	47	64	finally
    //   56	61	64	finally
  }
  
  /* Error */
  public final void a(com.google.android.gms.drive.internal.OnListParentsResponse paramOnListParentsResponse)
  {
    // Byte code:
    //   0: invokestatic 22	android/os/Parcel:obtain	()Landroid/os/Parcel;
    //   3: astore_2
    //   4: invokestatic 22	android/os/Parcel:obtain	()Landroid/os/Parcel;
    //   7: astore_3
    //   8: aload_2
    //   9: ldc 24
    //   11: invokevirtual 28	android/os/Parcel:writeInterfaceToken	(Ljava/lang/String;)V
    //   14: aload_1
    //   15: ifnull +42 -> 57
    //   18: aload_2
    //   19: iconst_1
    //   20: invokevirtual 45	android/os/Parcel:writeInt	(I)V
    //   23: aload_1
    //   24: aload_2
    //   25: iconst_0
    //   26: invokevirtual 95	com/google/android/gms/drive/internal/OnListParentsResponse:writeToParcel	(Landroid/os/Parcel;I)V
    //   29: aload_0
    //   30: getfield 15	fch:a	Landroid/os/IBinder;
    //   33: bipush 8
    //   35: aload_2
    //   36: aload_3
    //   37: iconst_0
    //   38: invokeinterface 34 5 0
    //   43: pop
    //   44: aload_3
    //   45: invokevirtual 37	android/os/Parcel:readException	()V
    //   48: aload_3
    //   49: invokevirtual 40	android/os/Parcel:recycle	()V
    //   52: aload_2
    //   53: invokevirtual 40	android/os/Parcel:recycle	()V
    //   56: return
    //   57: aload_2
    //   58: iconst_0
    //   59: invokevirtual 45	android/os/Parcel:writeInt	(I)V
    //   62: goto -33 -> 29
    //   65: astore_1
    //   66: aload_3
    //   67: invokevirtual 40	android/os/Parcel:recycle	()V
    //   70: aload_2
    //   71: invokevirtual 40	android/os/Parcel:recycle	()V
    //   74: aload_1
    //   75: athrow
    // Local variable table:
    //   start	length	slot	name	signature
    //   0	76	0	this	fch
    //   0	76	1	paramOnListParentsResponse	com.google.android.gms.drive.internal.OnListParentsResponse
    //   3	68	2	localParcel1	Parcel
    //   7	60	3	localParcel2	Parcel
    // Exception table:
    //   from	to	target	type
    //   8	14	65	finally
    //   18	29	65	finally
    //   29	48	65	finally
    //   57	62	65	finally
  }
  
  public final void a(OnLoadRealtimeResponse paramOnLoadRealtimeResponse, fip paramfip)
  {
    Parcel localParcel1 = Parcel.obtain();
    Parcel localParcel2 = Parcel.obtain();
    for (;;)
    {
      try
      {
        localParcel1.writeInterfaceToken("com.google.android.gms.drive.internal.IDriveServiceCallbacks");
        if (paramOnLoadRealtimeResponse != null)
        {
          localParcel1.writeInt(1);
          paramOnLoadRealtimeResponse.writeToParcel(localParcel1, 0);
          if (paramfip != null)
          {
            paramOnLoadRealtimeResponse = paramfip.asBinder();
            localParcel1.writeStrongBinder(paramOnLoadRealtimeResponse);
            a.transact(11, localParcel1, localParcel2, 0);
            localParcel2.readException();
          }
        }
        else
        {
          localParcel1.writeInt(0);
          continue;
        }
        paramOnLoadRealtimeResponse = null;
      }
      finally
      {
        localParcel2.recycle();
        localParcel1.recycle();
      }
    }
  }
  
  /* Error */
  public final void a(com.google.android.gms.drive.internal.OnMetadataResponse paramOnMetadataResponse)
  {
    // Byte code:
    //   0: invokestatic 22	android/os/Parcel:obtain	()Landroid/os/Parcel;
    //   3: astore_2
    //   4: invokestatic 22	android/os/Parcel:obtain	()Landroid/os/Parcel;
    //   7: astore_3
    //   8: aload_2
    //   9: ldc 24
    //   11: invokevirtual 28	android/os/Parcel:writeInterfaceToken	(Ljava/lang/String;)V
    //   14: aload_1
    //   15: ifnull +41 -> 56
    //   18: aload_2
    //   19: iconst_1
    //   20: invokevirtual 45	android/os/Parcel:writeInt	(I)V
    //   23: aload_1
    //   24: aload_2
    //   25: iconst_0
    //   26: invokevirtual 112	com/google/android/gms/drive/internal/OnMetadataResponse:writeToParcel	(Landroid/os/Parcel;I)V
    //   29: aload_0
    //   30: getfield 15	fch:a	Landroid/os/IBinder;
    //   33: iconst_4
    //   34: aload_2
    //   35: aload_3
    //   36: iconst_0
    //   37: invokeinterface 34 5 0
    //   42: pop
    //   43: aload_3
    //   44: invokevirtual 37	android/os/Parcel:readException	()V
    //   47: aload_3
    //   48: invokevirtual 40	android/os/Parcel:recycle	()V
    //   51: aload_2
    //   52: invokevirtual 40	android/os/Parcel:recycle	()V
    //   55: return
    //   56: aload_2
    //   57: iconst_0
    //   58: invokevirtual 45	android/os/Parcel:writeInt	(I)V
    //   61: goto -32 -> 29
    //   64: astore_1
    //   65: aload_3
    //   66: invokevirtual 40	android/os/Parcel:recycle	()V
    //   69: aload_2
    //   70: invokevirtual 40	android/os/Parcel:recycle	()V
    //   73: aload_1
    //   74: athrow
    // Local variable table:
    //   start	length	slot	name	signature
    //   0	75	0	this	fch
    //   0	75	1	paramOnMetadataResponse	com.google.android.gms.drive.internal.OnMetadataResponse
    //   3	67	2	localParcel1	Parcel
    //   7	59	3	localParcel2	Parcel
    // Exception table:
    //   from	to	target	type
    //   8	14	64	finally
    //   18	29	64	finally
    //   29	47	64	finally
    //   56	61	64	finally
  }
  
  /* Error */
  public final void a(com.google.android.gms.drive.internal.OnResourceIdSetResponse paramOnResourceIdSetResponse)
  {
    // Byte code:
    //   0: invokestatic 22	android/os/Parcel:obtain	()Landroid/os/Parcel;
    //   3: astore_2
    //   4: invokestatic 22	android/os/Parcel:obtain	()Landroid/os/Parcel;
    //   7: astore_3
    //   8: aload_2
    //   9: ldc 24
    //   11: invokevirtual 28	android/os/Parcel:writeInterfaceToken	(Ljava/lang/String;)V
    //   14: aload_1
    //   15: ifnull +42 -> 57
    //   18: aload_2
    //   19: iconst_1
    //   20: invokevirtual 45	android/os/Parcel:writeInt	(I)V
    //   23: aload_1
    //   24: aload_2
    //   25: iconst_0
    //   26: invokevirtual 116	com/google/android/gms/drive/internal/OnResourceIdSetResponse:writeToParcel	(Landroid/os/Parcel;I)V
    //   29: aload_0
    //   30: getfield 15	fch:a	Landroid/os/IBinder;
    //   33: bipush 12
    //   35: aload_2
    //   36: aload_3
    //   37: iconst_0
    //   38: invokeinterface 34 5 0
    //   43: pop
    //   44: aload_3
    //   45: invokevirtual 37	android/os/Parcel:readException	()V
    //   48: aload_3
    //   49: invokevirtual 40	android/os/Parcel:recycle	()V
    //   52: aload_2
    //   53: invokevirtual 40	android/os/Parcel:recycle	()V
    //   56: return
    //   57: aload_2
    //   58: iconst_0
    //   59: invokevirtual 45	android/os/Parcel:writeInt	(I)V
    //   62: goto -33 -> 29
    //   65: astore_1
    //   66: aload_3
    //   67: invokevirtual 40	android/os/Parcel:recycle	()V
    //   70: aload_2
    //   71: invokevirtual 40	android/os/Parcel:recycle	()V
    //   74: aload_1
    //   75: athrow
    // Local variable table:
    //   start	length	slot	name	signature
    //   0	76	0	this	fch
    //   0	76	1	paramOnResourceIdSetResponse	com.google.android.gms.drive.internal.OnResourceIdSetResponse
    //   3	68	2	localParcel1	Parcel
    //   7	60	3	localParcel2	Parcel
    // Exception table:
    //   from	to	target	type
    //   8	14	65	finally
    //   18	29	65	finally
    //   29	48	65	finally
    //   57	62	65	finally
  }
  
  /* Error */
  public final void a(com.google.android.gms.drive.internal.OnSyncMoreResponse paramOnSyncMoreResponse)
  {
    // Byte code:
    //   0: invokestatic 22	android/os/Parcel:obtain	()Landroid/os/Parcel;
    //   3: astore_2
    //   4: invokestatic 22	android/os/Parcel:obtain	()Landroid/os/Parcel;
    //   7: astore_3
    //   8: aload_2
    //   9: ldc 24
    //   11: invokevirtual 28	android/os/Parcel:writeInterfaceToken	(Ljava/lang/String;)V
    //   14: aload_1
    //   15: ifnull +42 -> 57
    //   18: aload_2
    //   19: iconst_1
    //   20: invokevirtual 45	android/os/Parcel:writeInt	(I)V
    //   23: aload_1
    //   24: aload_2
    //   25: iconst_0
    //   26: invokevirtual 120	com/google/android/gms/drive/internal/OnSyncMoreResponse:writeToParcel	(Landroid/os/Parcel;I)V
    //   29: aload_0
    //   30: getfield 15	fch:a	Landroid/os/IBinder;
    //   33: bipush 9
    //   35: aload_2
    //   36: aload_3
    //   37: iconst_0
    //   38: invokeinterface 34 5 0
    //   43: pop
    //   44: aload_3
    //   45: invokevirtual 37	android/os/Parcel:readException	()V
    //   48: aload_3
    //   49: invokevirtual 40	android/os/Parcel:recycle	()V
    //   52: aload_2
    //   53: invokevirtual 40	android/os/Parcel:recycle	()V
    //   56: return
    //   57: aload_2
    //   58: iconst_0
    //   59: invokevirtual 45	android/os/Parcel:writeInt	(I)V
    //   62: goto -33 -> 29
    //   65: astore_1
    //   66: aload_3
    //   67: invokevirtual 40	android/os/Parcel:recycle	()V
    //   70: aload_2
    //   71: invokevirtual 40	android/os/Parcel:recycle	()V
    //   74: aload_1
    //   75: athrow
    // Local variable table:
    //   start	length	slot	name	signature
    //   0	76	0	this	fch
    //   0	76	1	paramOnSyncMoreResponse	com.google.android.gms.drive.internal.OnSyncMoreResponse
    //   3	68	2	localParcel1	Parcel
    //   7	60	3	localParcel2	Parcel
    // Exception table:
    //   from	to	target	type
    //   8	14	65	finally
    //   18	29	65	finally
    //   29	48	65	finally
    //   57	62	65	finally
  }
  
  public final void a(boolean paramBoolean)
  {
    int i = 0;
    Parcel localParcel1 = Parcel.obtain();
    Parcel localParcel2 = Parcel.obtain();
    try
    {
      localParcel1.writeInterfaceToken("com.google.android.gms.drive.internal.IDriveServiceCallbacks");
      if (paramBoolean) {
        i = 1;
      }
      localParcel1.writeInt(i);
      a.transact(15, localParcel1, localParcel2, 0);
      localParcel2.readException();
      return;
    }
    finally
    {
      localParcel2.recycle();
      localParcel1.recycle();
    }
  }
  
  public final IBinder asBinder()
  {
    return a;
  }
}

/* Location:
 * Qualified Name:     fch
 * Java Class Version: 6 (50.0)
 * JD-Core Version:    0.7.1
 */