import android.os.IBinder;
import android.os.Parcel;
import com.google.android.gms.common.data.DataHolder;
import com.google.android.gms.drive.DriveId;
import com.google.android.gms.drive.realtime.internal.BeginCompoundOperationRequest;
import com.google.android.gms.drive.realtime.internal.EndCompoundOperationRequest;
import com.google.android.gms.drive.realtime.internal.ParcelableIndexReference;

public final class fir
  implements fip
{
  private IBinder a;
  
  public fir(IBinder paramIBinder)
  {
    a = paramIBinder;
  }
  
  public final void a()
  {
    Parcel localParcel1 = Parcel.obtain();
    Parcel localParcel2 = Parcel.obtain();
    try
    {
      localParcel1.writeInterfaceToken("com.google.android.gms.drive.realtime.internal.IRealtimeService");
      a.transact(44, localParcel1, localParcel2, 0);
      localParcel2.readException();
      return;
    }
    finally
    {
      localParcel2.recycle();
      localParcel1.recycle();
    }
  }
  
  /* Error */
  public final void a(int paramInt, fig paramfig)
  {
    // Byte code:
    //   0: invokestatic 22	android/os/Parcel:obtain	()Landroid/os/Parcel;
    //   3: astore_3
    //   4: invokestatic 22	android/os/Parcel:obtain	()Landroid/os/Parcel;
    //   7: astore 4
    //   9: aload_3
    //   10: ldc 24
    //   12: invokevirtual 28	android/os/Parcel:writeInterfaceToken	(Ljava/lang/String;)V
    //   15: aload_3
    //   16: iload_1
    //   17: invokevirtual 45	android/os/Parcel:writeInt	(I)V
    //   20: aload_2
    //   21: ifnull +46 -> 67
    //   24: aload_2
    //   25: invokeinterface 51 1 0
    //   30: astore_2
    //   31: aload_3
    //   32: aload_2
    //   33: invokevirtual 54	android/os/Parcel:writeStrongBinder	(Landroid/os/IBinder;)V
    //   36: aload_0
    //   37: getfield 15	fir:a	Landroid/os/IBinder;
    //   40: bipush 30
    //   42: aload_3
    //   43: aload 4
    //   45: iconst_0
    //   46: invokeinterface 34 5 0
    //   51: pop
    //   52: aload 4
    //   54: invokevirtual 37	android/os/Parcel:readException	()V
    //   57: aload 4
    //   59: invokevirtual 40	android/os/Parcel:recycle	()V
    //   62: aload_3
    //   63: invokevirtual 40	android/os/Parcel:recycle	()V
    //   66: return
    //   67: aconst_null
    //   68: astore_2
    //   69: goto -38 -> 31
    //   72: astore_2
    //   73: aload 4
    //   75: invokevirtual 40	android/os/Parcel:recycle	()V
    //   78: aload_3
    //   79: invokevirtual 40	android/os/Parcel:recycle	()V
    //   82: aload_2
    //   83: athrow
    // Local variable table:
    //   start	length	slot	name	signature
    //   0	84	0	this	fir
    //   0	84	1	paramInt	int
    //   0	84	2	paramfig	fig
    //   3	76	3	localParcel1	Parcel
    //   7	67	4	localParcel2	Parcel
    // Exception table:
    //   from	to	target	type
    //   9	20	72	finally
    //   24	31	72	finally
    //   31	57	72	finally
  }
  
  /* Error */
  public final void a(int paramInt, fiv paramfiv)
  {
    // Byte code:
    //   0: invokestatic 22	android/os/Parcel:obtain	()Landroid/os/Parcel;
    //   3: astore_3
    //   4: invokestatic 22	android/os/Parcel:obtain	()Landroid/os/Parcel;
    //   7: astore 4
    //   9: aload_3
    //   10: ldc 24
    //   12: invokevirtual 28	android/os/Parcel:writeInterfaceToken	(Ljava/lang/String;)V
    //   15: aload_3
    //   16: iload_1
    //   17: invokevirtual 45	android/os/Parcel:writeInt	(I)V
    //   20: aload_2
    //   21: ifnull +46 -> 67
    //   24: aload_2
    //   25: invokeinterface 58 1 0
    //   30: astore_2
    //   31: aload_3
    //   32: aload_2
    //   33: invokevirtual 54	android/os/Parcel:writeStrongBinder	(Landroid/os/IBinder;)V
    //   36: aload_0
    //   37: getfield 15	fir:a	Landroid/os/IBinder;
    //   40: bipush 50
    //   42: aload_3
    //   43: aload 4
    //   45: iconst_0
    //   46: invokeinterface 34 5 0
    //   51: pop
    //   52: aload 4
    //   54: invokevirtual 37	android/os/Parcel:readException	()V
    //   57: aload 4
    //   59: invokevirtual 40	android/os/Parcel:recycle	()V
    //   62: aload_3
    //   63: invokevirtual 40	android/os/Parcel:recycle	()V
    //   66: return
    //   67: aconst_null
    //   68: astore_2
    //   69: goto -38 -> 31
    //   72: astore_2
    //   73: aload 4
    //   75: invokevirtual 40	android/os/Parcel:recycle	()V
    //   78: aload_3
    //   79: invokevirtual 40	android/os/Parcel:recycle	()V
    //   82: aload_2
    //   83: athrow
    // Local variable table:
    //   start	length	slot	name	signature
    //   0	84	0	this	fir
    //   0	84	1	paramInt	int
    //   0	84	2	paramfiv	fiv
    //   3	76	3	localParcel1	Parcel
    //   7	67	4	localParcel2	Parcel
    // Exception table:
    //   from	to	target	type
    //   9	20	72	finally
    //   24	31	72	finally
    //   31	57	72	finally
  }
  
  public final void a(DriveId paramDriveId, fiv paramfiv)
  {
    Parcel localParcel1 = Parcel.obtain();
    Parcel localParcel2 = Parcel.obtain();
    for (;;)
    {
      try
      {
        localParcel1.writeInterfaceToken("com.google.android.gms.drive.realtime.internal.IRealtimeService");
        if (paramDriveId != null)
        {
          localParcel1.writeInt(1);
          paramDriveId.writeToParcel(localParcel1, 0);
          if (paramfiv != null)
          {
            paramDriveId = paramfiv.asBinder();
            localParcel1.writeStrongBinder(paramDriveId);
            a.transact(48, localParcel1, localParcel2, 0);
            localParcel2.readException();
          }
        }
        else
        {
          localParcel1.writeInt(0);
          continue;
        }
        paramDriveId = null;
      }
      finally
      {
        localParcel2.recycle();
        localParcel1.recycle();
      }
    }
  }
  
  public final void a(BeginCompoundOperationRequest paramBeginCompoundOperationRequest, fiv paramfiv)
  {
    Parcel localParcel1 = Parcel.obtain();
    Parcel localParcel2 = Parcel.obtain();
    for (;;)
    {
      try
      {
        localParcel1.writeInterfaceToken("com.google.android.gms.drive.realtime.internal.IRealtimeService");
        if (paramBeginCompoundOperationRequest != null)
        {
          localParcel1.writeInt(1);
          paramBeginCompoundOperationRequest.writeToParcel(localParcel1, 0);
          if (paramfiv != null)
          {
            paramBeginCompoundOperationRequest = paramfiv.asBinder();
            localParcel1.writeStrongBinder(paramBeginCompoundOperationRequest);
            a.transact(18, localParcel1, localParcel2, 0);
            localParcel2.readException();
          }
        }
        else
        {
          localParcel1.writeInt(0);
          continue;
        }
        paramBeginCompoundOperationRequest = null;
      }
      finally
      {
        localParcel2.recycle();
        localParcel1.recycle();
      }
    }
  }
  
  public final void a(EndCompoundOperationRequest paramEndCompoundOperationRequest, fig paramfig)
  {
    Parcel localParcel1 = Parcel.obtain();
    Parcel localParcel2 = Parcel.obtain();
    for (;;)
    {
      try
      {
        localParcel1.writeInterfaceToken("com.google.android.gms.drive.realtime.internal.IRealtimeService");
        if (paramEndCompoundOperationRequest != null)
        {
          localParcel1.writeInt(1);
          paramEndCompoundOperationRequest.writeToParcel(localParcel1, 0);
          if (paramfig != null)
          {
            paramEndCompoundOperationRequest = paramfig.asBinder();
            localParcel1.writeStrongBinder(paramEndCompoundOperationRequest);
            a.transact(41, localParcel1, localParcel2, 0);
            localParcel2.readException();
          }
        }
        else
        {
          localParcel1.writeInt(0);
          continue;
        }
        paramEndCompoundOperationRequest = null;
      }
      finally
      {
        localParcel2.recycle();
        localParcel1.recycle();
      }
    }
  }
  
  public final void a(EndCompoundOperationRequest paramEndCompoundOperationRequest, fiv paramfiv)
  {
    Parcel localParcel1 = Parcel.obtain();
    Parcel localParcel2 = Parcel.obtain();
    for (;;)
    {
      try
      {
        localParcel1.writeInterfaceToken("com.google.android.gms.drive.realtime.internal.IRealtimeService");
        if (paramEndCompoundOperationRequest != null)
        {
          localParcel1.writeInt(1);
          paramEndCompoundOperationRequest.writeToParcel(localParcel1, 0);
          if (paramfiv != null)
          {
            paramEndCompoundOperationRequest = paramfiv.asBinder();
            localParcel1.writeStrongBinder(paramEndCompoundOperationRequest);
            a.transact(19, localParcel1, localParcel2, 0);
            localParcel2.readException();
          }
        }
        else
        {
          localParcel1.writeInt(0);
          continue;
        }
        paramEndCompoundOperationRequest = null;
      }
      finally
      {
        localParcel2.recycle();
        localParcel1.recycle();
      }
    }
  }
  
  public final void a(ParcelableIndexReference paramParcelableIndexReference, fis paramfis)
  {
    Parcel localParcel1 = Parcel.obtain();
    Parcel localParcel2 = Parcel.obtain();
    for (;;)
    {
      try
      {
        localParcel1.writeInterfaceToken("com.google.android.gms.drive.realtime.internal.IRealtimeService");
        if (paramParcelableIndexReference != null)
        {
          localParcel1.writeInt(1);
          paramParcelableIndexReference.writeToParcel(localParcel1, 0);
          if (paramfis != null)
          {
            paramParcelableIndexReference = paramfis.asBinder();
            localParcel1.writeStrongBinder(paramParcelableIndexReference);
            a.transact(26, localParcel1, localParcel2, 0);
            localParcel2.readException();
          }
        }
        else
        {
          localParcel1.writeInt(0);
          continue;
        }
        paramParcelableIndexReference = null;
      }
      finally
      {
        localParcel2.recycle();
        localParcel1.recycle();
      }
    }
  }
  
  /* Error */
  public final void a(fhl paramfhl)
  {
    // Byte code:
    //   0: invokestatic 22	android/os/Parcel:obtain	()Landroid/os/Parcel;
    //   3: astore_2
    //   4: invokestatic 22	android/os/Parcel:obtain	()Landroid/os/Parcel;
    //   7: astore_3
    //   8: aload_2
    //   9: ldc 24
    //   11: invokevirtual 28	android/os/Parcel:writeInterfaceToken	(Ljava/lang/String;)V
    //   14: aload_1
    //   15: ifnull +42 -> 57
    //   18: aload_1
    //   19: invokeinterface 85 1 0
    //   24: astore_1
    //   25: aload_2
    //   26: aload_1
    //   27: invokevirtual 54	android/os/Parcel:writeStrongBinder	(Landroid/os/IBinder;)V
    //   30: aload_0
    //   31: getfield 15	fir:a	Landroid/os/IBinder;
    //   34: iconst_2
    //   35: aload_2
    //   36: aload_3
    //   37: iconst_0
    //   38: invokeinterface 34 5 0
    //   43: pop
    //   44: aload_3
    //   45: invokevirtual 37	android/os/Parcel:readException	()V
    //   48: aload_3
    //   49: invokevirtual 40	android/os/Parcel:recycle	()V
    //   52: aload_2
    //   53: invokevirtual 40	android/os/Parcel:recycle	()V
    //   56: return
    //   57: aconst_null
    //   58: astore_1
    //   59: goto -34 -> 25
    //   62: astore_1
    //   63: aload_3
    //   64: invokevirtual 40	android/os/Parcel:recycle	()V
    //   67: aload_2
    //   68: invokevirtual 40	android/os/Parcel:recycle	()V
    //   71: aload_1
    //   72: athrow
    // Local variable table:
    //   start	length	slot	name	signature
    //   0	73	0	this	fir
    //   0	73	1	paramfhl	fhl
    //   3	65	2	localParcel1	Parcel
    //   7	57	3	localParcel2	Parcel
    // Exception table:
    //   from	to	target	type
    //   8	14	62	finally
    //   18	25	62	finally
    //   25	48	62	finally
  }
  
  /* Error */
  public final void a(fho paramfho)
  {
    // Byte code:
    //   0: invokestatic 22	android/os/Parcel:obtain	()Landroid/os/Parcel;
    //   3: astore_2
    //   4: invokestatic 22	android/os/Parcel:obtain	()Landroid/os/Parcel;
    //   7: astore_3
    //   8: aload_2
    //   9: ldc 24
    //   11: invokevirtual 28	android/os/Parcel:writeInterfaceToken	(Ljava/lang/String;)V
    //   14: aload_1
    //   15: ifnull +43 -> 58
    //   18: aload_1
    //   19: invokeinterface 89 1 0
    //   24: astore_1
    //   25: aload_2
    //   26: aload_1
    //   27: invokevirtual 54	android/os/Parcel:writeStrongBinder	(Landroid/os/IBinder;)V
    //   30: aload_0
    //   31: getfield 15	fir:a	Landroid/os/IBinder;
    //   34: bipush 32
    //   36: aload_2
    //   37: aload_3
    //   38: iconst_0
    //   39: invokeinterface 34 5 0
    //   44: pop
    //   45: aload_3
    //   46: invokevirtual 37	android/os/Parcel:readException	()V
    //   49: aload_3
    //   50: invokevirtual 40	android/os/Parcel:recycle	()V
    //   53: aload_2
    //   54: invokevirtual 40	android/os/Parcel:recycle	()V
    //   57: return
    //   58: aconst_null
    //   59: astore_1
    //   60: goto -35 -> 25
    //   63: astore_1
    //   64: aload_3
    //   65: invokevirtual 40	android/os/Parcel:recycle	()V
    //   68: aload_2
    //   69: invokevirtual 40	android/os/Parcel:recycle	()V
    //   72: aload_1
    //   73: athrow
    // Local variable table:
    //   start	length	slot	name	signature
    //   0	74	0	this	fir
    //   0	74	1	paramfho	fho
    //   3	66	2	localParcel1	Parcel
    //   7	58	3	localParcel2	Parcel
    // Exception table:
    //   from	to	target	type
    //   8	14	63	finally
    //   18	25	63	finally
    //   25	49	63	finally
  }
  
  /* Error */
  public final void a(fhr paramfhr)
  {
    // Byte code:
    //   0: invokestatic 22	android/os/Parcel:obtain	()Landroid/os/Parcel;
    //   3: astore_2
    //   4: invokestatic 22	android/os/Parcel:obtain	()Landroid/os/Parcel;
    //   7: astore_3
    //   8: aload_2
    //   9: ldc 24
    //   11: invokevirtual 28	android/os/Parcel:writeInterfaceToken	(Ljava/lang/String;)V
    //   14: aload_1
    //   15: ifnull +43 -> 58
    //   18: aload_1
    //   19: invokeinterface 93 1 0
    //   24: astore_1
    //   25: aload_2
    //   26: aload_1
    //   27: invokevirtual 54	android/os/Parcel:writeStrongBinder	(Landroid/os/IBinder;)V
    //   30: aload_0
    //   31: getfield 15	fir:a	Landroid/os/IBinder;
    //   34: bipush 31
    //   36: aload_2
    //   37: aload_3
    //   38: iconst_0
    //   39: invokeinterface 34 5 0
    //   44: pop
    //   45: aload_3
    //   46: invokevirtual 37	android/os/Parcel:readException	()V
    //   49: aload_3
    //   50: invokevirtual 40	android/os/Parcel:recycle	()V
    //   53: aload_2
    //   54: invokevirtual 40	android/os/Parcel:recycle	()V
    //   57: return
    //   58: aconst_null
    //   59: astore_1
    //   60: goto -35 -> 25
    //   63: astore_1
    //   64: aload_3
    //   65: invokevirtual 40	android/os/Parcel:recycle	()V
    //   68: aload_2
    //   69: invokevirtual 40	android/os/Parcel:recycle	()V
    //   72: aload_1
    //   73: athrow
    // Local variable table:
    //   start	length	slot	name	signature
    //   0	74	0	this	fir
    //   0	74	1	paramfhr	fhr
    //   3	66	2	localParcel1	Parcel
    //   7	58	3	localParcel2	Parcel
    // Exception table:
    //   from	to	target	type
    //   8	14	63	finally
    //   18	25	63	finally
    //   25	49	63	finally
  }
  
  /* Error */
  public final void a(fia paramfia)
  {
    // Byte code:
    //   0: invokestatic 22	android/os/Parcel:obtain	()Landroid/os/Parcel;
    //   3: astore_2
    //   4: invokestatic 22	android/os/Parcel:obtain	()Landroid/os/Parcel;
    //   7: astore_3
    //   8: aload_2
    //   9: ldc 24
    //   11: invokevirtual 28	android/os/Parcel:writeInterfaceToken	(Ljava/lang/String;)V
    //   14: aload_1
    //   15: ifnull +43 -> 58
    //   18: aload_1
    //   19: invokeinterface 97 1 0
    //   24: astore_1
    //   25: aload_2
    //   26: aload_1
    //   27: invokevirtual 54	android/os/Parcel:writeStrongBinder	(Landroid/os/IBinder;)V
    //   30: aload_0
    //   31: getfield 15	fir:a	Landroid/os/IBinder;
    //   34: bipush 36
    //   36: aload_2
    //   37: aload_3
    //   38: iconst_0
    //   39: invokeinterface 34 5 0
    //   44: pop
    //   45: aload_3
    //   46: invokevirtual 37	android/os/Parcel:readException	()V
    //   49: aload_3
    //   50: invokevirtual 40	android/os/Parcel:recycle	()V
    //   53: aload_2
    //   54: invokevirtual 40	android/os/Parcel:recycle	()V
    //   57: return
    //   58: aconst_null
    //   59: astore_1
    //   60: goto -35 -> 25
    //   63: astore_1
    //   64: aload_3
    //   65: invokevirtual 40	android/os/Parcel:recycle	()V
    //   68: aload_2
    //   69: invokevirtual 40	android/os/Parcel:recycle	()V
    //   72: aload_1
    //   73: athrow
    // Local variable table:
    //   start	length	slot	name	signature
    //   0	74	0	this	fir
    //   0	74	1	paramfia	fia
    //   3	66	2	localParcel1	Parcel
    //   7	58	3	localParcel2	Parcel
    // Exception table:
    //   from	to	target	type
    //   8	14	63	finally
    //   18	25	63	finally
    //   25	49	63	finally
  }
  
  /* Error */
  public final void a(fid paramfid)
  {
    // Byte code:
    //   0: invokestatic 22	android/os/Parcel:obtain	()Landroid/os/Parcel;
    //   3: astore_2
    //   4: invokestatic 22	android/os/Parcel:obtain	()Landroid/os/Parcel;
    //   7: astore_3
    //   8: aload_2
    //   9: ldc 24
    //   11: invokevirtual 28	android/os/Parcel:writeInterfaceToken	(Ljava/lang/String;)V
    //   14: aload_1
    //   15: ifnull +43 -> 58
    //   18: aload_1
    //   19: invokeinterface 101 1 0
    //   24: astore_1
    //   25: aload_2
    //   26: aload_1
    //   27: invokevirtual 54	android/os/Parcel:writeStrongBinder	(Landroid/os/IBinder;)V
    //   30: aload_0
    //   31: getfield 15	fir:a	Landroid/os/IBinder;
    //   34: bipush 34
    //   36: aload_2
    //   37: aload_3
    //   38: iconst_0
    //   39: invokeinterface 34 5 0
    //   44: pop
    //   45: aload_3
    //   46: invokevirtual 37	android/os/Parcel:readException	()V
    //   49: aload_3
    //   50: invokevirtual 40	android/os/Parcel:recycle	()V
    //   53: aload_2
    //   54: invokevirtual 40	android/os/Parcel:recycle	()V
    //   57: return
    //   58: aconst_null
    //   59: astore_1
    //   60: goto -35 -> 25
    //   63: astore_1
    //   64: aload_3
    //   65: invokevirtual 40	android/os/Parcel:recycle	()V
    //   68: aload_2
    //   69: invokevirtual 40	android/os/Parcel:recycle	()V
    //   72: aload_1
    //   73: athrow
    // Local variable table:
    //   start	length	slot	name	signature
    //   0	74	0	this	fir
    //   0	74	1	paramfid	fid
    //   3	66	2	localParcel1	Parcel
    //   7	58	3	localParcel2	Parcel
    // Exception table:
    //   from	to	target	type
    //   8	14	63	finally
    //   18	25	63	finally
    //   25	49	63	finally
  }
  
  /* Error */
  public final void a(fig paramfig)
  {
    // Byte code:
    //   0: invokestatic 22	android/os/Parcel:obtain	()Landroid/os/Parcel;
    //   3: astore_2
    //   4: invokestatic 22	android/os/Parcel:obtain	()Landroid/os/Parcel;
    //   7: astore_3
    //   8: aload_2
    //   9: ldc 24
    //   11: invokevirtual 28	android/os/Parcel:writeInterfaceToken	(Ljava/lang/String;)V
    //   14: aload_1
    //   15: ifnull +43 -> 58
    //   18: aload_1
    //   19: invokeinterface 51 1 0
    //   24: astore_1
    //   25: aload_2
    //   26: aload_1
    //   27: invokevirtual 54	android/os/Parcel:writeStrongBinder	(Landroid/os/IBinder;)V
    //   30: aload_0
    //   31: getfield 15	fir:a	Landroid/os/IBinder;
    //   34: bipush 22
    //   36: aload_2
    //   37: aload_3
    //   38: iconst_0
    //   39: invokeinterface 34 5 0
    //   44: pop
    //   45: aload_3
    //   46: invokevirtual 37	android/os/Parcel:readException	()V
    //   49: aload_3
    //   50: invokevirtual 40	android/os/Parcel:recycle	()V
    //   53: aload_2
    //   54: invokevirtual 40	android/os/Parcel:recycle	()V
    //   57: return
    //   58: aconst_null
    //   59: astore_1
    //   60: goto -35 -> 25
    //   63: astore_1
    //   64: aload_3
    //   65: invokevirtual 40	android/os/Parcel:recycle	()V
    //   68: aload_2
    //   69: invokevirtual 40	android/os/Parcel:recycle	()V
    //   72: aload_1
    //   73: athrow
    // Local variable table:
    //   start	length	slot	name	signature
    //   0	74	0	this	fir
    //   0	74	1	paramfig	fig
    //   3	66	2	localParcel1	Parcel
    //   7	58	3	localParcel2	Parcel
    // Exception table:
    //   from	to	target	type
    //   8	14	63	finally
    //   18	25	63	finally
    //   25	49	63	finally
  }
  
  /* Error */
  public final void a(fim paramfim)
  {
    // Byte code:
    //   0: invokestatic 22	android/os/Parcel:obtain	()Landroid/os/Parcel;
    //   3: astore_2
    //   4: invokestatic 22	android/os/Parcel:obtain	()Landroid/os/Parcel;
    //   7: astore_3
    //   8: aload_2
    //   9: ldc 24
    //   11: invokevirtual 28	android/os/Parcel:writeInterfaceToken	(Ljava/lang/String;)V
    //   14: aload_1
    //   15: ifnull +43 -> 58
    //   18: aload_1
    //   19: invokeinterface 106 1 0
    //   24: astore_1
    //   25: aload_2
    //   26: aload_1
    //   27: invokevirtual 54	android/os/Parcel:writeStrongBinder	(Landroid/os/IBinder;)V
    //   30: aload_0
    //   31: getfield 15	fir:a	Landroid/os/IBinder;
    //   34: bipush 40
    //   36: aload_2
    //   37: aload_3
    //   38: iconst_0
    //   39: invokeinterface 34 5 0
    //   44: pop
    //   45: aload_3
    //   46: invokevirtual 37	android/os/Parcel:readException	()V
    //   49: aload_3
    //   50: invokevirtual 40	android/os/Parcel:recycle	()V
    //   53: aload_2
    //   54: invokevirtual 40	android/os/Parcel:recycle	()V
    //   57: return
    //   58: aconst_null
    //   59: astore_1
    //   60: goto -35 -> 25
    //   63: astore_1
    //   64: aload_3
    //   65: invokevirtual 40	android/os/Parcel:recycle	()V
    //   68: aload_2
    //   69: invokevirtual 40	android/os/Parcel:recycle	()V
    //   72: aload_1
    //   73: athrow
    // Local variable table:
    //   start	length	slot	name	signature
    //   0	74	0	this	fir
    //   0	74	1	paramfim	fim
    //   3	66	2	localParcel1	Parcel
    //   7	58	3	localParcel2	Parcel
    // Exception table:
    //   from	to	target	type
    //   8	14	63	finally
    //   18	25	63	finally
    //   25	49	63	finally
  }
  
  /* Error */
  public final void a(fiv paramfiv)
  {
    // Byte code:
    //   0: invokestatic 22	android/os/Parcel:obtain	()Landroid/os/Parcel;
    //   3: astore_2
    //   4: invokestatic 22	android/os/Parcel:obtain	()Landroid/os/Parcel;
    //   7: astore_3
    //   8: aload_2
    //   9: ldc 24
    //   11: invokevirtual 28	android/os/Parcel:writeInterfaceToken	(Ljava/lang/String;)V
    //   14: aload_1
    //   15: ifnull +42 -> 57
    //   18: aload_1
    //   19: invokeinterface 58 1 0
    //   24: astore_1
    //   25: aload_2
    //   26: aload_1
    //   27: invokevirtual 54	android/os/Parcel:writeStrongBinder	(Landroid/os/IBinder;)V
    //   30: aload_0
    //   31: getfield 15	fir:a	Landroid/os/IBinder;
    //   34: iconst_3
    //   35: aload_2
    //   36: aload_3
    //   37: iconst_0
    //   38: invokeinterface 34 5 0
    //   43: pop
    //   44: aload_3
    //   45: invokevirtual 37	android/os/Parcel:readException	()V
    //   48: aload_3
    //   49: invokevirtual 40	android/os/Parcel:recycle	()V
    //   52: aload_2
    //   53: invokevirtual 40	android/os/Parcel:recycle	()V
    //   56: return
    //   57: aconst_null
    //   58: astore_1
    //   59: goto -34 -> 25
    //   62: astore_1
    //   63: aload_3
    //   64: invokevirtual 40	android/os/Parcel:recycle	()V
    //   67: aload_2
    //   68: invokevirtual 40	android/os/Parcel:recycle	()V
    //   71: aload_1
    //   72: athrow
    // Local variable table:
    //   start	length	slot	name	signature
    //   0	73	0	this	fir
    //   0	73	1	paramfiv	fiv
    //   3	65	2	localParcel1	Parcel
    //   7	57	3	localParcel2	Parcel
    // Exception table:
    //   from	to	target	type
    //   8	14	62	finally
    //   18	25	62	finally
    //   25	48	62	finally
  }
  
  /* Error */
  public final void a(String paramString, int paramInt1, int paramInt2, fhx paramfhx)
  {
    // Byte code:
    //   0: invokestatic 22	android/os/Parcel:obtain	()Landroid/os/Parcel;
    //   3: astore 5
    //   5: invokestatic 22	android/os/Parcel:obtain	()Landroid/os/Parcel;
    //   8: astore 6
    //   10: aload 5
    //   12: ldc 24
    //   14: invokevirtual 28	android/os/Parcel:writeInterfaceToken	(Ljava/lang/String;)V
    //   17: aload 5
    //   19: aload_1
    //   20: invokevirtual 111	android/os/Parcel:writeString	(Ljava/lang/String;)V
    //   23: aload 5
    //   25: iload_2
    //   26: invokevirtual 45	android/os/Parcel:writeInt	(I)V
    //   29: aload 5
    //   31: iload_3
    //   32: invokevirtual 45	android/os/Parcel:writeInt	(I)V
    //   35: aload 4
    //   37: ifnull +50 -> 87
    //   40: aload 4
    //   42: invokeinterface 114 1 0
    //   47: astore_1
    //   48: aload 5
    //   50: aload_1
    //   51: invokevirtual 54	android/os/Parcel:writeStrongBinder	(Landroid/os/IBinder;)V
    //   54: aload_0
    //   55: getfield 15	fir:a	Landroid/os/IBinder;
    //   58: bipush 17
    //   60: aload 5
    //   62: aload 6
    //   64: iconst_0
    //   65: invokeinterface 34 5 0
    //   70: pop
    //   71: aload 6
    //   73: invokevirtual 37	android/os/Parcel:readException	()V
    //   76: aload 6
    //   78: invokevirtual 40	android/os/Parcel:recycle	()V
    //   81: aload 5
    //   83: invokevirtual 40	android/os/Parcel:recycle	()V
    //   86: return
    //   87: aconst_null
    //   88: astore_1
    //   89: goto -41 -> 48
    //   92: astore_1
    //   93: aload 6
    //   95: invokevirtual 40	android/os/Parcel:recycle	()V
    //   98: aload 5
    //   100: invokevirtual 40	android/os/Parcel:recycle	()V
    //   103: aload_1
    //   104: athrow
    // Local variable table:
    //   start	length	slot	name	signature
    //   0	105	0	this	fir
    //   0	105	1	paramString	String
    //   0	105	2	paramInt1	int
    //   0	105	3	paramInt2	int
    //   0	105	4	paramfhx	fhx
    //   3	96	5	localParcel1	Parcel
    //   8	86	6	localParcel2	Parcel
    // Exception table:
    //   from	to	target	type
    //   10	35	92	finally
    //   40	48	92	finally
    //   48	76	92	finally
  }
  
  /* Error */
  public final void a(String paramString, int paramInt1, int paramInt2, fig paramfig)
  {
    // Byte code:
    //   0: invokestatic 22	android/os/Parcel:obtain	()Landroid/os/Parcel;
    //   3: astore 5
    //   5: invokestatic 22	android/os/Parcel:obtain	()Landroid/os/Parcel;
    //   8: astore 6
    //   10: aload 5
    //   12: ldc 24
    //   14: invokevirtual 28	android/os/Parcel:writeInterfaceToken	(Ljava/lang/String;)V
    //   17: aload 5
    //   19: aload_1
    //   20: invokevirtual 111	android/os/Parcel:writeString	(Ljava/lang/String;)V
    //   23: aload 5
    //   25: iload_2
    //   26: invokevirtual 45	android/os/Parcel:writeInt	(I)V
    //   29: aload 5
    //   31: iload_3
    //   32: invokevirtual 45	android/os/Parcel:writeInt	(I)V
    //   35: aload 4
    //   37: ifnull +50 -> 87
    //   40: aload 4
    //   42: invokeinterface 51 1 0
    //   47: astore_1
    //   48: aload 5
    //   50: aload_1
    //   51: invokevirtual 54	android/os/Parcel:writeStrongBinder	(Landroid/os/IBinder;)V
    //   54: aload_0
    //   55: getfield 15	fir:a	Landroid/os/IBinder;
    //   58: bipush 11
    //   60: aload 5
    //   62: aload 6
    //   64: iconst_0
    //   65: invokeinterface 34 5 0
    //   70: pop
    //   71: aload 6
    //   73: invokevirtual 37	android/os/Parcel:readException	()V
    //   76: aload 6
    //   78: invokevirtual 40	android/os/Parcel:recycle	()V
    //   81: aload 5
    //   83: invokevirtual 40	android/os/Parcel:recycle	()V
    //   86: return
    //   87: aconst_null
    //   88: astore_1
    //   89: goto -41 -> 48
    //   92: astore_1
    //   93: aload 6
    //   95: invokevirtual 40	android/os/Parcel:recycle	()V
    //   98: aload 5
    //   100: invokevirtual 40	android/os/Parcel:recycle	()V
    //   103: aload_1
    //   104: athrow
    // Local variable table:
    //   start	length	slot	name	signature
    //   0	105	0	this	fir
    //   0	105	1	paramString	String
    //   0	105	2	paramInt1	int
    //   0	105	3	paramInt2	int
    //   0	105	4	paramfig	fig
    //   3	96	5	localParcel1	Parcel
    //   8	86	6	localParcel2	Parcel
    // Exception table:
    //   from	to	target	type
    //   10	35	92	finally
    //   40	48	92	finally
    //   48	76	92	finally
  }
  
  public final void a(String paramString, int paramInt, DataHolder paramDataHolder, fhx paramfhx)
  {
    Parcel localParcel1 = Parcel.obtain();
    Parcel localParcel2 = Parcel.obtain();
    for (;;)
    {
      try
      {
        localParcel1.writeInterfaceToken("com.google.android.gms.drive.realtime.internal.IRealtimeService");
        localParcel1.writeString(paramString);
        localParcel1.writeInt(paramInt);
        if (paramDataHolder != null)
        {
          localParcel1.writeInt(1);
          paramDataHolder.writeToParcel(localParcel1, 0);
          if (paramfhx != null)
          {
            paramString = paramfhx.asBinder();
            localParcel1.writeStrongBinder(paramString);
            a.transact(16, localParcel1, localParcel2, 0);
            localParcel2.readException();
          }
        }
        else
        {
          localParcel1.writeInt(0);
          continue;
        }
        paramString = null;
      }
      finally
      {
        localParcel2.recycle();
        localParcel1.recycle();
      }
    }
  }
  
  public final void a(String paramString, int paramInt, DataHolder paramDataHolder, fig paramfig)
  {
    Parcel localParcel1 = Parcel.obtain();
    Parcel localParcel2 = Parcel.obtain();
    for (;;)
    {
      try
      {
        localParcel1.writeInterfaceToken("com.google.android.gms.drive.realtime.internal.IRealtimeService");
        localParcel1.writeString(paramString);
        localParcel1.writeInt(paramInt);
        if (paramDataHolder != null)
        {
          localParcel1.writeInt(1);
          paramDataHolder.writeToParcel(localParcel1, 0);
          if (paramfig != null)
          {
            paramString = paramfig.asBinder();
            localParcel1.writeStrongBinder(paramString);
            a.transact(15, localParcel1, localParcel2, 0);
            localParcel2.readException();
          }
        }
        else
        {
          localParcel1.writeInt(0);
          continue;
        }
        paramString = null;
      }
      finally
      {
        localParcel2.recycle();
        localParcel1.recycle();
      }
    }
  }
  
  /* Error */
  public final void a(String paramString, int paramInt, fis paramfis)
  {
    // Byte code:
    //   0: invokestatic 22	android/os/Parcel:obtain	()Landroid/os/Parcel;
    //   3: astore 4
    //   5: invokestatic 22	android/os/Parcel:obtain	()Landroid/os/Parcel;
    //   8: astore 5
    //   10: aload 4
    //   12: ldc 24
    //   14: invokevirtual 28	android/os/Parcel:writeInterfaceToken	(Ljava/lang/String;)V
    //   17: aload 4
    //   19: aload_1
    //   20: invokevirtual 111	android/os/Parcel:writeString	(Ljava/lang/String;)V
    //   23: aload 4
    //   25: iload_2
    //   26: invokevirtual 45	android/os/Parcel:writeInt	(I)V
    //   29: aload_3
    //   30: ifnull +49 -> 79
    //   33: aload_3
    //   34: invokeinterface 81 1 0
    //   39: astore_1
    //   40: aload 4
    //   42: aload_1
    //   43: invokevirtual 54	android/os/Parcel:writeStrongBinder	(Landroid/os/IBinder;)V
    //   46: aload_0
    //   47: getfield 15	fir:a	Landroid/os/IBinder;
    //   50: bipush 46
    //   52: aload 4
    //   54: aload 5
    //   56: iconst_0
    //   57: invokeinterface 34 5 0
    //   62: pop
    //   63: aload 5
    //   65: invokevirtual 37	android/os/Parcel:readException	()V
    //   68: aload 5
    //   70: invokevirtual 40	android/os/Parcel:recycle	()V
    //   73: aload 4
    //   75: invokevirtual 40	android/os/Parcel:recycle	()V
    //   78: return
    //   79: aconst_null
    //   80: astore_1
    //   81: goto -41 -> 40
    //   84: astore_1
    //   85: aload 5
    //   87: invokevirtual 40	android/os/Parcel:recycle	()V
    //   90: aload 4
    //   92: invokevirtual 40	android/os/Parcel:recycle	()V
    //   95: aload_1
    //   96: athrow
    // Local variable table:
    //   start	length	slot	name	signature
    //   0	97	0	this	fir
    //   0	97	1	paramString	String
    //   0	97	2	paramInt	int
    //   0	97	3	paramfis	fis
    //   3	88	4	localParcel1	Parcel
    //   8	78	5	localParcel2	Parcel
    // Exception table:
    //   from	to	target	type
    //   10	29	84	finally
    //   33	40	84	finally
    //   40	68	84	finally
  }
  
  /* Error */
  public final void a(String paramString, int paramInt, fiv paramfiv)
  {
    // Byte code:
    //   0: invokestatic 22	android/os/Parcel:obtain	()Landroid/os/Parcel;
    //   3: astore 4
    //   5: invokestatic 22	android/os/Parcel:obtain	()Landroid/os/Parcel;
    //   8: astore 5
    //   10: aload 4
    //   12: ldc 24
    //   14: invokevirtual 28	android/os/Parcel:writeInterfaceToken	(Ljava/lang/String;)V
    //   17: aload 4
    //   19: aload_1
    //   20: invokevirtual 111	android/os/Parcel:writeString	(Ljava/lang/String;)V
    //   23: aload 4
    //   25: iload_2
    //   26: invokevirtual 45	android/os/Parcel:writeInt	(I)V
    //   29: aload_3
    //   30: ifnull +49 -> 79
    //   33: aload_3
    //   34: invokeinterface 58 1 0
    //   39: astore_1
    //   40: aload 4
    //   42: aload_1
    //   43: invokevirtual 54	android/os/Parcel:writeStrongBinder	(Landroid/os/IBinder;)V
    //   46: aload_0
    //   47: getfield 15	fir:a	Landroid/os/IBinder;
    //   50: bipush 28
    //   52: aload 4
    //   54: aload 5
    //   56: iconst_0
    //   57: invokeinterface 34 5 0
    //   62: pop
    //   63: aload 5
    //   65: invokevirtual 37	android/os/Parcel:readException	()V
    //   68: aload 5
    //   70: invokevirtual 40	android/os/Parcel:recycle	()V
    //   73: aload 4
    //   75: invokevirtual 40	android/os/Parcel:recycle	()V
    //   78: return
    //   79: aconst_null
    //   80: astore_1
    //   81: goto -41 -> 40
    //   84: astore_1
    //   85: aload 5
    //   87: invokevirtual 40	android/os/Parcel:recycle	()V
    //   90: aload 4
    //   92: invokevirtual 40	android/os/Parcel:recycle	()V
    //   95: aload_1
    //   96: athrow
    // Local variable table:
    //   start	length	slot	name	signature
    //   0	97	0	this	fir
    //   0	97	1	paramString	String
    //   0	97	2	paramInt	int
    //   0	97	3	paramfiv	fiv
    //   3	88	4	localParcel1	Parcel
    //   8	78	5	localParcel2	Parcel
    // Exception table:
    //   from	to	target	type
    //   10	29	84	finally
    //   33	40	84	finally
    //   40	68	84	finally
  }
  
  /* Error */
  public final void a(String paramString1, int paramInt1, String paramString2, int paramInt2, fig paramfig)
  {
    // Byte code:
    //   0: invokestatic 22	android/os/Parcel:obtain	()Landroid/os/Parcel;
    //   3: astore 6
    //   5: invokestatic 22	android/os/Parcel:obtain	()Landroid/os/Parcel;
    //   8: astore 7
    //   10: aload 6
    //   12: ldc 24
    //   14: invokevirtual 28	android/os/Parcel:writeInterfaceToken	(Ljava/lang/String;)V
    //   17: aload 6
    //   19: aload_1
    //   20: invokevirtual 111	android/os/Parcel:writeString	(Ljava/lang/String;)V
    //   23: aload 6
    //   25: iload_2
    //   26: invokevirtual 45	android/os/Parcel:writeInt	(I)V
    //   29: aload 6
    //   31: aload_3
    //   32: invokevirtual 111	android/os/Parcel:writeString	(Ljava/lang/String;)V
    //   35: aload 6
    //   37: iload 4
    //   39: invokevirtual 45	android/os/Parcel:writeInt	(I)V
    //   42: aload 5
    //   44: ifnull +50 -> 94
    //   47: aload 5
    //   49: invokeinterface 51 1 0
    //   54: astore_1
    //   55: aload 6
    //   57: aload_1
    //   58: invokevirtual 54	android/os/Parcel:writeStrongBinder	(Landroid/os/IBinder;)V
    //   61: aload_0
    //   62: getfield 15	fir:a	Landroid/os/IBinder;
    //   65: bipush 37
    //   67: aload 6
    //   69: aload 7
    //   71: iconst_0
    //   72: invokeinterface 34 5 0
    //   77: pop
    //   78: aload 7
    //   80: invokevirtual 37	android/os/Parcel:readException	()V
    //   83: aload 7
    //   85: invokevirtual 40	android/os/Parcel:recycle	()V
    //   88: aload 6
    //   90: invokevirtual 40	android/os/Parcel:recycle	()V
    //   93: return
    //   94: aconst_null
    //   95: astore_1
    //   96: goto -41 -> 55
    //   99: astore_1
    //   100: aload 7
    //   102: invokevirtual 40	android/os/Parcel:recycle	()V
    //   105: aload 6
    //   107: invokevirtual 40	android/os/Parcel:recycle	()V
    //   110: aload_1
    //   111: athrow
    // Local variable table:
    //   start	length	slot	name	signature
    //   0	112	0	this	fir
    //   0	112	1	paramString1	String
    //   0	112	2	paramInt1	int
    //   0	112	3	paramString2	String
    //   0	112	4	paramInt2	int
    //   0	112	5	paramfig	fig
    //   3	103	6	localParcel1	Parcel
    //   8	93	7	localParcel2	Parcel
    // Exception table:
    //   from	to	target	type
    //   10	42	99	finally
    //   47	55	99	finally
    //   55	83	99	finally
  }
  
  /* Error */
  public final void a(String paramString1, int paramInt, String paramString2, fig paramfig)
  {
    // Byte code:
    //   0: invokestatic 22	android/os/Parcel:obtain	()Landroid/os/Parcel;
    //   3: astore 5
    //   5: invokestatic 22	android/os/Parcel:obtain	()Landroid/os/Parcel;
    //   8: astore 6
    //   10: aload 5
    //   12: ldc 24
    //   14: invokevirtual 28	android/os/Parcel:writeInterfaceToken	(Ljava/lang/String;)V
    //   17: aload 5
    //   19: aload_1
    //   20: invokevirtual 111	android/os/Parcel:writeString	(Ljava/lang/String;)V
    //   23: aload 5
    //   25: iload_2
    //   26: invokevirtual 45	android/os/Parcel:writeInt	(I)V
    //   29: aload 5
    //   31: aload_3
    //   32: invokevirtual 111	android/os/Parcel:writeString	(Ljava/lang/String;)V
    //   35: aload 4
    //   37: ifnull +50 -> 87
    //   40: aload 4
    //   42: invokeinterface 51 1 0
    //   47: astore_1
    //   48: aload 5
    //   50: aload_1
    //   51: invokevirtual 54	android/os/Parcel:writeStrongBinder	(Landroid/os/IBinder;)V
    //   54: aload_0
    //   55: getfield 15	fir:a	Landroid/os/IBinder;
    //   58: bipush 10
    //   60: aload 5
    //   62: aload 6
    //   64: iconst_0
    //   65: invokeinterface 34 5 0
    //   70: pop
    //   71: aload 6
    //   73: invokevirtual 37	android/os/Parcel:readException	()V
    //   76: aload 6
    //   78: invokevirtual 40	android/os/Parcel:recycle	()V
    //   81: aload 5
    //   83: invokevirtual 40	android/os/Parcel:recycle	()V
    //   86: return
    //   87: aconst_null
    //   88: astore_1
    //   89: goto -41 -> 48
    //   92: astore_1
    //   93: aload 6
    //   95: invokevirtual 40	android/os/Parcel:recycle	()V
    //   98: aload 5
    //   100: invokevirtual 40	android/os/Parcel:recycle	()V
    //   103: aload_1
    //   104: athrow
    // Local variable table:
    //   start	length	slot	name	signature
    //   0	105	0	this	fir
    //   0	105	1	paramString1	String
    //   0	105	2	paramInt	int
    //   0	105	3	paramString2	String
    //   0	105	4	paramfig	fig
    //   3	96	5	localParcel1	Parcel
    //   8	86	6	localParcel2	Parcel
    // Exception table:
    //   from	to	target	type
    //   10	35	92	finally
    //   40	48	92	finally
    //   48	76	92	finally
  }
  
  public final void a(String paramString, DataHolder paramDataHolder, fig paramfig)
  {
    Parcel localParcel1 = Parcel.obtain();
    Parcel localParcel2 = Parcel.obtain();
    for (;;)
    {
      try
      {
        localParcel1.writeInterfaceToken("com.google.android.gms.drive.realtime.internal.IRealtimeService");
        localParcel1.writeString(paramString);
        if (paramDataHolder != null)
        {
          localParcel1.writeInt(1);
          paramDataHolder.writeToParcel(localParcel1, 0);
          if (paramfig != null)
          {
            paramString = paramfig.asBinder();
            localParcel1.writeStrongBinder(paramString);
            a.transact(6, localParcel1, localParcel2, 0);
            localParcel2.readException();
          }
        }
        else
        {
          localParcel1.writeInt(0);
          continue;
        }
        paramString = null;
      }
      finally
      {
        localParcel2.recycle();
        localParcel1.recycle();
      }
    }
  }
  
  /* Error */
  public final void a(String paramString, fhu paramfhu)
  {
    // Byte code:
    //   0: invokestatic 22	android/os/Parcel:obtain	()Landroid/os/Parcel;
    //   3: astore_3
    //   4: invokestatic 22	android/os/Parcel:obtain	()Landroid/os/Parcel;
    //   7: astore 4
    //   9: aload_3
    //   10: ldc 24
    //   12: invokevirtual 28	android/os/Parcel:writeInterfaceToken	(Ljava/lang/String;)V
    //   15: aload_3
    //   16: aload_1
    //   17: invokevirtual 111	android/os/Parcel:writeString	(Ljava/lang/String;)V
    //   20: aload_2
    //   21: ifnull +46 -> 67
    //   24: aload_2
    //   25: invokeinterface 129 1 0
    //   30: astore_1
    //   31: aload_3
    //   32: aload_1
    //   33: invokevirtual 54	android/os/Parcel:writeStrongBinder	(Landroid/os/IBinder;)V
    //   36: aload_0
    //   37: getfield 15	fir:a	Landroid/os/IBinder;
    //   40: bipush 20
    //   42: aload_3
    //   43: aload 4
    //   45: iconst_0
    //   46: invokeinterface 34 5 0
    //   51: pop
    //   52: aload 4
    //   54: invokevirtual 37	android/os/Parcel:readException	()V
    //   57: aload 4
    //   59: invokevirtual 40	android/os/Parcel:recycle	()V
    //   62: aload_3
    //   63: invokevirtual 40	android/os/Parcel:recycle	()V
    //   66: return
    //   67: aconst_null
    //   68: astore_1
    //   69: goto -38 -> 31
    //   72: astore_1
    //   73: aload 4
    //   75: invokevirtual 40	android/os/Parcel:recycle	()V
    //   78: aload_3
    //   79: invokevirtual 40	android/os/Parcel:recycle	()V
    //   82: aload_1
    //   83: athrow
    // Local variable table:
    //   start	length	slot	name	signature
    //   0	84	0	this	fir
    //   0	84	1	paramString	String
    //   0	84	2	paramfhu	fhu
    //   3	76	3	localParcel1	Parcel
    //   7	67	4	localParcel2	Parcel
    // Exception table:
    //   from	to	target	type
    //   9	20	72	finally
    //   24	31	72	finally
    //   31	57	72	finally
  }
  
  /* Error */
  public final void a(String paramString, fig paramfig)
  {
    // Byte code:
    //   0: invokestatic 22	android/os/Parcel:obtain	()Landroid/os/Parcel;
    //   3: astore_3
    //   4: invokestatic 22	android/os/Parcel:obtain	()Landroid/os/Parcel;
    //   7: astore 4
    //   9: aload_3
    //   10: ldc 24
    //   12: invokevirtual 28	android/os/Parcel:writeInterfaceToken	(Ljava/lang/String;)V
    //   15: aload_3
    //   16: aload_1
    //   17: invokevirtual 111	android/os/Parcel:writeString	(Ljava/lang/String;)V
    //   20: aload_2
    //   21: ifnull +46 -> 67
    //   24: aload_2
    //   25: invokeinterface 51 1 0
    //   30: astore_1
    //   31: aload_3
    //   32: aload_1
    //   33: invokevirtual 54	android/os/Parcel:writeStrongBinder	(Landroid/os/IBinder;)V
    //   36: aload_0
    //   37: getfield 15	fir:a	Landroid/os/IBinder;
    //   40: bipush 7
    //   42: aload_3
    //   43: aload 4
    //   45: iconst_0
    //   46: invokeinterface 34 5 0
    //   51: pop
    //   52: aload 4
    //   54: invokevirtual 37	android/os/Parcel:readException	()V
    //   57: aload 4
    //   59: invokevirtual 40	android/os/Parcel:recycle	()V
    //   62: aload_3
    //   63: invokevirtual 40	android/os/Parcel:recycle	()V
    //   66: return
    //   67: aconst_null
    //   68: astore_1
    //   69: goto -38 -> 31
    //   72: astore_1
    //   73: aload 4
    //   75: invokevirtual 40	android/os/Parcel:recycle	()V
    //   78: aload_3
    //   79: invokevirtual 40	android/os/Parcel:recycle	()V
    //   82: aload_1
    //   83: athrow
    // Local variable table:
    //   start	length	slot	name	signature
    //   0	84	0	this	fir
    //   0	84	1	paramString	String
    //   0	84	2	paramfig	fig
    //   3	76	3	localParcel1	Parcel
    //   7	67	4	localParcel2	Parcel
    // Exception table:
    //   from	to	target	type
    //   9	20	72	finally
    //   24	31	72	finally
    //   31	57	72	finally
  }
  
  /* Error */
  public final void a(String paramString, fij paramfij)
  {
    // Byte code:
    //   0: invokestatic 22	android/os/Parcel:obtain	()Landroid/os/Parcel;
    //   3: astore_3
    //   4: invokestatic 22	android/os/Parcel:obtain	()Landroid/os/Parcel;
    //   7: astore 4
    //   9: aload_3
    //   10: ldc 24
    //   12: invokevirtual 28	android/os/Parcel:writeInterfaceToken	(Ljava/lang/String;)V
    //   15: aload_3
    //   16: aload_1
    //   17: invokevirtual 111	android/os/Parcel:writeString	(Ljava/lang/String;)V
    //   20: aload_2
    //   21: ifnull +46 -> 67
    //   24: aload_2
    //   25: invokeinterface 134 1 0
    //   30: astore_1
    //   31: aload_3
    //   32: aload_1
    //   33: invokevirtual 54	android/os/Parcel:writeStrongBinder	(Landroid/os/IBinder;)V
    //   36: aload_0
    //   37: getfield 15	fir:a	Landroid/os/IBinder;
    //   40: bipush 27
    //   42: aload_3
    //   43: aload 4
    //   45: iconst_0
    //   46: invokeinterface 34 5 0
    //   51: pop
    //   52: aload 4
    //   54: invokevirtual 37	android/os/Parcel:readException	()V
    //   57: aload 4
    //   59: invokevirtual 40	android/os/Parcel:recycle	()V
    //   62: aload_3
    //   63: invokevirtual 40	android/os/Parcel:recycle	()V
    //   66: return
    //   67: aconst_null
    //   68: astore_1
    //   69: goto -38 -> 31
    //   72: astore_1
    //   73: aload 4
    //   75: invokevirtual 40	android/os/Parcel:recycle	()V
    //   78: aload_3
    //   79: invokevirtual 40	android/os/Parcel:recycle	()V
    //   82: aload_1
    //   83: athrow
    // Local variable table:
    //   start	length	slot	name	signature
    //   0	84	0	this	fir
    //   0	84	1	paramString	String
    //   0	84	2	paramfij	fij
    //   3	76	3	localParcel1	Parcel
    //   7	67	4	localParcel2	Parcel
    // Exception table:
    //   from	to	target	type
    //   9	20	72	finally
    //   24	31	72	finally
    //   31	57	72	finally
  }
  
  /* Error */
  public final void a(String paramString, fim paramfim)
  {
    // Byte code:
    //   0: invokestatic 22	android/os/Parcel:obtain	()Landroid/os/Parcel;
    //   3: astore_3
    //   4: invokestatic 22	android/os/Parcel:obtain	()Landroid/os/Parcel;
    //   7: astore 4
    //   9: aload_3
    //   10: ldc 24
    //   12: invokevirtual 28	android/os/Parcel:writeInterfaceToken	(Ljava/lang/String;)V
    //   15: aload_3
    //   16: aload_1
    //   17: invokevirtual 111	android/os/Parcel:writeString	(Ljava/lang/String;)V
    //   20: aload_2
    //   21: ifnull +45 -> 66
    //   24: aload_2
    //   25: invokeinterface 106 1 0
    //   30: astore_1
    //   31: aload_3
    //   32: aload_1
    //   33: invokevirtual 54	android/os/Parcel:writeStrongBinder	(Landroid/os/IBinder;)V
    //   36: aload_0
    //   37: getfield 15	fir:a	Landroid/os/IBinder;
    //   40: iconst_5
    //   41: aload_3
    //   42: aload 4
    //   44: iconst_0
    //   45: invokeinterface 34 5 0
    //   50: pop
    //   51: aload 4
    //   53: invokevirtual 37	android/os/Parcel:readException	()V
    //   56: aload 4
    //   58: invokevirtual 40	android/os/Parcel:recycle	()V
    //   61: aload_3
    //   62: invokevirtual 40	android/os/Parcel:recycle	()V
    //   65: return
    //   66: aconst_null
    //   67: astore_1
    //   68: goto -37 -> 31
    //   71: astore_1
    //   72: aload 4
    //   74: invokevirtual 40	android/os/Parcel:recycle	()V
    //   77: aload_3
    //   78: invokevirtual 40	android/os/Parcel:recycle	()V
    //   81: aload_1
    //   82: athrow
    // Local variable table:
    //   start	length	slot	name	signature
    //   0	83	0	this	fir
    //   0	83	1	paramString	String
    //   0	83	2	paramfim	fim
    //   3	75	3	localParcel1	Parcel
    //   7	66	4	localParcel2	Parcel
    // Exception table:
    //   from	to	target	type
    //   9	20	71	finally
    //   24	31	71	finally
    //   31	56	71	finally
  }
  
  /* Error */
  public final void a(String paramString, fis paramfis)
  {
    // Byte code:
    //   0: invokestatic 22	android/os/Parcel:obtain	()Landroid/os/Parcel;
    //   3: astore_3
    //   4: invokestatic 22	android/os/Parcel:obtain	()Landroid/os/Parcel;
    //   7: astore 4
    //   9: aload_3
    //   10: ldc 24
    //   12: invokevirtual 28	android/os/Parcel:writeInterfaceToken	(Ljava/lang/String;)V
    //   15: aload_3
    //   16: aload_1
    //   17: invokevirtual 111	android/os/Parcel:writeString	(Ljava/lang/String;)V
    //   20: aload_2
    //   21: ifnull +45 -> 66
    //   24: aload_2
    //   25: invokeinterface 81 1 0
    //   30: astore_1
    //   31: aload_3
    //   32: aload_1
    //   33: invokevirtual 54	android/os/Parcel:writeStrongBinder	(Landroid/os/IBinder;)V
    //   36: aload_0
    //   37: getfield 15	fir:a	Landroid/os/IBinder;
    //   40: iconst_1
    //   41: aload_3
    //   42: aload 4
    //   44: iconst_0
    //   45: invokeinterface 34 5 0
    //   50: pop
    //   51: aload 4
    //   53: invokevirtual 37	android/os/Parcel:readException	()V
    //   56: aload 4
    //   58: invokevirtual 40	android/os/Parcel:recycle	()V
    //   61: aload_3
    //   62: invokevirtual 40	android/os/Parcel:recycle	()V
    //   65: return
    //   66: aconst_null
    //   67: astore_1
    //   68: goto -37 -> 31
    //   71: astore_1
    //   72: aload 4
    //   74: invokevirtual 40	android/os/Parcel:recycle	()V
    //   77: aload_3
    //   78: invokevirtual 40	android/os/Parcel:recycle	()V
    //   81: aload_1
    //   82: athrow
    // Local variable table:
    //   start	length	slot	name	signature
    //   0	83	0	this	fir
    //   0	83	1	paramString	String
    //   0	83	2	paramfis	fis
    //   3	75	3	localParcel1	Parcel
    //   7	66	4	localParcel2	Parcel
    // Exception table:
    //   from	to	target	type
    //   9	20	71	finally
    //   24	31	71	finally
    //   31	56	71	finally
  }
  
  /* Error */
  public final void a(String paramString, fiv paramfiv)
  {
    // Byte code:
    //   0: invokestatic 22	android/os/Parcel:obtain	()Landroid/os/Parcel;
    //   3: astore_3
    //   4: invokestatic 22	android/os/Parcel:obtain	()Landroid/os/Parcel;
    //   7: astore 4
    //   9: aload_3
    //   10: ldc 24
    //   12: invokevirtual 28	android/os/Parcel:writeInterfaceToken	(Ljava/lang/String;)V
    //   15: aload_3
    //   16: aload_1
    //   17: invokevirtual 111	android/os/Parcel:writeString	(Ljava/lang/String;)V
    //   20: aload_2
    //   21: ifnull +46 -> 67
    //   24: aload_2
    //   25: invokeinterface 58 1 0
    //   30: astore_1
    //   31: aload_3
    //   32: aload_1
    //   33: invokevirtual 54	android/os/Parcel:writeStrongBinder	(Landroid/os/IBinder;)V
    //   36: aload_0
    //   37: getfield 15	fir:a	Landroid/os/IBinder;
    //   40: bipush 38
    //   42: aload_3
    //   43: aload 4
    //   45: iconst_0
    //   46: invokeinterface 34 5 0
    //   51: pop
    //   52: aload 4
    //   54: invokevirtual 37	android/os/Parcel:readException	()V
    //   57: aload 4
    //   59: invokevirtual 40	android/os/Parcel:recycle	()V
    //   62: aload_3
    //   63: invokevirtual 40	android/os/Parcel:recycle	()V
    //   66: return
    //   67: aconst_null
    //   68: astore_1
    //   69: goto -38 -> 31
    //   72: astore_1
    //   73: aload 4
    //   75: invokevirtual 40	android/os/Parcel:recycle	()V
    //   78: aload_3
    //   79: invokevirtual 40	android/os/Parcel:recycle	()V
    //   82: aload_1
    //   83: athrow
    // Local variable table:
    //   start	length	slot	name	signature
    //   0	84	0	this	fir
    //   0	84	1	paramString	String
    //   0	84	2	paramfiv	fiv
    //   3	76	3	localParcel1	Parcel
    //   7	67	4	localParcel2	Parcel
    // Exception table:
    //   from	to	target	type
    //   9	20	72	finally
    //   24	31	72	finally
    //   31	57	72	finally
  }
  
  public final void a(String paramString1, String paramString2, DataHolder paramDataHolder, fig paramfig)
  {
    Parcel localParcel1 = Parcel.obtain();
    Parcel localParcel2 = Parcel.obtain();
    for (;;)
    {
      try
      {
        localParcel1.writeInterfaceToken("com.google.android.gms.drive.realtime.internal.IRealtimeService");
        localParcel1.writeString(paramString1);
        localParcel1.writeString(paramString2);
        if (paramDataHolder != null)
        {
          localParcel1.writeInt(1);
          paramDataHolder.writeToParcel(localParcel1, 0);
          if (paramfig != null)
          {
            paramString1 = paramfig.asBinder();
            localParcel1.writeStrongBinder(paramString1);
            a.transact(43, localParcel1, localParcel2, 0);
            localParcel2.readException();
          }
        }
        else
        {
          localParcel1.writeInt(0);
          continue;
        }
        paramString1 = null;
      }
      finally
      {
        localParcel2.recycle();
        localParcel1.recycle();
      }
    }
  }
  
  /* Error */
  public final void a(String paramString1, String paramString2, fhu paramfhu)
  {
    // Byte code:
    //   0: invokestatic 22	android/os/Parcel:obtain	()Landroid/os/Parcel;
    //   3: astore 4
    //   5: invokestatic 22	android/os/Parcel:obtain	()Landroid/os/Parcel;
    //   8: astore 5
    //   10: aload 4
    //   12: ldc 24
    //   14: invokevirtual 28	android/os/Parcel:writeInterfaceToken	(Ljava/lang/String;)V
    //   17: aload 4
    //   19: aload_1
    //   20: invokevirtual 111	android/os/Parcel:writeString	(Ljava/lang/String;)V
    //   23: aload 4
    //   25: aload_2
    //   26: invokevirtual 111	android/os/Parcel:writeString	(Ljava/lang/String;)V
    //   29: aload_3
    //   30: ifnull +48 -> 78
    //   33: aload_3
    //   34: invokeinterface 129 1 0
    //   39: astore_1
    //   40: aload 4
    //   42: aload_1
    //   43: invokevirtual 54	android/os/Parcel:writeStrongBinder	(Landroid/os/IBinder;)V
    //   46: aload_0
    //   47: getfield 15	fir:a	Landroid/os/IBinder;
    //   50: iconst_4
    //   51: aload 4
    //   53: aload 5
    //   55: iconst_0
    //   56: invokeinterface 34 5 0
    //   61: pop
    //   62: aload 5
    //   64: invokevirtual 37	android/os/Parcel:readException	()V
    //   67: aload 5
    //   69: invokevirtual 40	android/os/Parcel:recycle	()V
    //   72: aload 4
    //   74: invokevirtual 40	android/os/Parcel:recycle	()V
    //   77: return
    //   78: aconst_null
    //   79: astore_1
    //   80: goto -40 -> 40
    //   83: astore_1
    //   84: aload 5
    //   86: invokevirtual 40	android/os/Parcel:recycle	()V
    //   89: aload 4
    //   91: invokevirtual 40	android/os/Parcel:recycle	()V
    //   94: aload_1
    //   95: athrow
    // Local variable table:
    //   start	length	slot	name	signature
    //   0	96	0	this	fir
    //   0	96	1	paramString1	String
    //   0	96	2	paramString2	String
    //   0	96	3	paramfhu	fhu
    //   3	87	4	localParcel1	Parcel
    //   8	77	5	localParcel2	Parcel
    // Exception table:
    //   from	to	target	type
    //   10	29	83	finally
    //   33	40	83	finally
    //   40	67	83	finally
  }
  
  /* Error */
  public final void a(String paramString1, String paramString2, fhx paramfhx)
  {
    // Byte code:
    //   0: invokestatic 22	android/os/Parcel:obtain	()Landroid/os/Parcel;
    //   3: astore 4
    //   5: invokestatic 22	android/os/Parcel:obtain	()Landroid/os/Parcel;
    //   8: astore 5
    //   10: aload 4
    //   12: ldc 24
    //   14: invokevirtual 28	android/os/Parcel:writeInterfaceToken	(Ljava/lang/String;)V
    //   17: aload 4
    //   19: aload_1
    //   20: invokevirtual 111	android/os/Parcel:writeString	(Ljava/lang/String;)V
    //   23: aload 4
    //   25: aload_2
    //   26: invokevirtual 111	android/os/Parcel:writeString	(Ljava/lang/String;)V
    //   29: aload_3
    //   30: ifnull +49 -> 79
    //   33: aload_3
    //   34: invokeinterface 114 1 0
    //   39: astore_1
    //   40: aload 4
    //   42: aload_1
    //   43: invokevirtual 54	android/os/Parcel:writeStrongBinder	(Landroid/os/IBinder;)V
    //   46: aload_0
    //   47: getfield 15	fir:a	Landroid/os/IBinder;
    //   50: bipush 21
    //   52: aload 4
    //   54: aload 5
    //   56: iconst_0
    //   57: invokeinterface 34 5 0
    //   62: pop
    //   63: aload 5
    //   65: invokevirtual 37	android/os/Parcel:readException	()V
    //   68: aload 5
    //   70: invokevirtual 40	android/os/Parcel:recycle	()V
    //   73: aload 4
    //   75: invokevirtual 40	android/os/Parcel:recycle	()V
    //   78: return
    //   79: aconst_null
    //   80: astore_1
    //   81: goto -41 -> 40
    //   84: astore_1
    //   85: aload 5
    //   87: invokevirtual 40	android/os/Parcel:recycle	()V
    //   90: aload 4
    //   92: invokevirtual 40	android/os/Parcel:recycle	()V
    //   95: aload_1
    //   96: athrow
    // Local variable table:
    //   start	length	slot	name	signature
    //   0	97	0	this	fir
    //   0	97	1	paramString1	String
    //   0	97	2	paramString2	String
    //   0	97	3	paramfhx	fhx
    //   3	88	4	localParcel1	Parcel
    //   8	78	5	localParcel2	Parcel
    // Exception table:
    //   from	to	target	type
    //   10	29	84	finally
    //   33	40	84	finally
    //   40	68	84	finally
  }
  
  /* Error */
  public final void a(String paramString1, String paramString2, fig paramfig)
  {
    // Byte code:
    //   0: invokestatic 22	android/os/Parcel:obtain	()Landroid/os/Parcel;
    //   3: astore 4
    //   5: invokestatic 22	android/os/Parcel:obtain	()Landroid/os/Parcel;
    //   8: astore 5
    //   10: aload 4
    //   12: ldc 24
    //   14: invokevirtual 28	android/os/Parcel:writeInterfaceToken	(Ljava/lang/String;)V
    //   17: aload 4
    //   19: aload_1
    //   20: invokevirtual 111	android/os/Parcel:writeString	(Ljava/lang/String;)V
    //   23: aload 4
    //   25: aload_2
    //   26: invokevirtual 111	android/os/Parcel:writeString	(Ljava/lang/String;)V
    //   29: aload_3
    //   30: ifnull +49 -> 79
    //   33: aload_3
    //   34: invokeinterface 51 1 0
    //   39: astore_1
    //   40: aload 4
    //   42: aload_1
    //   43: invokevirtual 54	android/os/Parcel:writeStrongBinder	(Landroid/os/IBinder;)V
    //   46: aload_0
    //   47: getfield 15	fir:a	Landroid/os/IBinder;
    //   50: bipush 12
    //   52: aload 4
    //   54: aload 5
    //   56: iconst_0
    //   57: invokeinterface 34 5 0
    //   62: pop
    //   63: aload 5
    //   65: invokevirtual 37	android/os/Parcel:readException	()V
    //   68: aload 5
    //   70: invokevirtual 40	android/os/Parcel:recycle	()V
    //   73: aload 4
    //   75: invokevirtual 40	android/os/Parcel:recycle	()V
    //   78: return
    //   79: aconst_null
    //   80: astore_1
    //   81: goto -41 -> 40
    //   84: astore_1
    //   85: aload 5
    //   87: invokevirtual 40	android/os/Parcel:recycle	()V
    //   90: aload 4
    //   92: invokevirtual 40	android/os/Parcel:recycle	()V
    //   95: aload_1
    //   96: athrow
    // Local variable table:
    //   start	length	slot	name	signature
    //   0	97	0	this	fir
    //   0	97	1	paramString1	String
    //   0	97	2	paramString2	String
    //   0	97	3	paramfig	fig
    //   3	88	4	localParcel1	Parcel
    //   8	78	5	localParcel2	Parcel
    // Exception table:
    //   from	to	target	type
    //   10	29	84	finally
    //   33	40	84	finally
    //   40	68	84	finally
  }
  
  /* Error */
  public final void a(boolean paramBoolean, fiv paramfiv)
  {
    // Byte code:
    //   0: iconst_0
    //   1: istore_3
    //   2: invokestatic 22	android/os/Parcel:obtain	()Landroid/os/Parcel;
    //   5: astore 4
    //   7: invokestatic 22	android/os/Parcel:obtain	()Landroid/os/Parcel;
    //   10: astore 5
    //   12: aload 4
    //   14: ldc 24
    //   16: invokevirtual 28	android/os/Parcel:writeInterfaceToken	(Ljava/lang/String;)V
    //   19: iload_1
    //   20: ifeq +5 -> 25
    //   23: iconst_1
    //   24: istore_3
    //   25: aload 4
    //   27: iload_3
    //   28: invokevirtual 45	android/os/Parcel:writeInt	(I)V
    //   31: aload_2
    //   32: ifnull +49 -> 81
    //   35: aload_2
    //   36: invokeinterface 58 1 0
    //   41: astore_2
    //   42: aload 4
    //   44: aload_2
    //   45: invokevirtual 54	android/os/Parcel:writeStrongBinder	(Landroid/os/IBinder;)V
    //   48: aload_0
    //   49: getfield 15	fir:a	Landroid/os/IBinder;
    //   52: bipush 47
    //   54: aload 4
    //   56: aload 5
    //   58: iconst_0
    //   59: invokeinterface 34 5 0
    //   64: pop
    //   65: aload 5
    //   67: invokevirtual 37	android/os/Parcel:readException	()V
    //   70: aload 5
    //   72: invokevirtual 40	android/os/Parcel:recycle	()V
    //   75: aload 4
    //   77: invokevirtual 40	android/os/Parcel:recycle	()V
    //   80: return
    //   81: aconst_null
    //   82: astore_2
    //   83: goto -41 -> 42
    //   86: astore_2
    //   87: aload 5
    //   89: invokevirtual 40	android/os/Parcel:recycle	()V
    //   92: aload 4
    //   94: invokevirtual 40	android/os/Parcel:recycle	()V
    //   97: aload_2
    //   98: athrow
    // Local variable table:
    //   start	length	slot	name	signature
    //   0	99	0	this	fir
    //   0	99	1	paramBoolean	boolean
    //   0	99	2	paramfiv	fiv
    //   1	27	3	i	int
    //   5	88	4	localParcel1	Parcel
    //   10	78	5	localParcel2	Parcel
    // Exception table:
    //   from	to	target	type
    //   12	19	86	finally
    //   25	31	86	finally
    //   35	42	86	finally
    //   42	70	86	finally
  }
  
  public final IBinder asBinder()
  {
    return a;
  }
  
  /* Error */
  public final void b(fhl paramfhl)
  {
    // Byte code:
    //   0: invokestatic 22	android/os/Parcel:obtain	()Landroid/os/Parcel;
    //   3: astore_2
    //   4: invokestatic 22	android/os/Parcel:obtain	()Landroid/os/Parcel;
    //   7: astore_3
    //   8: aload_2
    //   9: ldc 24
    //   11: invokevirtual 28	android/os/Parcel:writeInterfaceToken	(Ljava/lang/String;)V
    //   14: aload_1
    //   15: ifnull +43 -> 58
    //   18: aload_1
    //   19: invokeinterface 85 1 0
    //   24: astore_1
    //   25: aload_2
    //   26: aload_1
    //   27: invokevirtual 54	android/os/Parcel:writeStrongBinder	(Landroid/os/IBinder;)V
    //   30: aload_0
    //   31: getfield 15	fir:a	Landroid/os/IBinder;
    //   34: bipush 33
    //   36: aload_2
    //   37: aload_3
    //   38: iconst_0
    //   39: invokeinterface 34 5 0
    //   44: pop
    //   45: aload_3
    //   46: invokevirtual 37	android/os/Parcel:readException	()V
    //   49: aload_3
    //   50: invokevirtual 40	android/os/Parcel:recycle	()V
    //   53: aload_2
    //   54: invokevirtual 40	android/os/Parcel:recycle	()V
    //   57: return
    //   58: aconst_null
    //   59: astore_1
    //   60: goto -35 -> 25
    //   63: astore_1
    //   64: aload_3
    //   65: invokevirtual 40	android/os/Parcel:recycle	()V
    //   68: aload_2
    //   69: invokevirtual 40	android/os/Parcel:recycle	()V
    //   72: aload_1
    //   73: athrow
    // Local variable table:
    //   start	length	slot	name	signature
    //   0	74	0	this	fir
    //   0	74	1	paramfhl	fhl
    //   3	66	2	localParcel1	Parcel
    //   7	58	3	localParcel2	Parcel
    // Exception table:
    //   from	to	target	type
    //   8	14	63	finally
    //   18	25	63	finally
    //   25	49	63	finally
  }
  
  /* Error */
  public final void b(fig paramfig)
  {
    // Byte code:
    //   0: invokestatic 22	android/os/Parcel:obtain	()Landroid/os/Parcel;
    //   3: astore_2
    //   4: invokestatic 22	android/os/Parcel:obtain	()Landroid/os/Parcel;
    //   7: astore_3
    //   8: aload_2
    //   9: ldc 24
    //   11: invokevirtual 28	android/os/Parcel:writeInterfaceToken	(Ljava/lang/String;)V
    //   14: aload_1
    //   15: ifnull +43 -> 58
    //   18: aload_1
    //   19: invokeinterface 51 1 0
    //   24: astore_1
    //   25: aload_2
    //   26: aload_1
    //   27: invokevirtual 54	android/os/Parcel:writeStrongBinder	(Landroid/os/IBinder;)V
    //   30: aload_0
    //   31: getfield 15	fir:a	Landroid/os/IBinder;
    //   34: bipush 23
    //   36: aload_2
    //   37: aload_3
    //   38: iconst_0
    //   39: invokeinterface 34 5 0
    //   44: pop
    //   45: aload_3
    //   46: invokevirtual 37	android/os/Parcel:readException	()V
    //   49: aload_3
    //   50: invokevirtual 40	android/os/Parcel:recycle	()V
    //   53: aload_2
    //   54: invokevirtual 40	android/os/Parcel:recycle	()V
    //   57: return
    //   58: aconst_null
    //   59: astore_1
    //   60: goto -35 -> 25
    //   63: astore_1
    //   64: aload_3
    //   65: invokevirtual 40	android/os/Parcel:recycle	()V
    //   68: aload_2
    //   69: invokevirtual 40	android/os/Parcel:recycle	()V
    //   72: aload_1
    //   73: athrow
    // Local variable table:
    //   start	length	slot	name	signature
    //   0	74	0	this	fir
    //   0	74	1	paramfig	fig
    //   3	66	2	localParcel1	Parcel
    //   7	58	3	localParcel2	Parcel
    // Exception table:
    //   from	to	target	type
    //   8	14	63	finally
    //   18	25	63	finally
    //   25	49	63	finally
  }
  
  /* Error */
  public final void b(fim paramfim)
  {
    // Byte code:
    //   0: invokestatic 22	android/os/Parcel:obtain	()Landroid/os/Parcel;
    //   3: astore_2
    //   4: invokestatic 22	android/os/Parcel:obtain	()Landroid/os/Parcel;
    //   7: astore_3
    //   8: aload_2
    //   9: ldc 24
    //   11: invokevirtual 28	android/os/Parcel:writeInterfaceToken	(Ljava/lang/String;)V
    //   14: aload_1
    //   15: ifnull +43 -> 58
    //   18: aload_1
    //   19: invokeinterface 106 1 0
    //   24: astore_1
    //   25: aload_2
    //   26: aload_1
    //   27: invokevirtual 54	android/os/Parcel:writeStrongBinder	(Landroid/os/IBinder;)V
    //   30: aload_0
    //   31: getfield 15	fir:a	Landroid/os/IBinder;
    //   34: bipush 29
    //   36: aload_2
    //   37: aload_3
    //   38: iconst_0
    //   39: invokeinterface 34 5 0
    //   44: pop
    //   45: aload_3
    //   46: invokevirtual 37	android/os/Parcel:readException	()V
    //   49: aload_3
    //   50: invokevirtual 40	android/os/Parcel:recycle	()V
    //   53: aload_2
    //   54: invokevirtual 40	android/os/Parcel:recycle	()V
    //   57: return
    //   58: aconst_null
    //   59: astore_1
    //   60: goto -35 -> 25
    //   63: astore_1
    //   64: aload_3
    //   65: invokevirtual 40	android/os/Parcel:recycle	()V
    //   68: aload_2
    //   69: invokevirtual 40	android/os/Parcel:recycle	()V
    //   72: aload_1
    //   73: athrow
    // Local variable table:
    //   start	length	slot	name	signature
    //   0	74	0	this	fir
    //   0	74	1	paramfim	fim
    //   3	66	2	localParcel1	Parcel
    //   7	58	3	localParcel2	Parcel
    // Exception table:
    //   from	to	target	type
    //   8	14	63	finally
    //   18	25	63	finally
    //   25	49	63	finally
  }
  
  /* Error */
  public final void b(fiv paramfiv)
  {
    // Byte code:
    //   0: invokestatic 22	android/os/Parcel:obtain	()Landroid/os/Parcel;
    //   3: astore_2
    //   4: invokestatic 22	android/os/Parcel:obtain	()Landroid/os/Parcel;
    //   7: astore_3
    //   8: aload_2
    //   9: ldc 24
    //   11: invokevirtual 28	android/os/Parcel:writeInterfaceToken	(Ljava/lang/String;)V
    //   14: aload_1
    //   15: ifnull +43 -> 58
    //   18: aload_1
    //   19: invokeinterface 58 1 0
    //   24: astore_1
    //   25: aload_2
    //   26: aload_1
    //   27: invokevirtual 54	android/os/Parcel:writeStrongBinder	(Landroid/os/IBinder;)V
    //   30: aload_0
    //   31: getfield 15	fir:a	Landroid/os/IBinder;
    //   34: bipush 35
    //   36: aload_2
    //   37: aload_3
    //   38: iconst_0
    //   39: invokeinterface 34 5 0
    //   44: pop
    //   45: aload_3
    //   46: invokevirtual 37	android/os/Parcel:readException	()V
    //   49: aload_3
    //   50: invokevirtual 40	android/os/Parcel:recycle	()V
    //   53: aload_2
    //   54: invokevirtual 40	android/os/Parcel:recycle	()V
    //   57: return
    //   58: aconst_null
    //   59: astore_1
    //   60: goto -35 -> 25
    //   63: astore_1
    //   64: aload_3
    //   65: invokevirtual 40	android/os/Parcel:recycle	()V
    //   68: aload_2
    //   69: invokevirtual 40	android/os/Parcel:recycle	()V
    //   72: aload_1
    //   73: athrow
    // Local variable table:
    //   start	length	slot	name	signature
    //   0	74	0	this	fir
    //   0	74	1	paramfiv	fiv
    //   3	66	2	localParcel1	Parcel
    //   7	58	3	localParcel2	Parcel
    // Exception table:
    //   from	to	target	type
    //   8	14	63	finally
    //   18	25	63	finally
    //   25	49	63	finally
  }
  
  /* Error */
  public final void b(String paramString, fhu paramfhu)
  {
    // Byte code:
    //   0: invokestatic 22	android/os/Parcel:obtain	()Landroid/os/Parcel;
    //   3: astore_3
    //   4: invokestatic 22	android/os/Parcel:obtain	()Landroid/os/Parcel;
    //   7: astore 4
    //   9: aload_3
    //   10: ldc 24
    //   12: invokevirtual 28	android/os/Parcel:writeInterfaceToken	(Ljava/lang/String;)V
    //   15: aload_3
    //   16: aload_1
    //   17: invokevirtual 111	android/os/Parcel:writeString	(Ljava/lang/String;)V
    //   20: aload_2
    //   21: ifnull +46 -> 67
    //   24: aload_2
    //   25: invokeinterface 129 1 0
    //   30: astore_1
    //   31: aload_3
    //   32: aload_1
    //   33: invokevirtual 54	android/os/Parcel:writeStrongBinder	(Landroid/os/IBinder;)V
    //   36: aload_0
    //   37: getfield 15	fir:a	Landroid/os/IBinder;
    //   40: bipush 13
    //   42: aload_3
    //   43: aload 4
    //   45: iconst_0
    //   46: invokeinterface 34 5 0
    //   51: pop
    //   52: aload 4
    //   54: invokevirtual 37	android/os/Parcel:readException	()V
    //   57: aload 4
    //   59: invokevirtual 40	android/os/Parcel:recycle	()V
    //   62: aload_3
    //   63: invokevirtual 40	android/os/Parcel:recycle	()V
    //   66: return
    //   67: aconst_null
    //   68: astore_1
    //   69: goto -38 -> 31
    //   72: astore_1
    //   73: aload 4
    //   75: invokevirtual 40	android/os/Parcel:recycle	()V
    //   78: aload_3
    //   79: invokevirtual 40	android/os/Parcel:recycle	()V
    //   82: aload_1
    //   83: athrow
    // Local variable table:
    //   start	length	slot	name	signature
    //   0	84	0	this	fir
    //   0	84	1	paramString	String
    //   0	84	2	paramfhu	fhu
    //   3	76	3	localParcel1	Parcel
    //   7	67	4	localParcel2	Parcel
    // Exception table:
    //   from	to	target	type
    //   9	20	72	finally
    //   24	31	72	finally
    //   31	57	72	finally
  }
  
  /* Error */
  public final void b(String paramString, fim paramfim)
  {
    // Byte code:
    //   0: invokestatic 22	android/os/Parcel:obtain	()Landroid/os/Parcel;
    //   3: astore_3
    //   4: invokestatic 22	android/os/Parcel:obtain	()Landroid/os/Parcel;
    //   7: astore 4
    //   9: aload_3
    //   10: ldc 24
    //   12: invokevirtual 28	android/os/Parcel:writeInterfaceToken	(Ljava/lang/String;)V
    //   15: aload_3
    //   16: aload_1
    //   17: invokevirtual 111	android/os/Parcel:writeString	(Ljava/lang/String;)V
    //   20: aload_2
    //   21: ifnull +46 -> 67
    //   24: aload_2
    //   25: invokeinterface 106 1 0
    //   30: astore_1
    //   31: aload_3
    //   32: aload_1
    //   33: invokevirtual 54	android/os/Parcel:writeStrongBinder	(Landroid/os/IBinder;)V
    //   36: aload_0
    //   37: getfield 15	fir:a	Landroid/os/IBinder;
    //   40: bipush 8
    //   42: aload_3
    //   43: aload 4
    //   45: iconst_0
    //   46: invokeinterface 34 5 0
    //   51: pop
    //   52: aload 4
    //   54: invokevirtual 37	android/os/Parcel:readException	()V
    //   57: aload 4
    //   59: invokevirtual 40	android/os/Parcel:recycle	()V
    //   62: aload_3
    //   63: invokevirtual 40	android/os/Parcel:recycle	()V
    //   66: return
    //   67: aconst_null
    //   68: astore_1
    //   69: goto -38 -> 31
    //   72: astore_1
    //   73: aload 4
    //   75: invokevirtual 40	android/os/Parcel:recycle	()V
    //   78: aload_3
    //   79: invokevirtual 40	android/os/Parcel:recycle	()V
    //   82: aload_1
    //   83: athrow
    // Local variable table:
    //   start	length	slot	name	signature
    //   0	84	0	this	fir
    //   0	84	1	paramString	String
    //   0	84	2	paramfim	fim
    //   3	76	3	localParcel1	Parcel
    //   7	67	4	localParcel2	Parcel
    // Exception table:
    //   from	to	target	type
    //   9	20	72	finally
    //   24	31	72	finally
    //   31	57	72	finally
  }
  
  /* Error */
  public final void b(String paramString, fis paramfis)
  {
    // Byte code:
    //   0: invokestatic 22	android/os/Parcel:obtain	()Landroid/os/Parcel;
    //   3: astore_3
    //   4: invokestatic 22	android/os/Parcel:obtain	()Landroid/os/Parcel;
    //   7: astore 4
    //   9: aload_3
    //   10: ldc 24
    //   12: invokevirtual 28	android/os/Parcel:writeInterfaceToken	(Ljava/lang/String;)V
    //   15: aload_3
    //   16: aload_1
    //   17: invokevirtual 111	android/os/Parcel:writeString	(Ljava/lang/String;)V
    //   20: aload_2
    //   21: ifnull +46 -> 67
    //   24: aload_2
    //   25: invokeinterface 81 1 0
    //   30: astore_1
    //   31: aload_3
    //   32: aload_1
    //   33: invokevirtual 54	android/os/Parcel:writeStrongBinder	(Landroid/os/IBinder;)V
    //   36: aload_0
    //   37: getfield 15	fir:a	Landroid/os/IBinder;
    //   40: bipush 9
    //   42: aload_3
    //   43: aload 4
    //   45: iconst_0
    //   46: invokeinterface 34 5 0
    //   51: pop
    //   52: aload 4
    //   54: invokevirtual 37	android/os/Parcel:readException	()V
    //   57: aload 4
    //   59: invokevirtual 40	android/os/Parcel:recycle	()V
    //   62: aload_3
    //   63: invokevirtual 40	android/os/Parcel:recycle	()V
    //   66: return
    //   67: aconst_null
    //   68: astore_1
    //   69: goto -38 -> 31
    //   72: astore_1
    //   73: aload 4
    //   75: invokevirtual 40	android/os/Parcel:recycle	()V
    //   78: aload_3
    //   79: invokevirtual 40	android/os/Parcel:recycle	()V
    //   82: aload_1
    //   83: athrow
    // Local variable table:
    //   start	length	slot	name	signature
    //   0	84	0	this	fir
    //   0	84	1	paramString	String
    //   0	84	2	paramfis	fis
    //   3	76	3	localParcel1	Parcel
    //   7	67	4	localParcel2	Parcel
    // Exception table:
    //   from	to	target	type
    //   9	20	72	finally
    //   24	31	72	finally
    //   31	57	72	finally
  }
  
  /* Error */
  public final void b(String paramString, fiv paramfiv)
  {
    // Byte code:
    //   0: invokestatic 22	android/os/Parcel:obtain	()Landroid/os/Parcel;
    //   3: astore_3
    //   4: invokestatic 22	android/os/Parcel:obtain	()Landroid/os/Parcel;
    //   7: astore 4
    //   9: aload_3
    //   10: ldc 24
    //   12: invokevirtual 28	android/os/Parcel:writeInterfaceToken	(Ljava/lang/String;)V
    //   15: aload_3
    //   16: aload_1
    //   17: invokevirtual 111	android/os/Parcel:writeString	(Ljava/lang/String;)V
    //   20: aload_2
    //   21: ifnull +46 -> 67
    //   24: aload_2
    //   25: invokeinterface 58 1 0
    //   30: astore_1
    //   31: aload_3
    //   32: aload_1
    //   33: invokevirtual 54	android/os/Parcel:writeStrongBinder	(Landroid/os/IBinder;)V
    //   36: aload_0
    //   37: getfield 15	fir:a	Landroid/os/IBinder;
    //   40: bipush 39
    //   42: aload_3
    //   43: aload 4
    //   45: iconst_0
    //   46: invokeinterface 34 5 0
    //   51: pop
    //   52: aload 4
    //   54: invokevirtual 37	android/os/Parcel:readException	()V
    //   57: aload 4
    //   59: invokevirtual 40	android/os/Parcel:recycle	()V
    //   62: aload_3
    //   63: invokevirtual 40	android/os/Parcel:recycle	()V
    //   66: return
    //   67: aconst_null
    //   68: astore_1
    //   69: goto -38 -> 31
    //   72: astore_1
    //   73: aload 4
    //   75: invokevirtual 40	android/os/Parcel:recycle	()V
    //   78: aload_3
    //   79: invokevirtual 40	android/os/Parcel:recycle	()V
    //   82: aload_1
    //   83: athrow
    // Local variable table:
    //   start	length	slot	name	signature
    //   0	84	0	this	fir
    //   0	84	1	paramString	String
    //   0	84	2	paramfiv	fiv
    //   3	76	3	localParcel1	Parcel
    //   7	67	4	localParcel2	Parcel
    // Exception table:
    //   from	to	target	type
    //   9	20	72	finally
    //   24	31	72	finally
    //   31	57	72	finally
  }
  
  /* Error */
  public final void b(String paramString1, String paramString2, fhu paramfhu)
  {
    // Byte code:
    //   0: invokestatic 22	android/os/Parcel:obtain	()Landroid/os/Parcel;
    //   3: astore 4
    //   5: invokestatic 22	android/os/Parcel:obtain	()Landroid/os/Parcel;
    //   8: astore 5
    //   10: aload 4
    //   12: ldc 24
    //   14: invokevirtual 28	android/os/Parcel:writeInterfaceToken	(Ljava/lang/String;)V
    //   17: aload 4
    //   19: aload_1
    //   20: invokevirtual 111	android/os/Parcel:writeString	(Ljava/lang/String;)V
    //   23: aload 4
    //   25: aload_2
    //   26: invokevirtual 111	android/os/Parcel:writeString	(Ljava/lang/String;)V
    //   29: aload_3
    //   30: ifnull +49 -> 79
    //   33: aload_3
    //   34: invokeinterface 129 1 0
    //   39: astore_1
    //   40: aload 4
    //   42: aload_1
    //   43: invokevirtual 54	android/os/Parcel:writeStrongBinder	(Landroid/os/IBinder;)V
    //   46: aload_0
    //   47: getfield 15	fir:a	Landroid/os/IBinder;
    //   50: bipush 42
    //   52: aload 4
    //   54: aload 5
    //   56: iconst_0
    //   57: invokeinterface 34 5 0
    //   62: pop
    //   63: aload 5
    //   65: invokevirtual 37	android/os/Parcel:readException	()V
    //   68: aload 5
    //   70: invokevirtual 40	android/os/Parcel:recycle	()V
    //   73: aload 4
    //   75: invokevirtual 40	android/os/Parcel:recycle	()V
    //   78: return
    //   79: aconst_null
    //   80: astore_1
    //   81: goto -41 -> 40
    //   84: astore_1
    //   85: aload 5
    //   87: invokevirtual 40	android/os/Parcel:recycle	()V
    //   90: aload 4
    //   92: invokevirtual 40	android/os/Parcel:recycle	()V
    //   95: aload_1
    //   96: athrow
    // Local variable table:
    //   start	length	slot	name	signature
    //   0	97	0	this	fir
    //   0	97	1	paramString1	String
    //   0	97	2	paramString2	String
    //   0	97	3	paramfhu	fhu
    //   3	88	4	localParcel1	Parcel
    //   8	78	5	localParcel2	Parcel
    // Exception table:
    //   from	to	target	type
    //   10	29	84	finally
    //   33	40	84	finally
    //   40	68	84	finally
  }
  
  /* Error */
  public final void c(fhl paramfhl)
  {
    // Byte code:
    //   0: invokestatic 22	android/os/Parcel:obtain	()Landroid/os/Parcel;
    //   3: astore_2
    //   4: invokestatic 22	android/os/Parcel:obtain	()Landroid/os/Parcel;
    //   7: astore_3
    //   8: aload_2
    //   9: ldc 24
    //   11: invokevirtual 28	android/os/Parcel:writeInterfaceToken	(Ljava/lang/String;)V
    //   14: aload_1
    //   15: ifnull +43 -> 58
    //   18: aload_1
    //   19: invokeinterface 85 1 0
    //   24: astore_1
    //   25: aload_2
    //   26: aload_1
    //   27: invokevirtual 54	android/os/Parcel:writeStrongBinder	(Landroid/os/IBinder;)V
    //   30: aload_0
    //   31: getfield 15	fir:a	Landroid/os/IBinder;
    //   34: bipush 45
    //   36: aload_2
    //   37: aload_3
    //   38: iconst_0
    //   39: invokeinterface 34 5 0
    //   44: pop
    //   45: aload_3
    //   46: invokevirtual 37	android/os/Parcel:readException	()V
    //   49: aload_3
    //   50: invokevirtual 40	android/os/Parcel:recycle	()V
    //   53: aload_2
    //   54: invokevirtual 40	android/os/Parcel:recycle	()V
    //   57: return
    //   58: aconst_null
    //   59: astore_1
    //   60: goto -35 -> 25
    //   63: astore_1
    //   64: aload_3
    //   65: invokevirtual 40	android/os/Parcel:recycle	()V
    //   68: aload_2
    //   69: invokevirtual 40	android/os/Parcel:recycle	()V
    //   72: aload_1
    //   73: athrow
    // Local variable table:
    //   start	length	slot	name	signature
    //   0	74	0	this	fir
    //   0	74	1	paramfhl	fhl
    //   3	66	2	localParcel1	Parcel
    //   7	58	3	localParcel2	Parcel
    // Exception table:
    //   from	to	target	type
    //   8	14	63	finally
    //   18	25	63	finally
    //   25	49	63	finally
  }
  
  /* Error */
  public final void c(fiv paramfiv)
  {
    // Byte code:
    //   0: invokestatic 22	android/os/Parcel:obtain	()Landroid/os/Parcel;
    //   3: astore_2
    //   4: invokestatic 22	android/os/Parcel:obtain	()Landroid/os/Parcel;
    //   7: astore_3
    //   8: aload_2
    //   9: ldc 24
    //   11: invokevirtual 28	android/os/Parcel:writeInterfaceToken	(Ljava/lang/String;)V
    //   14: aload_1
    //   15: ifnull +43 -> 58
    //   18: aload_1
    //   19: invokeinterface 58 1 0
    //   24: astore_1
    //   25: aload_2
    //   26: aload_1
    //   27: invokevirtual 54	android/os/Parcel:writeStrongBinder	(Landroid/os/IBinder;)V
    //   30: aload_0
    //   31: getfield 15	fir:a	Landroid/os/IBinder;
    //   34: bipush 49
    //   36: aload_2
    //   37: aload_3
    //   38: iconst_0
    //   39: invokeinterface 34 5 0
    //   44: pop
    //   45: aload_3
    //   46: invokevirtual 37	android/os/Parcel:readException	()V
    //   49: aload_3
    //   50: invokevirtual 40	android/os/Parcel:recycle	()V
    //   53: aload_2
    //   54: invokevirtual 40	android/os/Parcel:recycle	()V
    //   57: return
    //   58: aconst_null
    //   59: astore_1
    //   60: goto -35 -> 25
    //   63: astore_1
    //   64: aload_3
    //   65: invokevirtual 40	android/os/Parcel:recycle	()V
    //   68: aload_2
    //   69: invokevirtual 40	android/os/Parcel:recycle	()V
    //   72: aload_1
    //   73: athrow
    // Local variable table:
    //   start	length	slot	name	signature
    //   0	74	0	this	fir
    //   0	74	1	paramfiv	fiv
    //   3	66	2	localParcel1	Parcel
    //   7	58	3	localParcel2	Parcel
    // Exception table:
    //   from	to	target	type
    //   8	14	63	finally
    //   18	25	63	finally
    //   25	49	63	finally
  }
  
  /* Error */
  public final void c(String paramString, fim paramfim)
  {
    // Byte code:
    //   0: invokestatic 22	android/os/Parcel:obtain	()Landroid/os/Parcel;
    //   3: astore_3
    //   4: invokestatic 22	android/os/Parcel:obtain	()Landroid/os/Parcel;
    //   7: astore 4
    //   9: aload_3
    //   10: ldc 24
    //   12: invokevirtual 28	android/os/Parcel:writeInterfaceToken	(Ljava/lang/String;)V
    //   15: aload_3
    //   16: aload_1
    //   17: invokevirtual 111	android/os/Parcel:writeString	(Ljava/lang/String;)V
    //   20: aload_2
    //   21: ifnull +46 -> 67
    //   24: aload_2
    //   25: invokeinterface 106 1 0
    //   30: astore_1
    //   31: aload_3
    //   32: aload_1
    //   33: invokevirtual 54	android/os/Parcel:writeStrongBinder	(Landroid/os/IBinder;)V
    //   36: aload_0
    //   37: getfield 15	fir:a	Landroid/os/IBinder;
    //   40: bipush 14
    //   42: aload_3
    //   43: aload 4
    //   45: iconst_0
    //   46: invokeinterface 34 5 0
    //   51: pop
    //   52: aload 4
    //   54: invokevirtual 37	android/os/Parcel:readException	()V
    //   57: aload 4
    //   59: invokevirtual 40	android/os/Parcel:recycle	()V
    //   62: aload_3
    //   63: invokevirtual 40	android/os/Parcel:recycle	()V
    //   66: return
    //   67: aconst_null
    //   68: astore_1
    //   69: goto -38 -> 31
    //   72: astore_1
    //   73: aload 4
    //   75: invokevirtual 40	android/os/Parcel:recycle	()V
    //   78: aload_3
    //   79: invokevirtual 40	android/os/Parcel:recycle	()V
    //   82: aload_1
    //   83: athrow
    // Local variable table:
    //   start	length	slot	name	signature
    //   0	84	0	this	fir
    //   0	84	1	paramString	String
    //   0	84	2	paramfim	fim
    //   3	76	3	localParcel1	Parcel
    //   7	67	4	localParcel2	Parcel
    // Exception table:
    //   from	to	target	type
    //   9	20	72	finally
    //   24	31	72	finally
    //   31	57	72	finally
  }
  
  /* Error */
  public final void d(fhl paramfhl)
  {
    // Byte code:
    //   0: invokestatic 22	android/os/Parcel:obtain	()Landroid/os/Parcel;
    //   3: astore_2
    //   4: invokestatic 22	android/os/Parcel:obtain	()Landroid/os/Parcel;
    //   7: astore_3
    //   8: aload_2
    //   9: ldc 24
    //   11: invokevirtual 28	android/os/Parcel:writeInterfaceToken	(Ljava/lang/String;)V
    //   14: aload_1
    //   15: ifnull +43 -> 58
    //   18: aload_1
    //   19: invokeinterface 85 1 0
    //   24: astore_1
    //   25: aload_2
    //   26: aload_1
    //   27: invokevirtual 54	android/os/Parcel:writeStrongBinder	(Landroid/os/IBinder;)V
    //   30: aload_0
    //   31: getfield 15	fir:a	Landroid/os/IBinder;
    //   34: bipush 24
    //   36: aload_2
    //   37: aload_3
    //   38: iconst_0
    //   39: invokeinterface 34 5 0
    //   44: pop
    //   45: aload_3
    //   46: invokevirtual 37	android/os/Parcel:readException	()V
    //   49: aload_3
    //   50: invokevirtual 40	android/os/Parcel:recycle	()V
    //   53: aload_2
    //   54: invokevirtual 40	android/os/Parcel:recycle	()V
    //   57: return
    //   58: aconst_null
    //   59: astore_1
    //   60: goto -35 -> 25
    //   63: astore_1
    //   64: aload_3
    //   65: invokevirtual 40	android/os/Parcel:recycle	()V
    //   68: aload_2
    //   69: invokevirtual 40	android/os/Parcel:recycle	()V
    //   72: aload_1
    //   73: athrow
    // Local variable table:
    //   start	length	slot	name	signature
    //   0	74	0	this	fir
    //   0	74	1	paramfhl	fhl
    //   3	66	2	localParcel1	Parcel
    //   7	58	3	localParcel2	Parcel
    // Exception table:
    //   from	to	target	type
    //   8	14	63	finally
    //   18	25	63	finally
    //   25	49	63	finally
  }
  
  /* Error */
  public final void e(fhl paramfhl)
  {
    // Byte code:
    //   0: invokestatic 22	android/os/Parcel:obtain	()Landroid/os/Parcel;
    //   3: astore_2
    //   4: invokestatic 22	android/os/Parcel:obtain	()Landroid/os/Parcel;
    //   7: astore_3
    //   8: aload_2
    //   9: ldc 24
    //   11: invokevirtual 28	android/os/Parcel:writeInterfaceToken	(Ljava/lang/String;)V
    //   14: aload_1
    //   15: ifnull +43 -> 58
    //   18: aload_1
    //   19: invokeinterface 85 1 0
    //   24: astore_1
    //   25: aload_2
    //   26: aload_1
    //   27: invokevirtual 54	android/os/Parcel:writeStrongBinder	(Landroid/os/IBinder;)V
    //   30: aload_0
    //   31: getfield 15	fir:a	Landroid/os/IBinder;
    //   34: bipush 25
    //   36: aload_2
    //   37: aload_3
    //   38: iconst_0
    //   39: invokeinterface 34 5 0
    //   44: pop
    //   45: aload_3
    //   46: invokevirtual 37	android/os/Parcel:readException	()V
    //   49: aload_3
    //   50: invokevirtual 40	android/os/Parcel:recycle	()V
    //   53: aload_2
    //   54: invokevirtual 40	android/os/Parcel:recycle	()V
    //   57: return
    //   58: aconst_null
    //   59: astore_1
    //   60: goto -35 -> 25
    //   63: astore_1
    //   64: aload_3
    //   65: invokevirtual 40	android/os/Parcel:recycle	()V
    //   68: aload_2
    //   69: invokevirtual 40	android/os/Parcel:recycle	()V
    //   72: aload_1
    //   73: athrow
    // Local variable table:
    //   start	length	slot	name	signature
    //   0	74	0	this	fir
    //   0	74	1	paramfhl	fhl
    //   3	66	2	localParcel1	Parcel
    //   7	58	3	localParcel2	Parcel
    // Exception table:
    //   from	to	target	type
    //   8	14	63	finally
    //   18	25	63	finally
    //   25	49	63	finally
  }
}

/* Location:
 * Qualified Name:     fir
 * Java Class Version: 6 (50.0)
 * JD-Core Version:    0.7.1
 */