import android.net.Uri;
import android.os.Bundle;
import android.os.IBinder;
import android.os.Parcel;
import android.os.Parcelable.Creator;
import com.google.android.gms.people.identity.internal.AccountToken;
import com.google.android.gms.people.identity.internal.ParcelableGetOptions;
import com.google.android.gms.people.identity.internal.ParcelableListOptions;
import com.google.android.gms.people.internal.ParcelableLoadImageOptions;
import com.google.android.gms.people.model.AvatarReference;
import java.util.List;

final class fwy
  implements fww
{
  private IBinder a;
  
  fwy(IBinder paramIBinder)
  {
    a = paramIBinder;
  }
  
  public final Bundle a(Uri paramUri)
  {
    Parcel localParcel1 = Parcel.obtain();
    Parcel localParcel2 = Parcel.obtain();
    for (;;)
    {
      try
      {
        localParcel1.writeInterfaceToken("com.google.android.gms.people.internal.IPeopleService");
        if (paramUri != null)
        {
          localParcel1.writeInt(1);
          paramUri.writeToParcel(localParcel1, 0);
          a.transact(8, localParcel1, localParcel2, 0);
          localParcel2.readException();
          if (localParcel2.readInt() != 0)
          {
            paramUri = (Bundle)Bundle.CREATOR.createFromParcel(localParcel2);
            return paramUri;
          }
        }
        else
        {
          localParcel1.writeInt(0);
          continue;
        }
        paramUri = null;
      }
      finally
      {
        localParcel2.recycle();
        localParcel1.recycle();
      }
    }
  }
  
  /* Error */
  public final Bundle a(fwt paramfwt, boolean paramBoolean, String paramString1, String paramString2, int paramInt)
  {
    // Byte code:
    //   0: aconst_null
    //   1: astore 7
    //   3: iconst_0
    //   4: istore 6
    //   6: invokestatic 23	android/os/Parcel:obtain	()Landroid/os/Parcel;
    //   9: astore 8
    //   11: invokestatic 23	android/os/Parcel:obtain	()Landroid/os/Parcel;
    //   14: astore 9
    //   16: aload 8
    //   18: ldc 25
    //   20: invokevirtual 29	android/os/Parcel:writeInterfaceToken	(Ljava/lang/String;)V
    //   23: aload_1
    //   24: ifnull +109 -> 133
    //   27: aload_1
    //   28: invokeinterface 74 1 0
    //   33: astore_1
    //   34: aload 8
    //   36: aload_1
    //   37: invokevirtual 77	android/os/Parcel:writeStrongBinder	(Landroid/os/IBinder;)V
    //   40: iload_2
    //   41: ifeq +6 -> 47
    //   44: iconst_1
    //   45: istore 6
    //   47: aload 8
    //   49: iload 6
    //   51: invokevirtual 33	android/os/Parcel:writeInt	(I)V
    //   54: aload 8
    //   56: aload_3
    //   57: invokevirtual 80	android/os/Parcel:writeString	(Ljava/lang/String;)V
    //   60: aload 8
    //   62: aload 4
    //   64: invokevirtual 80	android/os/Parcel:writeString	(Ljava/lang/String;)V
    //   67: aload 8
    //   69: iload 5
    //   71: invokevirtual 33	android/os/Parcel:writeInt	(I)V
    //   74: aload_0
    //   75: getfield 15	fwy:a	Landroid/os/IBinder;
    //   78: bipush 11
    //   80: aload 8
    //   82: aload 9
    //   84: iconst_0
    //   85: invokeinterface 45 5 0
    //   90: pop
    //   91: aload 9
    //   93: invokevirtual 48	android/os/Parcel:readException	()V
    //   96: aload 7
    //   98: astore_1
    //   99: aload 9
    //   101: invokevirtual 52	android/os/Parcel:readInt	()I
    //   104: ifeq +17 -> 121
    //   107: getstatic 58	android/os/Bundle:CREATOR	Landroid/os/Parcelable$Creator;
    //   110: aload 9
    //   112: invokeinterface 64 2 0
    //   117: checkcast 54	android/os/Bundle
    //   120: astore_1
    //   121: aload 9
    //   123: invokevirtual 67	android/os/Parcel:recycle	()V
    //   126: aload 8
    //   128: invokevirtual 67	android/os/Parcel:recycle	()V
    //   131: aload_1
    //   132: areturn
    //   133: aconst_null
    //   134: astore_1
    //   135: goto -101 -> 34
    //   138: astore_1
    //   139: aload 9
    //   141: invokevirtual 67	android/os/Parcel:recycle	()V
    //   144: aload 8
    //   146: invokevirtual 67	android/os/Parcel:recycle	()V
    //   149: aload_1
    //   150: athrow
    // Local variable table:
    //   start	length	slot	name	signature
    //   0	151	0	this	fwy
    //   0	151	1	paramfwt	fwt
    //   0	151	2	paramBoolean	boolean
    //   0	151	3	paramString1	String
    //   0	151	4	paramString2	String
    //   0	151	5	paramInt	int
    //   4	46	6	i	int
    //   1	96	7	localObject	Object
    //   9	136	8	localParcel1	Parcel
    //   14	126	9	localParcel2	Parcel
    // Exception table:
    //   from	to	target	type
    //   16	23	138	finally
    //   27	34	138	finally
    //   34	40	138	finally
    //   47	96	138	finally
    //   99	121	138	finally
  }
  
  /* Error */
  public final Bundle a(String paramString1, String paramString2)
  {
    // Byte code:
    //   0: invokestatic 23	android/os/Parcel:obtain	()Landroid/os/Parcel;
    //   3: astore_3
    //   4: invokestatic 23	android/os/Parcel:obtain	()Landroid/os/Parcel;
    //   7: astore 4
    //   9: aload_3
    //   10: ldc 25
    //   12: invokevirtual 29	android/os/Parcel:writeInterfaceToken	(Ljava/lang/String;)V
    //   15: aload_3
    //   16: aload_1
    //   17: invokevirtual 80	android/os/Parcel:writeString	(Ljava/lang/String;)V
    //   20: aload_3
    //   21: aload_2
    //   22: invokevirtual 80	android/os/Parcel:writeString	(Ljava/lang/String;)V
    //   25: aload_0
    //   26: getfield 15	fwy:a	Landroid/os/IBinder;
    //   29: bipush 12
    //   31: aload_3
    //   32: aload 4
    //   34: iconst_0
    //   35: invokeinterface 45 5 0
    //   40: pop
    //   41: aload 4
    //   43: invokevirtual 48	android/os/Parcel:readException	()V
    //   46: aload 4
    //   48: invokevirtual 52	android/os/Parcel:readInt	()I
    //   51: ifeq +28 -> 79
    //   54: getstatic 58	android/os/Bundle:CREATOR	Landroid/os/Parcelable$Creator;
    //   57: aload 4
    //   59: invokeinterface 64 2 0
    //   64: checkcast 54	android/os/Bundle
    //   67: astore_1
    //   68: aload 4
    //   70: invokevirtual 67	android/os/Parcel:recycle	()V
    //   73: aload_3
    //   74: invokevirtual 67	android/os/Parcel:recycle	()V
    //   77: aload_1
    //   78: areturn
    //   79: aconst_null
    //   80: astore_1
    //   81: goto -13 -> 68
    //   84: astore_1
    //   85: aload 4
    //   87: invokevirtual 67	android/os/Parcel:recycle	()V
    //   90: aload_3
    //   91: invokevirtual 67	android/os/Parcel:recycle	()V
    //   94: aload_1
    //   95: athrow
    // Local variable table:
    //   start	length	slot	name	signature
    //   0	96	0	this	fwy
    //   0	96	1	paramString1	String
    //   0	96	2	paramString2	String
    //   3	88	3	localParcel1	Parcel
    //   7	79	4	localParcel2	Parcel
    // Exception table:
    //   from	to	target	type
    //   9	68	84	finally
  }
  
  /* Error */
  public final Bundle a(String paramString1, String paramString2, long paramLong)
  {
    // Byte code:
    //   0: invokestatic 23	android/os/Parcel:obtain	()Landroid/os/Parcel;
    //   3: astore 5
    //   5: invokestatic 23	android/os/Parcel:obtain	()Landroid/os/Parcel;
    //   8: astore 6
    //   10: aload 5
    //   12: ldc 25
    //   14: invokevirtual 29	android/os/Parcel:writeInterfaceToken	(Ljava/lang/String;)V
    //   17: aload 5
    //   19: aload_1
    //   20: invokevirtual 80	android/os/Parcel:writeString	(Ljava/lang/String;)V
    //   23: aload 5
    //   25: aload_2
    //   26: invokevirtual 80	android/os/Parcel:writeString	(Ljava/lang/String;)V
    //   29: aload 5
    //   31: lload_3
    //   32: invokevirtual 86	android/os/Parcel:writeLong	(J)V
    //   35: aload_0
    //   36: getfield 15	fwy:a	Landroid/os/IBinder;
    //   39: bipush 20
    //   41: aload 5
    //   43: aload 6
    //   45: iconst_0
    //   46: invokeinterface 45 5 0
    //   51: pop
    //   52: aload 6
    //   54: invokevirtual 48	android/os/Parcel:readException	()V
    //   57: aload 6
    //   59: invokevirtual 52	android/os/Parcel:readInt	()I
    //   62: ifeq +29 -> 91
    //   65: getstatic 58	android/os/Bundle:CREATOR	Landroid/os/Parcelable$Creator;
    //   68: aload 6
    //   70: invokeinterface 64 2 0
    //   75: checkcast 54	android/os/Bundle
    //   78: astore_1
    //   79: aload 6
    //   81: invokevirtual 67	android/os/Parcel:recycle	()V
    //   84: aload 5
    //   86: invokevirtual 67	android/os/Parcel:recycle	()V
    //   89: aload_1
    //   90: areturn
    //   91: aconst_null
    //   92: astore_1
    //   93: goto -14 -> 79
    //   96: astore_1
    //   97: aload 6
    //   99: invokevirtual 67	android/os/Parcel:recycle	()V
    //   102: aload 5
    //   104: invokevirtual 67	android/os/Parcel:recycle	()V
    //   107: aload_1
    //   108: athrow
    // Local variable table:
    //   start	length	slot	name	signature
    //   0	109	0	this	fwy
    //   0	109	1	paramString1	String
    //   0	109	2	paramString2	String
    //   0	109	3	paramLong	long
    //   3	100	5	localParcel1	Parcel
    //   8	90	6	localParcel2	Parcel
    // Exception table:
    //   from	to	target	type
    //   10	79	96	finally
  }
  
  /* Error */
  public final Bundle a(String paramString1, String paramString2, long paramLong, boolean paramBoolean)
  {
    // Byte code:
    //   0: iconst_0
    //   1: istore 6
    //   3: invokestatic 23	android/os/Parcel:obtain	()Landroid/os/Parcel;
    //   6: astore 7
    //   8: invokestatic 23	android/os/Parcel:obtain	()Landroid/os/Parcel;
    //   11: astore 8
    //   13: aload 7
    //   15: ldc 25
    //   17: invokevirtual 29	android/os/Parcel:writeInterfaceToken	(Ljava/lang/String;)V
    //   20: aload 7
    //   22: aload_1
    //   23: invokevirtual 80	android/os/Parcel:writeString	(Ljava/lang/String;)V
    //   26: aload 7
    //   28: aload_2
    //   29: invokevirtual 80	android/os/Parcel:writeString	(Ljava/lang/String;)V
    //   32: aload 7
    //   34: lload_3
    //   35: invokevirtual 86	android/os/Parcel:writeLong	(J)V
    //   38: iload 5
    //   40: ifeq +6 -> 46
    //   43: iconst_1
    //   44: istore 6
    //   46: aload 7
    //   48: iload 6
    //   50: invokevirtual 33	android/os/Parcel:writeInt	(I)V
    //   53: aload_0
    //   54: getfield 15	fwy:a	Landroid/os/IBinder;
    //   57: bipush 26
    //   59: aload 7
    //   61: aload 8
    //   63: iconst_0
    //   64: invokeinterface 45 5 0
    //   69: pop
    //   70: aload 8
    //   72: invokevirtual 48	android/os/Parcel:readException	()V
    //   75: aload 8
    //   77: invokevirtual 52	android/os/Parcel:readInt	()I
    //   80: ifeq +29 -> 109
    //   83: getstatic 58	android/os/Bundle:CREATOR	Landroid/os/Parcelable$Creator;
    //   86: aload 8
    //   88: invokeinterface 64 2 0
    //   93: checkcast 54	android/os/Bundle
    //   96: astore_1
    //   97: aload 8
    //   99: invokevirtual 67	android/os/Parcel:recycle	()V
    //   102: aload 7
    //   104: invokevirtual 67	android/os/Parcel:recycle	()V
    //   107: aload_1
    //   108: areturn
    //   109: aconst_null
    //   110: astore_1
    //   111: goto -14 -> 97
    //   114: astore_1
    //   115: aload 8
    //   117: invokevirtual 67	android/os/Parcel:recycle	()V
    //   120: aload 7
    //   122: invokevirtual 67	android/os/Parcel:recycle	()V
    //   125: aload_1
    //   126: athrow
    // Local variable table:
    //   start	length	slot	name	signature
    //   0	127	0	this	fwy
    //   0	127	1	paramString1	String
    //   0	127	2	paramString2	String
    //   0	127	3	paramLong	long
    //   0	127	5	paramBoolean	boolean
    //   1	48	6	i	int
    //   6	115	7	localParcel1	Parcel
    //   11	105	8	localParcel2	Parcel
    // Exception table:
    //   from	to	target	type
    //   13	38	114	finally
    //   46	97	114	finally
  }
  
  /* Error */
  public final Bundle a(String paramString1, String paramString2, long paramLong, boolean paramBoolean1, boolean paramBoolean2)
  {
    // Byte code:
    //   0: iconst_1
    //   1: istore 8
    //   3: invokestatic 23	android/os/Parcel:obtain	()Landroid/os/Parcel;
    //   6: astore 9
    //   8: invokestatic 23	android/os/Parcel:obtain	()Landroid/os/Parcel;
    //   11: astore 10
    //   13: aload 9
    //   15: ldc 25
    //   17: invokevirtual 29	android/os/Parcel:writeInterfaceToken	(Ljava/lang/String;)V
    //   20: aload 9
    //   22: aload_1
    //   23: invokevirtual 80	android/os/Parcel:writeString	(Ljava/lang/String;)V
    //   26: aload 9
    //   28: aload_2
    //   29: invokevirtual 80	android/os/Parcel:writeString	(Ljava/lang/String;)V
    //   32: aload 9
    //   34: lload_3
    //   35: invokevirtual 86	android/os/Parcel:writeLong	(J)V
    //   38: iload 5
    //   40: ifeq +86 -> 126
    //   43: iconst_1
    //   44: istore 7
    //   46: aload 9
    //   48: iload 7
    //   50: invokevirtual 33	android/os/Parcel:writeInt	(I)V
    //   53: iload 6
    //   55: ifeq +77 -> 132
    //   58: iload 8
    //   60: istore 7
    //   62: aload 9
    //   64: iload 7
    //   66: invokevirtual 33	android/os/Parcel:writeInt	(I)V
    //   69: aload_0
    //   70: getfield 15	fwy:a	Landroid/os/IBinder;
    //   73: sipush 205
    //   76: aload 9
    //   78: aload 10
    //   80: iconst_0
    //   81: invokeinterface 45 5 0
    //   86: pop
    //   87: aload 10
    //   89: invokevirtual 48	android/os/Parcel:readException	()V
    //   92: aload 10
    //   94: invokevirtual 52	android/os/Parcel:readInt	()I
    //   97: ifeq +41 -> 138
    //   100: getstatic 58	android/os/Bundle:CREATOR	Landroid/os/Parcelable$Creator;
    //   103: aload 10
    //   105: invokeinterface 64 2 0
    //   110: checkcast 54	android/os/Bundle
    //   113: astore_1
    //   114: aload 10
    //   116: invokevirtual 67	android/os/Parcel:recycle	()V
    //   119: aload 9
    //   121: invokevirtual 67	android/os/Parcel:recycle	()V
    //   124: aload_1
    //   125: areturn
    //   126: iconst_0
    //   127: istore 7
    //   129: goto -83 -> 46
    //   132: iconst_0
    //   133: istore 7
    //   135: goto -73 -> 62
    //   138: aconst_null
    //   139: astore_1
    //   140: goto -26 -> 114
    //   143: astore_1
    //   144: aload 10
    //   146: invokevirtual 67	android/os/Parcel:recycle	()V
    //   149: aload 9
    //   151: invokevirtual 67	android/os/Parcel:recycle	()V
    //   154: aload_1
    //   155: athrow
    // Local variable table:
    //   start	length	slot	name	signature
    //   0	156	0	this	fwy
    //   0	156	1	paramString1	String
    //   0	156	2	paramString2	String
    //   0	156	3	paramLong	long
    //   0	156	5	paramBoolean1	boolean
    //   0	156	6	paramBoolean2	boolean
    //   44	90	7	i	int
    //   1	58	8	j	int
    //   6	144	9	localParcel1	Parcel
    //   11	134	10	localParcel2	Parcel
    // Exception table:
    //   from	to	target	type
    //   13	38	143	finally
    //   46	53	143	finally
    //   62	114	143	finally
  }
  
  /* Error */
  public final enk a(fwt paramfwt, com.google.android.gms.common.data.DataHolder paramDataHolder, int paramInt1, int paramInt2, long paramLong)
  {
    // Byte code:
    //   0: invokestatic 23	android/os/Parcel:obtain	()Landroid/os/Parcel;
    //   3: astore 7
    //   5: invokestatic 23	android/os/Parcel:obtain	()Landroid/os/Parcel;
    //   8: astore 8
    //   10: aload 7
    //   12: ldc 25
    //   14: invokevirtual 29	android/os/Parcel:writeInterfaceToken	(Ljava/lang/String;)V
    //   17: aload_1
    //   18: ifnull +97 -> 115
    //   21: aload_1
    //   22: invokeinterface 74 1 0
    //   27: astore_1
    //   28: aload 7
    //   30: aload_1
    //   31: invokevirtual 77	android/os/Parcel:writeStrongBinder	(Landroid/os/IBinder;)V
    //   34: aload_2
    //   35: ifnull +85 -> 120
    //   38: aload 7
    //   40: iconst_1
    //   41: invokevirtual 33	android/os/Parcel:writeInt	(I)V
    //   44: aload_2
    //   45: aload 7
    //   47: iconst_0
    //   48: invokevirtual 92	com/google/android/gms/common/data/DataHolder:writeToParcel	(Landroid/os/Parcel;I)V
    //   51: aload 7
    //   53: iload_3
    //   54: invokevirtual 33	android/os/Parcel:writeInt	(I)V
    //   57: aload 7
    //   59: iload 4
    //   61: invokevirtual 33	android/os/Parcel:writeInt	(I)V
    //   64: aload 7
    //   66: lload 5
    //   68: invokevirtual 86	android/os/Parcel:writeLong	(J)V
    //   71: aload_0
    //   72: getfield 15	fwy:a	Landroid/os/IBinder;
    //   75: sipush 602
    //   78: aload 7
    //   80: aload 8
    //   82: iconst_0
    //   83: invokeinterface 45 5 0
    //   88: pop
    //   89: aload 8
    //   91: invokevirtual 48	android/os/Parcel:readException	()V
    //   94: aload 8
    //   96: invokevirtual 95	android/os/Parcel:readStrongBinder	()Landroid/os/IBinder;
    //   99: invokestatic 100	enl:a	(Landroid/os/IBinder;)Lenk;
    //   102: astore_1
    //   103: aload 8
    //   105: invokevirtual 67	android/os/Parcel:recycle	()V
    //   108: aload 7
    //   110: invokevirtual 67	android/os/Parcel:recycle	()V
    //   113: aload_1
    //   114: areturn
    //   115: aconst_null
    //   116: astore_1
    //   117: goto -89 -> 28
    //   120: aload 7
    //   122: iconst_0
    //   123: invokevirtual 33	android/os/Parcel:writeInt	(I)V
    //   126: goto -75 -> 51
    //   129: astore_1
    //   130: aload 8
    //   132: invokevirtual 67	android/os/Parcel:recycle	()V
    //   135: aload 7
    //   137: invokevirtual 67	android/os/Parcel:recycle	()V
    //   140: aload_1
    //   141: athrow
    // Local variable table:
    //   start	length	slot	name	signature
    //   0	142	0	this	fwy
    //   0	142	1	paramfwt	fwt
    //   0	142	2	paramDataHolder	com.google.android.gms.common.data.DataHolder
    //   0	142	3	paramInt1	int
    //   0	142	4	paramInt2	int
    //   0	142	5	paramLong	long
    //   3	133	7	localParcel1	Parcel
    //   8	123	8	localParcel2	Parcel
    // Exception table:
    //   from	to	target	type
    //   10	17	129	finally
    //   21	28	129	finally
    //   28	34	129	finally
    //   38	51	129	finally
    //   51	103	129	finally
    //   120	126	129	finally
  }
  
  public final enk a(fwt paramfwt, AccountToken paramAccountToken, ParcelableListOptions paramParcelableListOptions)
  {
    Parcel localParcel1 = Parcel.obtain();
    Parcel localParcel2 = Parcel.obtain();
    label139:
    for (;;)
    {
      try
      {
        localParcel1.writeInterfaceToken("com.google.android.gms.people.internal.IPeopleService");
        if (paramfwt != null)
        {
          paramfwt = paramfwt.asBinder();
          localParcel1.writeStrongBinder(paramfwt);
          if (paramAccountToken != null)
          {
            localParcel1.writeInt(1);
            paramAccountToken.writeToParcel(localParcel1, 0);
            if (paramParcelableListOptions == null) {
              break label139;
            }
            localParcel1.writeInt(1);
            paramParcelableListOptions.writeToParcel(localParcel1, 0);
            a.transact(601, localParcel1, localParcel2, 0);
            localParcel2.readException();
            paramfwt = enl.a(localParcel2.readStrongBinder());
            return paramfwt;
          }
        }
        else
        {
          paramfwt = null;
          continue;
        }
        localParcel1.writeInt(0);
        continue;
        localParcel1.writeInt(0);
      }
      finally
      {
        localParcel2.recycle();
        localParcel1.recycle();
      }
    }
  }
  
  public final enk a(fwt paramfwt, AvatarReference paramAvatarReference, ParcelableLoadImageOptions paramParcelableLoadImageOptions)
  {
    Parcel localParcel1 = Parcel.obtain();
    Parcel localParcel2 = Parcel.obtain();
    label139:
    for (;;)
    {
      try
      {
        localParcel1.writeInterfaceToken("com.google.android.gms.people.internal.IPeopleService");
        if (paramfwt != null)
        {
          paramfwt = paramfwt.asBinder();
          localParcel1.writeStrongBinder(paramfwt);
          if (paramAvatarReference != null)
          {
            localParcel1.writeInt(1);
            paramAvatarReference.writeToParcel(localParcel1, 0);
            if (paramParcelableLoadImageOptions == null) {
              break label139;
            }
            localParcel1.writeInt(1);
            paramParcelableLoadImageOptions.writeToParcel(localParcel1, 0);
            a.transact(508, localParcel1, localParcel2, 0);
            localParcel2.readException();
            paramfwt = enl.a(localParcel2.readStrongBinder());
            return paramfwt;
          }
        }
        else
        {
          paramfwt = null;
          continue;
        }
        localParcel1.writeInt(0);
        continue;
        localParcel1.writeInt(0);
      }
      finally
      {
        localParcel2.recycle();
        localParcel1.recycle();
      }
    }
  }
  
  /* Error */
  public final enk a(fwt paramfwt, String paramString, int paramInt)
  {
    // Byte code:
    //   0: invokestatic 23	android/os/Parcel:obtain	()Landroid/os/Parcel;
    //   3: astore 4
    //   5: invokestatic 23	android/os/Parcel:obtain	()Landroid/os/Parcel;
    //   8: astore 5
    //   10: aload 4
    //   12: ldc 25
    //   14: invokevirtual 29	android/os/Parcel:writeInterfaceToken	(Ljava/lang/String;)V
    //   17: aload_1
    //   18: ifnull +72 -> 90
    //   21: aload_1
    //   22: invokeinterface 74 1 0
    //   27: astore_1
    //   28: aload 4
    //   30: aload_1
    //   31: invokevirtual 77	android/os/Parcel:writeStrongBinder	(Landroid/os/IBinder;)V
    //   34: aload 4
    //   36: aload_2
    //   37: invokevirtual 80	android/os/Parcel:writeString	(Ljava/lang/String;)V
    //   40: aload 4
    //   42: iload_3
    //   43: invokevirtual 33	android/os/Parcel:writeInt	(I)V
    //   46: aload_0
    //   47: getfield 15	fwy:a	Landroid/os/IBinder;
    //   50: sipush 509
    //   53: aload 4
    //   55: aload 5
    //   57: iconst_0
    //   58: invokeinterface 45 5 0
    //   63: pop
    //   64: aload 5
    //   66: invokevirtual 48	android/os/Parcel:readException	()V
    //   69: aload 5
    //   71: invokevirtual 95	android/os/Parcel:readStrongBinder	()Landroid/os/IBinder;
    //   74: invokestatic 100	enl:a	(Landroid/os/IBinder;)Lenk;
    //   77: astore_1
    //   78: aload 5
    //   80: invokevirtual 67	android/os/Parcel:recycle	()V
    //   83: aload 4
    //   85: invokevirtual 67	android/os/Parcel:recycle	()V
    //   88: aload_1
    //   89: areturn
    //   90: aconst_null
    //   91: astore_1
    //   92: goto -64 -> 28
    //   95: astore_1
    //   96: aload 5
    //   98: invokevirtual 67	android/os/Parcel:recycle	()V
    //   101: aload 4
    //   103: invokevirtual 67	android/os/Parcel:recycle	()V
    //   106: aload_1
    //   107: athrow
    // Local variable table:
    //   start	length	slot	name	signature
    //   0	108	0	this	fwy
    //   0	108	1	paramfwt	fwt
    //   0	108	2	paramString	String
    //   0	108	3	paramInt	int
    //   3	99	4	localParcel1	Parcel
    //   8	89	5	localParcel2	Parcel
    // Exception table:
    //   from	to	target	type
    //   10	17	95	finally
    //   21	28	95	finally
    //   28	78	95	finally
  }
  
  /* Error */
  public final enk a(fwt paramfwt, String paramString1, String paramString2, boolean paramBoolean1, String paramString3, String paramString4, int paramInt1, int paramInt2, int paramInt3, boolean paramBoolean2)
  {
    // Byte code:
    //   0: iconst_1
    //   1: istore 12
    //   3: invokestatic 23	android/os/Parcel:obtain	()Landroid/os/Parcel;
    //   6: astore 13
    //   8: invokestatic 23	android/os/Parcel:obtain	()Landroid/os/Parcel;
    //   11: astore 14
    //   13: aload 13
    //   15: ldc 25
    //   17: invokevirtual 29	android/os/Parcel:writeInterfaceToken	(Ljava/lang/String;)V
    //   20: aload_1
    //   21: ifnull +138 -> 159
    //   24: aload_1
    //   25: invokeinterface 74 1 0
    //   30: astore_1
    //   31: aload 13
    //   33: aload_1
    //   34: invokevirtual 77	android/os/Parcel:writeStrongBinder	(Landroid/os/IBinder;)V
    //   37: aload 13
    //   39: aload_2
    //   40: invokevirtual 80	android/os/Parcel:writeString	(Ljava/lang/String;)V
    //   43: aload 13
    //   45: aload_3
    //   46: invokevirtual 80	android/os/Parcel:writeString	(Ljava/lang/String;)V
    //   49: iload 4
    //   51: ifeq +113 -> 164
    //   54: iconst_1
    //   55: istore 11
    //   57: aload 13
    //   59: iload 11
    //   61: invokevirtual 33	android/os/Parcel:writeInt	(I)V
    //   64: aload 13
    //   66: aload 5
    //   68: invokevirtual 80	android/os/Parcel:writeString	(Ljava/lang/String;)V
    //   71: aload 13
    //   73: aload 6
    //   75: invokevirtual 80	android/os/Parcel:writeString	(Ljava/lang/String;)V
    //   78: aload 13
    //   80: iload 7
    //   82: invokevirtual 33	android/os/Parcel:writeInt	(I)V
    //   85: aload 13
    //   87: iload 8
    //   89: invokevirtual 33	android/os/Parcel:writeInt	(I)V
    //   92: aload 13
    //   94: iload 9
    //   96: invokevirtual 33	android/os/Parcel:writeInt	(I)V
    //   99: iload 10
    //   101: ifeq +69 -> 170
    //   104: iload 12
    //   106: istore 7
    //   108: aload 13
    //   110: iload 7
    //   112: invokevirtual 33	android/os/Parcel:writeInt	(I)V
    //   115: aload_0
    //   116: getfield 15	fwy:a	Landroid/os/IBinder;
    //   119: sipush 507
    //   122: aload 13
    //   124: aload 14
    //   126: iconst_0
    //   127: invokeinterface 45 5 0
    //   132: pop
    //   133: aload 14
    //   135: invokevirtual 48	android/os/Parcel:readException	()V
    //   138: aload 14
    //   140: invokevirtual 95	android/os/Parcel:readStrongBinder	()Landroid/os/IBinder;
    //   143: invokestatic 100	enl:a	(Landroid/os/IBinder;)Lenk;
    //   146: astore_1
    //   147: aload 14
    //   149: invokevirtual 67	android/os/Parcel:recycle	()V
    //   152: aload 13
    //   154: invokevirtual 67	android/os/Parcel:recycle	()V
    //   157: aload_1
    //   158: areturn
    //   159: aconst_null
    //   160: astore_1
    //   161: goto -130 -> 31
    //   164: iconst_0
    //   165: istore 11
    //   167: goto -110 -> 57
    //   170: iconst_0
    //   171: istore 7
    //   173: goto -65 -> 108
    //   176: astore_1
    //   177: aload 14
    //   179: invokevirtual 67	android/os/Parcel:recycle	()V
    //   182: aload 13
    //   184: invokevirtual 67	android/os/Parcel:recycle	()V
    //   187: aload_1
    //   188: athrow
    // Local variable table:
    //   start	length	slot	name	signature
    //   0	189	0	this	fwy
    //   0	189	1	paramfwt	fwt
    //   0	189	2	paramString1	String
    //   0	189	3	paramString2	String
    //   0	189	4	paramBoolean1	boolean
    //   0	189	5	paramString3	String
    //   0	189	6	paramString4	String
    //   0	189	7	paramInt1	int
    //   0	189	8	paramInt2	int
    //   0	189	9	paramInt3	int
    //   0	189	10	paramBoolean2	boolean
    //   55	111	11	i	int
    //   1	104	12	j	int
    //   6	177	13	localParcel1	Parcel
    //   11	167	14	localParcel2	Parcel
    // Exception table:
    //   from	to	target	type
    //   13	20	176	finally
    //   24	31	176	finally
    //   31	49	176	finally
    //   57	99	176	finally
    //   108	147	176	finally
  }
  
  /* Error */
  public final void a(fwt paramfwt, long paramLong, boolean paramBoolean)
  {
    // Byte code:
    //   0: iconst_0
    //   1: istore 5
    //   3: invokestatic 23	android/os/Parcel:obtain	()Landroid/os/Parcel;
    //   6: astore 6
    //   8: invokestatic 23	android/os/Parcel:obtain	()Landroid/os/Parcel;
    //   11: astore 7
    //   13: aload 6
    //   15: ldc 25
    //   17: invokevirtual 29	android/os/Parcel:writeInterfaceToken	(Ljava/lang/String;)V
    //   20: aload_1
    //   21: ifnull +70 -> 91
    //   24: aload_1
    //   25: invokeinterface 74 1 0
    //   30: astore_1
    //   31: aload 6
    //   33: aload_1
    //   34: invokevirtual 77	android/os/Parcel:writeStrongBinder	(Landroid/os/IBinder;)V
    //   37: aload 6
    //   39: lload_2
    //   40: invokevirtual 86	android/os/Parcel:writeLong	(J)V
    //   43: iload 4
    //   45: ifeq +6 -> 51
    //   48: iconst_1
    //   49: istore 5
    //   51: aload 6
    //   53: iload 5
    //   55: invokevirtual 33	android/os/Parcel:writeInt	(I)V
    //   58: aload_0
    //   59: getfield 15	fwy:a	Landroid/os/IBinder;
    //   62: bipush 6
    //   64: aload 6
    //   66: aload 7
    //   68: iconst_0
    //   69: invokeinterface 45 5 0
    //   74: pop
    //   75: aload 7
    //   77: invokevirtual 48	android/os/Parcel:readException	()V
    //   80: aload 7
    //   82: invokevirtual 67	android/os/Parcel:recycle	()V
    //   85: aload 6
    //   87: invokevirtual 67	android/os/Parcel:recycle	()V
    //   90: return
    //   91: aconst_null
    //   92: astore_1
    //   93: goto -62 -> 31
    //   96: astore_1
    //   97: aload 7
    //   99: invokevirtual 67	android/os/Parcel:recycle	()V
    //   102: aload 6
    //   104: invokevirtual 67	android/os/Parcel:recycle	()V
    //   107: aload_1
    //   108: athrow
    // Local variable table:
    //   start	length	slot	name	signature
    //   0	109	0	this	fwy
    //   0	109	1	paramfwt	fwt
    //   0	109	2	paramLong	long
    //   0	109	4	paramBoolean	boolean
    //   1	53	5	i	int
    //   6	97	6	localParcel1	Parcel
    //   11	87	7	localParcel2	Parcel
    // Exception table:
    //   from	to	target	type
    //   13	20	96	finally
    //   24	31	96	finally
    //   31	43	96	finally
    //   51	80	96	finally
  }
  
  /* Error */
  public final void a(fwt paramfwt, Bundle paramBundle)
  {
    // Byte code:
    //   0: invokestatic 23	android/os/Parcel:obtain	()Landroid/os/Parcel;
    //   3: astore_3
    //   4: invokestatic 23	android/os/Parcel:obtain	()Landroid/os/Parcel;
    //   7: astore 4
    //   9: aload_3
    //   10: ldc 25
    //   12: invokevirtual 29	android/os/Parcel:writeInterfaceToken	(Ljava/lang/String;)V
    //   15: aload_1
    //   16: ifnull +62 -> 78
    //   19: aload_1
    //   20: invokeinterface 74 1 0
    //   25: astore_1
    //   26: aload_3
    //   27: aload_1
    //   28: invokevirtual 77	android/os/Parcel:writeStrongBinder	(Landroid/os/IBinder;)V
    //   31: aload_2
    //   32: ifnull +51 -> 83
    //   35: aload_3
    //   36: iconst_1
    //   37: invokevirtual 33	android/os/Parcel:writeInt	(I)V
    //   40: aload_2
    //   41: aload_3
    //   42: iconst_0
    //   43: invokevirtual 119	android/os/Bundle:writeToParcel	(Landroid/os/Parcel;I)V
    //   46: aload_0
    //   47: getfield 15	fwy:a	Landroid/os/IBinder;
    //   50: sipush 302
    //   53: aload_3
    //   54: aload 4
    //   56: iconst_0
    //   57: invokeinterface 45 5 0
    //   62: pop
    //   63: aload 4
    //   65: invokevirtual 48	android/os/Parcel:readException	()V
    //   68: aload 4
    //   70: invokevirtual 67	android/os/Parcel:recycle	()V
    //   73: aload_3
    //   74: invokevirtual 67	android/os/Parcel:recycle	()V
    //   77: return
    //   78: aconst_null
    //   79: astore_1
    //   80: goto -54 -> 26
    //   83: aload_3
    //   84: iconst_0
    //   85: invokevirtual 33	android/os/Parcel:writeInt	(I)V
    //   88: goto -42 -> 46
    //   91: astore_1
    //   92: aload 4
    //   94: invokevirtual 67	android/os/Parcel:recycle	()V
    //   97: aload_3
    //   98: invokevirtual 67	android/os/Parcel:recycle	()V
    //   101: aload_1
    //   102: athrow
    // Local variable table:
    //   start	length	slot	name	signature
    //   0	103	0	this	fwy
    //   0	103	1	paramfwt	fwt
    //   0	103	2	paramBundle	Bundle
    //   3	95	3	localParcel1	Parcel
    //   7	86	4	localParcel2	Parcel
    // Exception table:
    //   from	to	target	type
    //   9	15	91	finally
    //   19	26	91	finally
    //   26	31	91	finally
    //   35	46	91	finally
    //   46	68	91	finally
    //   83	88	91	finally
  }
  
  public final void a(fwt paramfwt, AccountToken paramAccountToken, List<String> paramList, ParcelableGetOptions paramParcelableGetOptions)
  {
    Parcel localParcel1 = Parcel.obtain();
    Parcel localParcel2 = Parcel.obtain();
    label137:
    for (;;)
    {
      try
      {
        localParcel1.writeInterfaceToken("com.google.android.gms.people.internal.IPeopleService");
        if (paramfwt != null)
        {
          paramfwt = paramfwt.asBinder();
          localParcel1.writeStrongBinder(paramfwt);
          if (paramAccountToken != null)
          {
            localParcel1.writeInt(1);
            paramAccountToken.writeToParcel(localParcel1, 0);
            localParcel1.writeStringList(paramList);
            if (paramParcelableGetOptions == null) {
              break label137;
            }
            localParcel1.writeInt(1);
            paramParcelableGetOptions.writeToParcel(localParcel1, 0);
            a.transact(501, localParcel1, localParcel2, 0);
            localParcel2.readException();
          }
        }
        else
        {
          paramfwt = null;
          continue;
        }
        localParcel1.writeInt(0);
        continue;
        localParcel1.writeInt(0);
      }
      finally
      {
        localParcel2.recycle();
        localParcel1.recycle();
      }
    }
  }
  
  /* Error */
  public final void a(fwt paramfwt, String paramString)
  {
    // Byte code:
    //   0: invokestatic 23	android/os/Parcel:obtain	()Landroid/os/Parcel;
    //   3: astore_3
    //   4: invokestatic 23	android/os/Parcel:obtain	()Landroid/os/Parcel;
    //   7: astore 4
    //   9: aload_3
    //   10: ldc 25
    //   12: invokevirtual 29	android/os/Parcel:writeInterfaceToken	(Ljava/lang/String;)V
    //   15: aload_1
    //   16: ifnull +51 -> 67
    //   19: aload_1
    //   20: invokeinterface 74 1 0
    //   25: astore_1
    //   26: aload_3
    //   27: aload_1
    //   28: invokevirtual 77	android/os/Parcel:writeStrongBinder	(Landroid/os/IBinder;)V
    //   31: aload_3
    //   32: aload_2
    //   33: invokevirtual 80	android/os/Parcel:writeString	(Ljava/lang/String;)V
    //   36: aload_0
    //   37: getfield 15	fwy:a	Landroid/os/IBinder;
    //   40: bipush 24
    //   42: aload_3
    //   43: aload 4
    //   45: iconst_0
    //   46: invokeinterface 45 5 0
    //   51: pop
    //   52: aload 4
    //   54: invokevirtual 48	android/os/Parcel:readException	()V
    //   57: aload 4
    //   59: invokevirtual 67	android/os/Parcel:recycle	()V
    //   62: aload_3
    //   63: invokevirtual 67	android/os/Parcel:recycle	()V
    //   66: return
    //   67: aconst_null
    //   68: astore_1
    //   69: goto -43 -> 26
    //   72: astore_1
    //   73: aload 4
    //   75: invokevirtual 67	android/os/Parcel:recycle	()V
    //   78: aload_3
    //   79: invokevirtual 67	android/os/Parcel:recycle	()V
    //   82: aload_1
    //   83: athrow
    // Local variable table:
    //   start	length	slot	name	signature
    //   0	84	0	this	fwy
    //   0	84	1	paramfwt	fwt
    //   0	84	2	paramString	String
    //   3	76	3	localParcel1	Parcel
    //   7	67	4	localParcel2	Parcel
    // Exception table:
    //   from	to	target	type
    //   9	15	72	finally
    //   19	26	72	finally
    //   26	57	72	finally
  }
  
  /* Error */
  public final void a(fwt paramfwt, String paramString, int paramInt1, int paramInt2)
  {
    // Byte code:
    //   0: invokestatic 23	android/os/Parcel:obtain	()Landroid/os/Parcel;
    //   3: astore 5
    //   5: invokestatic 23	android/os/Parcel:obtain	()Landroid/os/Parcel;
    //   8: astore 6
    //   10: aload 5
    //   12: ldc 25
    //   14: invokevirtual 29	android/os/Parcel:writeInterfaceToken	(Ljava/lang/String;)V
    //   17: aload_1
    //   18: ifnull +67 -> 85
    //   21: aload_1
    //   22: invokeinterface 74 1 0
    //   27: astore_1
    //   28: aload 5
    //   30: aload_1
    //   31: invokevirtual 77	android/os/Parcel:writeStrongBinder	(Landroid/os/IBinder;)V
    //   34: aload 5
    //   36: aload_2
    //   37: invokevirtual 80	android/os/Parcel:writeString	(Ljava/lang/String;)V
    //   40: aload 5
    //   42: iload_3
    //   43: invokevirtual 33	android/os/Parcel:writeInt	(I)V
    //   46: aload 5
    //   48: iload 4
    //   50: invokevirtual 33	android/os/Parcel:writeInt	(I)V
    //   53: aload_0
    //   54: getfield 15	fwy:a	Landroid/os/IBinder;
    //   57: iconst_5
    //   58: aload 5
    //   60: aload 6
    //   62: iconst_0
    //   63: invokeinterface 45 5 0
    //   68: pop
    //   69: aload 6
    //   71: invokevirtual 48	android/os/Parcel:readException	()V
    //   74: aload 6
    //   76: invokevirtual 67	android/os/Parcel:recycle	()V
    //   79: aload 5
    //   81: invokevirtual 67	android/os/Parcel:recycle	()V
    //   84: return
    //   85: aconst_null
    //   86: astore_1
    //   87: goto -59 -> 28
    //   90: astore_1
    //   91: aload 6
    //   93: invokevirtual 67	android/os/Parcel:recycle	()V
    //   96: aload 5
    //   98: invokevirtual 67	android/os/Parcel:recycle	()V
    //   101: aload_1
    //   102: athrow
    // Local variable table:
    //   start	length	slot	name	signature
    //   0	103	0	this	fwy
    //   0	103	1	paramfwt	fwt
    //   0	103	2	paramString	String
    //   0	103	3	paramInt1	int
    //   0	103	4	paramInt2	int
    //   3	94	5	localParcel1	Parcel
    //   8	84	6	localParcel2	Parcel
    // Exception table:
    //   from	to	target	type
    //   10	17	90	finally
    //   21	28	90	finally
    //   28	74	90	finally
  }
  
  /* Error */
  public final void a(fwt paramfwt, String paramString1, String paramString2)
  {
    // Byte code:
    //   0: invokestatic 23	android/os/Parcel:obtain	()Landroid/os/Parcel;
    //   3: astore 4
    //   5: invokestatic 23	android/os/Parcel:obtain	()Landroid/os/Parcel;
    //   8: astore 5
    //   10: aload 4
    //   12: ldc 25
    //   14: invokevirtual 29	android/os/Parcel:writeInterfaceToken	(Ljava/lang/String;)V
    //   17: aload_1
    //   18: ifnull +61 -> 79
    //   21: aload_1
    //   22: invokeinterface 74 1 0
    //   27: astore_1
    //   28: aload 4
    //   30: aload_1
    //   31: invokevirtual 77	android/os/Parcel:writeStrongBinder	(Landroid/os/IBinder;)V
    //   34: aload 4
    //   36: aload_2
    //   37: invokevirtual 80	android/os/Parcel:writeString	(Ljava/lang/String;)V
    //   40: aload 4
    //   42: aload_3
    //   43: invokevirtual 80	android/os/Parcel:writeString	(Ljava/lang/String;)V
    //   46: aload_0
    //   47: getfield 15	fwy:a	Landroid/os/IBinder;
    //   50: bipush 25
    //   52: aload 4
    //   54: aload 5
    //   56: iconst_0
    //   57: invokeinterface 45 5 0
    //   62: pop
    //   63: aload 5
    //   65: invokevirtual 48	android/os/Parcel:readException	()V
    //   68: aload 5
    //   70: invokevirtual 67	android/os/Parcel:recycle	()V
    //   73: aload 4
    //   75: invokevirtual 67	android/os/Parcel:recycle	()V
    //   78: return
    //   79: aconst_null
    //   80: astore_1
    //   81: goto -53 -> 28
    //   84: astore_1
    //   85: aload 5
    //   87: invokevirtual 67	android/os/Parcel:recycle	()V
    //   90: aload 4
    //   92: invokevirtual 67	android/os/Parcel:recycle	()V
    //   95: aload_1
    //   96: athrow
    // Local variable table:
    //   start	length	slot	name	signature
    //   0	97	0	this	fwy
    //   0	97	1	paramfwt	fwt
    //   0	97	2	paramString1	String
    //   0	97	3	paramString2	String
    //   3	88	4	localParcel1	Parcel
    //   8	78	5	localParcel2	Parcel
    // Exception table:
    //   from	to	target	type
    //   10	17	84	finally
    //   21	28	84	finally
    //   28	68	84	finally
  }
  
  /* Error */
  public final void a(fwt paramfwt, String paramString1, String paramString2, int paramInt)
  {
    // Byte code:
    //   0: invokestatic 23	android/os/Parcel:obtain	()Landroid/os/Parcel;
    //   3: astore 5
    //   5: invokestatic 23	android/os/Parcel:obtain	()Landroid/os/Parcel;
    //   8: astore 6
    //   10: aload 5
    //   12: ldc 25
    //   14: invokevirtual 29	android/os/Parcel:writeInterfaceToken	(Ljava/lang/String;)V
    //   17: aload_1
    //   18: ifnull +69 -> 87
    //   21: aload_1
    //   22: invokeinterface 74 1 0
    //   27: astore_1
    //   28: aload 5
    //   30: aload_1
    //   31: invokevirtual 77	android/os/Parcel:writeStrongBinder	(Landroid/os/IBinder;)V
    //   34: aload 5
    //   36: aload_2
    //   37: invokevirtual 80	android/os/Parcel:writeString	(Ljava/lang/String;)V
    //   40: aload 5
    //   42: aload_3
    //   43: invokevirtual 80	android/os/Parcel:writeString	(Ljava/lang/String;)V
    //   46: aload 5
    //   48: iload 4
    //   50: invokevirtual 33	android/os/Parcel:writeInt	(I)V
    //   53: aload_0
    //   54: getfield 15	fwy:a	Landroid/os/IBinder;
    //   57: sipush 403
    //   60: aload 5
    //   62: aload 6
    //   64: iconst_0
    //   65: invokeinterface 45 5 0
    //   70: pop
    //   71: aload 6
    //   73: invokevirtual 48	android/os/Parcel:readException	()V
    //   76: aload 6
    //   78: invokevirtual 67	android/os/Parcel:recycle	()V
    //   81: aload 5
    //   83: invokevirtual 67	android/os/Parcel:recycle	()V
    //   86: return
    //   87: aconst_null
    //   88: astore_1
    //   89: goto -61 -> 28
    //   92: astore_1
    //   93: aload 6
    //   95: invokevirtual 67	android/os/Parcel:recycle	()V
    //   98: aload 5
    //   100: invokevirtual 67	android/os/Parcel:recycle	()V
    //   103: aload_1
    //   104: athrow
    // Local variable table:
    //   start	length	slot	name	signature
    //   0	105	0	this	fwy
    //   0	105	1	paramfwt	fwt
    //   0	105	2	paramString1	String
    //   0	105	3	paramString2	String
    //   0	105	4	paramInt	int
    //   3	96	5	localParcel1	Parcel
    //   8	86	6	localParcel2	Parcel
    // Exception table:
    //   from	to	target	type
    //   10	17	92	finally
    //   21	28	92	finally
    //   28	76	92	finally
  }
  
  /* Error */
  public final void a(fwt paramfwt, String paramString1, String paramString2, int paramInt1, int paramInt2)
  {
    // Byte code:
    //   0: invokestatic 23	android/os/Parcel:obtain	()Landroid/os/Parcel;
    //   3: astore 6
    //   5: invokestatic 23	android/os/Parcel:obtain	()Landroid/os/Parcel;
    //   8: astore 7
    //   10: aload 6
    //   12: ldc 25
    //   14: invokevirtual 29	android/os/Parcel:writeInterfaceToken	(Ljava/lang/String;)V
    //   17: aload_1
    //   18: ifnull +75 -> 93
    //   21: aload_1
    //   22: invokeinterface 74 1 0
    //   27: astore_1
    //   28: aload 6
    //   30: aload_1
    //   31: invokevirtual 77	android/os/Parcel:writeStrongBinder	(Landroid/os/IBinder;)V
    //   34: aload 6
    //   36: aload_2
    //   37: invokevirtual 80	android/os/Parcel:writeString	(Ljava/lang/String;)V
    //   40: aload 6
    //   42: aload_3
    //   43: invokevirtual 80	android/os/Parcel:writeString	(Ljava/lang/String;)V
    //   46: aload 6
    //   48: iload 4
    //   50: invokevirtual 33	android/os/Parcel:writeInt	(I)V
    //   53: aload 6
    //   55: iload 5
    //   57: invokevirtual 33	android/os/Parcel:writeInt	(I)V
    //   60: aload_0
    //   61: getfield 15	fwy:a	Landroid/os/IBinder;
    //   64: bipush 29
    //   66: aload 6
    //   68: aload 7
    //   70: iconst_0
    //   71: invokeinterface 45 5 0
    //   76: pop
    //   77: aload 7
    //   79: invokevirtual 48	android/os/Parcel:readException	()V
    //   82: aload 7
    //   84: invokevirtual 67	android/os/Parcel:recycle	()V
    //   87: aload 6
    //   89: invokevirtual 67	android/os/Parcel:recycle	()V
    //   92: return
    //   93: aconst_null
    //   94: astore_1
    //   95: goto -67 -> 28
    //   98: astore_1
    //   99: aload 7
    //   101: invokevirtual 67	android/os/Parcel:recycle	()V
    //   104: aload 6
    //   106: invokevirtual 67	android/os/Parcel:recycle	()V
    //   109: aload_1
    //   110: athrow
    // Local variable table:
    //   start	length	slot	name	signature
    //   0	111	0	this	fwy
    //   0	111	1	paramfwt	fwt
    //   0	111	2	paramString1	String
    //   0	111	3	paramString2	String
    //   0	111	4	paramInt1	int
    //   0	111	5	paramInt2	int
    //   3	102	6	localParcel1	Parcel
    //   8	92	7	localParcel2	Parcel
    // Exception table:
    //   from	to	target	type
    //   10	17	98	finally
    //   21	28	98	finally
    //   28	82	98	finally
  }
  
  /* Error */
  public final void a(fwt paramfwt, String paramString1, String paramString2, Uri paramUri)
  {
    // Byte code:
    //   0: invokestatic 23	android/os/Parcel:obtain	()Landroid/os/Parcel;
    //   3: astore 5
    //   5: invokestatic 23	android/os/Parcel:obtain	()Landroid/os/Parcel;
    //   8: astore 6
    //   10: aload 5
    //   12: ldc 25
    //   14: invokevirtual 29	android/os/Parcel:writeInterfaceToken	(Ljava/lang/String;)V
    //   17: aload_1
    //   18: ifnull +80 -> 98
    //   21: aload_1
    //   22: invokeinterface 74 1 0
    //   27: astore_1
    //   28: aload 5
    //   30: aload_1
    //   31: invokevirtual 77	android/os/Parcel:writeStrongBinder	(Landroid/os/IBinder;)V
    //   34: aload 5
    //   36: aload_2
    //   37: invokevirtual 80	android/os/Parcel:writeString	(Ljava/lang/String;)V
    //   40: aload 5
    //   42: aload_3
    //   43: invokevirtual 80	android/os/Parcel:writeString	(Ljava/lang/String;)V
    //   46: aload 4
    //   48: ifnull +55 -> 103
    //   51: aload 5
    //   53: iconst_1
    //   54: invokevirtual 33	android/os/Parcel:writeInt	(I)V
    //   57: aload 4
    //   59: aload 5
    //   61: iconst_0
    //   62: invokevirtual 39	android/net/Uri:writeToParcel	(Landroid/os/Parcel;I)V
    //   65: aload_0
    //   66: getfield 15	fwy:a	Landroid/os/IBinder;
    //   69: bipush 13
    //   71: aload 5
    //   73: aload 6
    //   75: iconst_0
    //   76: invokeinterface 45 5 0
    //   81: pop
    //   82: aload 6
    //   84: invokevirtual 48	android/os/Parcel:readException	()V
    //   87: aload 6
    //   89: invokevirtual 67	android/os/Parcel:recycle	()V
    //   92: aload 5
    //   94: invokevirtual 67	android/os/Parcel:recycle	()V
    //   97: return
    //   98: aconst_null
    //   99: astore_1
    //   100: goto -72 -> 28
    //   103: aload 5
    //   105: iconst_0
    //   106: invokevirtual 33	android/os/Parcel:writeInt	(I)V
    //   109: goto -44 -> 65
    //   112: astore_1
    //   113: aload 6
    //   115: invokevirtual 67	android/os/Parcel:recycle	()V
    //   118: aload 5
    //   120: invokevirtual 67	android/os/Parcel:recycle	()V
    //   123: aload_1
    //   124: athrow
    // Local variable table:
    //   start	length	slot	name	signature
    //   0	125	0	this	fwy
    //   0	125	1	paramfwt	fwt
    //   0	125	2	paramString1	String
    //   0	125	3	paramString2	String
    //   0	125	4	paramUri	Uri
    //   3	116	5	localParcel1	Parcel
    //   8	106	6	localParcel2	Parcel
    // Exception table:
    //   from	to	target	type
    //   10	17	112	finally
    //   21	28	112	finally
    //   28	46	112	finally
    //   51	65	112	finally
    //   65	87	112	finally
    //   103	109	112	finally
  }
  
  public final void a(fwt paramfwt, String paramString1, String paramString2, Uri paramUri, boolean paramBoolean)
  {
    int i = 1;
    Parcel localParcel1 = Parcel.obtain();
    Parcel localParcel2 = Parcel.obtain();
    for (;;)
    {
      try
      {
        localParcel1.writeInterfaceToken("com.google.android.gms.people.internal.IPeopleService");
        if (paramfwt != null)
        {
          paramfwt = paramfwt.asBinder();
          localParcel1.writeStrongBinder(paramfwt);
          localParcel1.writeString(paramString1);
          localParcel1.writeString(paramString2);
          if (paramUri != null)
          {
            localParcel1.writeInt(1);
            paramUri.writeToParcel(localParcel1, 0);
            break label144;
            localParcel1.writeInt(i);
            a.transact(18, localParcel1, localParcel2, 0);
            localParcel2.readException();
          }
        }
        else
        {
          paramfwt = null;
          continue;
        }
        localParcel1.writeInt(0);
      }
      finally
      {
        localParcel2.recycle();
        localParcel1.recycle();
      }
      label144:
      do
      {
        i = 0;
        break;
      } while (!paramBoolean);
    }
  }
  
  /* Error */
  public final void a(fwt paramfwt, String paramString1, String paramString2, String paramString3)
  {
    // Byte code:
    //   0: invokestatic 23	android/os/Parcel:obtain	()Landroid/os/Parcel;
    //   3: astore 5
    //   5: invokestatic 23	android/os/Parcel:obtain	()Landroid/os/Parcel;
    //   8: astore 6
    //   10: aload 5
    //   12: ldc 25
    //   14: invokevirtual 29	android/os/Parcel:writeInterfaceToken	(Ljava/lang/String;)V
    //   17: aload_1
    //   18: ifnull +69 -> 87
    //   21: aload_1
    //   22: invokeinterface 74 1 0
    //   27: astore_1
    //   28: aload 5
    //   30: aload_1
    //   31: invokevirtual 77	android/os/Parcel:writeStrongBinder	(Landroid/os/IBinder;)V
    //   34: aload 5
    //   36: aload_2
    //   37: invokevirtual 80	android/os/Parcel:writeString	(Ljava/lang/String;)V
    //   40: aload 5
    //   42: aload_3
    //   43: invokevirtual 80	android/os/Parcel:writeString	(Ljava/lang/String;)V
    //   46: aload 5
    //   48: aload 4
    //   50: invokevirtual 80	android/os/Parcel:writeString	(Ljava/lang/String;)V
    //   53: aload_0
    //   54: getfield 15	fwy:a	Landroid/os/IBinder;
    //   57: sipush 204
    //   60: aload 5
    //   62: aload 6
    //   64: iconst_0
    //   65: invokeinterface 45 5 0
    //   70: pop
    //   71: aload 6
    //   73: invokevirtual 48	android/os/Parcel:readException	()V
    //   76: aload 6
    //   78: invokevirtual 67	android/os/Parcel:recycle	()V
    //   81: aload 5
    //   83: invokevirtual 67	android/os/Parcel:recycle	()V
    //   86: return
    //   87: aconst_null
    //   88: astore_1
    //   89: goto -61 -> 28
    //   92: astore_1
    //   93: aload 6
    //   95: invokevirtual 67	android/os/Parcel:recycle	()V
    //   98: aload 5
    //   100: invokevirtual 67	android/os/Parcel:recycle	()V
    //   103: aload_1
    //   104: athrow
    // Local variable table:
    //   start	length	slot	name	signature
    //   0	105	0	this	fwy
    //   0	105	1	paramfwt	fwt
    //   0	105	2	paramString1	String
    //   0	105	3	paramString2	String
    //   0	105	4	paramString3	String
    //   3	96	5	localParcel1	Parcel
    //   8	86	6	localParcel2	Parcel
    // Exception table:
    //   from	to	target	type
    //   10	17	92	finally
    //   21	28	92	finally
    //   28	76	92	finally
  }
  
  /* Error */
  public final void a(fwt paramfwt, String paramString1, String paramString2, String paramString3, int paramInt, String paramString4)
  {
    // Byte code:
    //   0: invokestatic 23	android/os/Parcel:obtain	()Landroid/os/Parcel;
    //   3: astore 7
    //   5: invokestatic 23	android/os/Parcel:obtain	()Landroid/os/Parcel;
    //   8: astore 8
    //   10: aload 7
    //   12: ldc 25
    //   14: invokevirtual 29	android/os/Parcel:writeInterfaceToken	(Ljava/lang/String;)V
    //   17: aload_1
    //   18: ifnull +81 -> 99
    //   21: aload_1
    //   22: invokeinterface 74 1 0
    //   27: astore_1
    //   28: aload 7
    //   30: aload_1
    //   31: invokevirtual 77	android/os/Parcel:writeStrongBinder	(Landroid/os/IBinder;)V
    //   34: aload 7
    //   36: aload_2
    //   37: invokevirtual 80	android/os/Parcel:writeString	(Ljava/lang/String;)V
    //   40: aload 7
    //   42: aload_3
    //   43: invokevirtual 80	android/os/Parcel:writeString	(Ljava/lang/String;)V
    //   46: aload 7
    //   48: aload 4
    //   50: invokevirtual 80	android/os/Parcel:writeString	(Ljava/lang/String;)V
    //   53: aload 7
    //   55: iload 5
    //   57: invokevirtual 33	android/os/Parcel:writeInt	(I)V
    //   60: aload 7
    //   62: aload 6
    //   64: invokevirtual 80	android/os/Parcel:writeString	(Ljava/lang/String;)V
    //   67: aload_0
    //   68: getfield 15	fwy:a	Landroid/os/IBinder;
    //   71: iconst_3
    //   72: aload 7
    //   74: aload 8
    //   76: iconst_0
    //   77: invokeinterface 45 5 0
    //   82: pop
    //   83: aload 8
    //   85: invokevirtual 48	android/os/Parcel:readException	()V
    //   88: aload 8
    //   90: invokevirtual 67	android/os/Parcel:recycle	()V
    //   93: aload 7
    //   95: invokevirtual 67	android/os/Parcel:recycle	()V
    //   98: return
    //   99: aconst_null
    //   100: astore_1
    //   101: goto -73 -> 28
    //   104: astore_1
    //   105: aload 8
    //   107: invokevirtual 67	android/os/Parcel:recycle	()V
    //   110: aload 7
    //   112: invokevirtual 67	android/os/Parcel:recycle	()V
    //   115: aload_1
    //   116: athrow
    // Local variable table:
    //   start	length	slot	name	signature
    //   0	117	0	this	fwy
    //   0	117	1	paramfwt	fwt
    //   0	117	2	paramString1	String
    //   0	117	3	paramString2	String
    //   0	117	4	paramString3	String
    //   0	117	5	paramInt	int
    //   0	117	6	paramString4	String
    //   3	108	7	localParcel1	Parcel
    //   8	98	8	localParcel2	Parcel
    // Exception table:
    //   from	to	target	type
    //   10	17	104	finally
    //   21	28	104	finally
    //   28	88	104	finally
  }
  
  /* Error */
  public final void a(fwt paramfwt, String paramString1, String paramString2, String paramString3, int paramInt, String paramString4, boolean paramBoolean)
  {
    // Byte code:
    //   0: iconst_0
    //   1: istore 8
    //   3: invokestatic 23	android/os/Parcel:obtain	()Landroid/os/Parcel;
    //   6: astore 9
    //   8: invokestatic 23	android/os/Parcel:obtain	()Landroid/os/Parcel;
    //   11: astore 10
    //   13: aload 9
    //   15: ldc 25
    //   17: invokevirtual 29	android/os/Parcel:writeInterfaceToken	(Ljava/lang/String;)V
    //   20: aload_1
    //   21: ifnull +101 -> 122
    //   24: aload_1
    //   25: invokeinterface 74 1 0
    //   30: astore_1
    //   31: aload 9
    //   33: aload_1
    //   34: invokevirtual 77	android/os/Parcel:writeStrongBinder	(Landroid/os/IBinder;)V
    //   37: aload 9
    //   39: aload_2
    //   40: invokevirtual 80	android/os/Parcel:writeString	(Ljava/lang/String;)V
    //   43: aload 9
    //   45: aload_3
    //   46: invokevirtual 80	android/os/Parcel:writeString	(Ljava/lang/String;)V
    //   49: aload 9
    //   51: aload 4
    //   53: invokevirtual 80	android/os/Parcel:writeString	(Ljava/lang/String;)V
    //   56: aload 9
    //   58: iload 5
    //   60: invokevirtual 33	android/os/Parcel:writeInt	(I)V
    //   63: aload 9
    //   65: aload 6
    //   67: invokevirtual 80	android/os/Parcel:writeString	(Ljava/lang/String;)V
    //   70: iload 8
    //   72: istore 5
    //   74: iload 7
    //   76: ifeq +6 -> 82
    //   79: iconst_1
    //   80: istore 5
    //   82: aload 9
    //   84: iload 5
    //   86: invokevirtual 33	android/os/Parcel:writeInt	(I)V
    //   89: aload_0
    //   90: getfield 15	fwy:a	Landroid/os/IBinder;
    //   93: bipush 19
    //   95: aload 9
    //   97: aload 10
    //   99: iconst_0
    //   100: invokeinterface 45 5 0
    //   105: pop
    //   106: aload 10
    //   108: invokevirtual 48	android/os/Parcel:readException	()V
    //   111: aload 10
    //   113: invokevirtual 67	android/os/Parcel:recycle	()V
    //   116: aload 9
    //   118: invokevirtual 67	android/os/Parcel:recycle	()V
    //   121: return
    //   122: aconst_null
    //   123: astore_1
    //   124: goto -93 -> 31
    //   127: astore_1
    //   128: aload 10
    //   130: invokevirtual 67	android/os/Parcel:recycle	()V
    //   133: aload 9
    //   135: invokevirtual 67	android/os/Parcel:recycle	()V
    //   138: aload_1
    //   139: athrow
    // Local variable table:
    //   start	length	slot	name	signature
    //   0	140	0	this	fwy
    //   0	140	1	paramfwt	fwt
    //   0	140	2	paramString1	String
    //   0	140	3	paramString2	String
    //   0	140	4	paramString3	String
    //   0	140	5	paramInt	int
    //   0	140	6	paramString4	String
    //   0	140	7	paramBoolean	boolean
    //   1	70	8	i	int
    //   6	128	9	localParcel1	Parcel
    //   11	118	10	localParcel2	Parcel
    // Exception table:
    //   from	to	target	type
    //   13	20	127	finally
    //   24	31	127	finally
    //   31	70	127	finally
    //   82	111	127	finally
  }
  
  /* Error */
  public final void a(fwt paramfwt, String paramString1, String paramString2, String paramString3, int paramInt1, boolean paramBoolean, int paramInt2, int paramInt3, String paramString4)
  {
    // Byte code:
    //   0: iconst_0
    //   1: istore 10
    //   3: invokestatic 23	android/os/Parcel:obtain	()Landroid/os/Parcel;
    //   6: astore 11
    //   8: invokestatic 23	android/os/Parcel:obtain	()Landroid/os/Parcel;
    //   11: astore 12
    //   13: aload 11
    //   15: ldc 25
    //   17: invokevirtual 29	android/os/Parcel:writeInterfaceToken	(Ljava/lang/String;)V
    //   20: aload_1
    //   21: ifnull +116 -> 137
    //   24: aload_1
    //   25: invokeinterface 74 1 0
    //   30: astore_1
    //   31: aload 11
    //   33: aload_1
    //   34: invokevirtual 77	android/os/Parcel:writeStrongBinder	(Landroid/os/IBinder;)V
    //   37: aload 11
    //   39: aload_2
    //   40: invokevirtual 80	android/os/Parcel:writeString	(Ljava/lang/String;)V
    //   43: aload 11
    //   45: aload_3
    //   46: invokevirtual 80	android/os/Parcel:writeString	(Ljava/lang/String;)V
    //   49: aload 11
    //   51: aload 4
    //   53: invokevirtual 80	android/os/Parcel:writeString	(Ljava/lang/String;)V
    //   56: aload 11
    //   58: iload 5
    //   60: invokevirtual 33	android/os/Parcel:writeInt	(I)V
    //   63: iload 10
    //   65: istore 5
    //   67: iload 6
    //   69: ifeq +6 -> 75
    //   72: iconst_1
    //   73: istore 5
    //   75: aload 11
    //   77: iload 5
    //   79: invokevirtual 33	android/os/Parcel:writeInt	(I)V
    //   82: aload 11
    //   84: iload 7
    //   86: invokevirtual 33	android/os/Parcel:writeInt	(I)V
    //   89: aload 11
    //   91: iload 8
    //   93: invokevirtual 33	android/os/Parcel:writeInt	(I)V
    //   96: aload 11
    //   98: aload 9
    //   100: invokevirtual 80	android/os/Parcel:writeString	(Ljava/lang/String;)V
    //   103: aload_0
    //   104: getfield 15	fwy:a	Landroid/os/IBinder;
    //   107: sipush 202
    //   110: aload 11
    //   112: aload 12
    //   114: iconst_0
    //   115: invokeinterface 45 5 0
    //   120: pop
    //   121: aload 12
    //   123: invokevirtual 48	android/os/Parcel:readException	()V
    //   126: aload 12
    //   128: invokevirtual 67	android/os/Parcel:recycle	()V
    //   131: aload 11
    //   133: invokevirtual 67	android/os/Parcel:recycle	()V
    //   136: return
    //   137: aconst_null
    //   138: astore_1
    //   139: goto -108 -> 31
    //   142: astore_1
    //   143: aload 12
    //   145: invokevirtual 67	android/os/Parcel:recycle	()V
    //   148: aload 11
    //   150: invokevirtual 67	android/os/Parcel:recycle	()V
    //   153: aload_1
    //   154: athrow
    // Local variable table:
    //   start	length	slot	name	signature
    //   0	155	0	this	fwy
    //   0	155	1	paramfwt	fwt
    //   0	155	2	paramString1	String
    //   0	155	3	paramString2	String
    //   0	155	4	paramString3	String
    //   0	155	5	paramInt1	int
    //   0	155	6	paramBoolean	boolean
    //   0	155	7	paramInt2	int
    //   0	155	8	paramInt3	int
    //   0	155	9	paramString4	String
    //   1	63	10	i	int
    //   6	143	11	localParcel1	Parcel
    //   11	133	12	localParcel2	Parcel
    // Exception table:
    //   from	to	target	type
    //   13	20	142	finally
    //   24	31	142	finally
    //   31	63	142	finally
    //   75	126	142	finally
  }
  
  /* Error */
  public final void a(fwt paramfwt, String paramString1, String paramString2, String paramString3, int paramInt1, boolean paramBoolean1, int paramInt2, int paramInt3, String paramString4, boolean paramBoolean2)
  {
    // Byte code:
    //   0: iconst_1
    //   1: istore 11
    //   3: invokestatic 23	android/os/Parcel:obtain	()Landroid/os/Parcel;
    //   6: astore 12
    //   8: invokestatic 23	android/os/Parcel:obtain	()Landroid/os/Parcel;
    //   11: astore 13
    //   13: aload 12
    //   15: ldc 25
    //   17: invokevirtual 29	android/os/Parcel:writeInterfaceToken	(Ljava/lang/String;)V
    //   20: aload_1
    //   21: ifnull +128 -> 149
    //   24: aload_1
    //   25: invokeinterface 74 1 0
    //   30: astore_1
    //   31: aload 12
    //   33: aload_1
    //   34: invokevirtual 77	android/os/Parcel:writeStrongBinder	(Landroid/os/IBinder;)V
    //   37: aload 12
    //   39: aload_2
    //   40: invokevirtual 80	android/os/Parcel:writeString	(Ljava/lang/String;)V
    //   43: aload 12
    //   45: aload_3
    //   46: invokevirtual 80	android/os/Parcel:writeString	(Ljava/lang/String;)V
    //   49: aload 12
    //   51: aload 4
    //   53: invokevirtual 80	android/os/Parcel:writeString	(Ljava/lang/String;)V
    //   56: aload 12
    //   58: iload 5
    //   60: invokevirtual 33	android/os/Parcel:writeInt	(I)V
    //   63: iload 6
    //   65: ifeq +89 -> 154
    //   68: iconst_1
    //   69: istore 5
    //   71: aload 12
    //   73: iload 5
    //   75: invokevirtual 33	android/os/Parcel:writeInt	(I)V
    //   78: aload 12
    //   80: iload 7
    //   82: invokevirtual 33	android/os/Parcel:writeInt	(I)V
    //   85: aload 12
    //   87: iload 8
    //   89: invokevirtual 33	android/os/Parcel:writeInt	(I)V
    //   92: aload 12
    //   94: aload 9
    //   96: invokevirtual 80	android/os/Parcel:writeString	(Ljava/lang/String;)V
    //   99: iload 10
    //   101: ifeq +59 -> 160
    //   104: iload 11
    //   106: istore 5
    //   108: aload 12
    //   110: iload 5
    //   112: invokevirtual 33	android/os/Parcel:writeInt	(I)V
    //   115: aload_0
    //   116: getfield 15	fwy:a	Landroid/os/IBinder;
    //   119: sipush 203
    //   122: aload 12
    //   124: aload 13
    //   126: iconst_0
    //   127: invokeinterface 45 5 0
    //   132: pop
    //   133: aload 13
    //   135: invokevirtual 48	android/os/Parcel:readException	()V
    //   138: aload 13
    //   140: invokevirtual 67	android/os/Parcel:recycle	()V
    //   143: aload 12
    //   145: invokevirtual 67	android/os/Parcel:recycle	()V
    //   148: return
    //   149: aconst_null
    //   150: astore_1
    //   151: goto -120 -> 31
    //   154: iconst_0
    //   155: istore 5
    //   157: goto -86 -> 71
    //   160: iconst_0
    //   161: istore 5
    //   163: goto -55 -> 108
    //   166: astore_1
    //   167: aload 13
    //   169: invokevirtual 67	android/os/Parcel:recycle	()V
    //   172: aload 12
    //   174: invokevirtual 67	android/os/Parcel:recycle	()V
    //   177: aload_1
    //   178: athrow
    // Local variable table:
    //   start	length	slot	name	signature
    //   0	179	0	this	fwy
    //   0	179	1	paramfwt	fwt
    //   0	179	2	paramString1	String
    //   0	179	3	paramString2	String
    //   0	179	4	paramString3	String
    //   0	179	5	paramInt1	int
    //   0	179	6	paramBoolean1	boolean
    //   0	179	7	paramInt2	int
    //   0	179	8	paramInt3	int
    //   0	179	9	paramString4	String
    //   0	179	10	paramBoolean2	boolean
    //   1	104	11	i	int
    //   6	167	12	localParcel1	Parcel
    //   11	157	13	localParcel2	Parcel
    // Exception table:
    //   from	to	target	type
    //   13	20	166	finally
    //   24	31	166	finally
    //   31	63	166	finally
    //   71	99	166	finally
    //   108	138	166	finally
  }
  
  /* Error */
  public final void a(fwt paramfwt, String paramString1, String paramString2, String paramString3, int paramInt1, boolean paramBoolean1, int paramInt2, int paramInt3, String paramString4, boolean paramBoolean2, int paramInt4, int paramInt5)
  {
    // Byte code:
    //   0: invokestatic 23	android/os/Parcel:obtain	()Landroid/os/Parcel;
    //   3: astore 13
    //   5: invokestatic 23	android/os/Parcel:obtain	()Landroid/os/Parcel;
    //   8: astore 14
    //   10: aload 13
    //   12: ldc 25
    //   14: invokevirtual 29	android/os/Parcel:writeInterfaceToken	(Ljava/lang/String;)V
    //   17: aload_1
    //   18: ifnull +141 -> 159
    //   21: aload_1
    //   22: invokeinterface 74 1 0
    //   27: astore_1
    //   28: aload 13
    //   30: aload_1
    //   31: invokevirtual 77	android/os/Parcel:writeStrongBinder	(Landroid/os/IBinder;)V
    //   34: aload 13
    //   36: aload_2
    //   37: invokevirtual 80	android/os/Parcel:writeString	(Ljava/lang/String;)V
    //   40: aload 13
    //   42: aload_3
    //   43: invokevirtual 80	android/os/Parcel:writeString	(Ljava/lang/String;)V
    //   46: aload 13
    //   48: aload 4
    //   50: invokevirtual 80	android/os/Parcel:writeString	(Ljava/lang/String;)V
    //   53: aload 13
    //   55: iload 5
    //   57: invokevirtual 33	android/os/Parcel:writeInt	(I)V
    //   60: iload 6
    //   62: ifeq +102 -> 164
    //   65: iconst_1
    //   66: istore 5
    //   68: aload 13
    //   70: iload 5
    //   72: invokevirtual 33	android/os/Parcel:writeInt	(I)V
    //   75: aload 13
    //   77: iload 7
    //   79: invokevirtual 33	android/os/Parcel:writeInt	(I)V
    //   82: aload 13
    //   84: iload 8
    //   86: invokevirtual 33	android/os/Parcel:writeInt	(I)V
    //   89: aload 13
    //   91: aload 9
    //   93: invokevirtual 80	android/os/Parcel:writeString	(Ljava/lang/String;)V
    //   96: iload 10
    //   98: ifeq +72 -> 170
    //   101: iconst_1
    //   102: istore 5
    //   104: aload 13
    //   106: iload 5
    //   108: invokevirtual 33	android/os/Parcel:writeInt	(I)V
    //   111: aload 13
    //   113: iload 11
    //   115: invokevirtual 33	android/os/Parcel:writeInt	(I)V
    //   118: aload 13
    //   120: iload 12
    //   122: invokevirtual 33	android/os/Parcel:writeInt	(I)V
    //   125: aload_0
    //   126: getfield 15	fwy:a	Landroid/os/IBinder;
    //   129: sipush 402
    //   132: aload 13
    //   134: aload 14
    //   136: iconst_0
    //   137: invokeinterface 45 5 0
    //   142: pop
    //   143: aload 14
    //   145: invokevirtual 48	android/os/Parcel:readException	()V
    //   148: aload 14
    //   150: invokevirtual 67	android/os/Parcel:recycle	()V
    //   153: aload 13
    //   155: invokevirtual 67	android/os/Parcel:recycle	()V
    //   158: return
    //   159: aconst_null
    //   160: astore_1
    //   161: goto -133 -> 28
    //   164: iconst_0
    //   165: istore 5
    //   167: goto -99 -> 68
    //   170: iconst_0
    //   171: istore 5
    //   173: goto -69 -> 104
    //   176: astore_1
    //   177: aload 14
    //   179: invokevirtual 67	android/os/Parcel:recycle	()V
    //   182: aload 13
    //   184: invokevirtual 67	android/os/Parcel:recycle	()V
    //   187: aload_1
    //   188: athrow
    // Local variable table:
    //   start	length	slot	name	signature
    //   0	189	0	this	fwy
    //   0	189	1	paramfwt	fwt
    //   0	189	2	paramString1	String
    //   0	189	3	paramString2	String
    //   0	189	4	paramString3	String
    //   0	189	5	paramInt1	int
    //   0	189	6	paramBoolean1	boolean
    //   0	189	7	paramInt2	int
    //   0	189	8	paramInt3	int
    //   0	189	9	paramString4	String
    //   0	189	10	paramBoolean2	boolean
    //   0	189	11	paramInt4	int
    //   0	189	12	paramInt5	int
    //   3	180	13	localParcel1	Parcel
    //   8	170	14	localParcel2	Parcel
    // Exception table:
    //   from	to	target	type
    //   10	17	176	finally
    //   21	28	176	finally
    //   28	60	176	finally
    //   68	96	176	finally
    //   104	148	176	finally
  }
  
  /* Error */
  public final void a(fwt paramfwt, String paramString1, String paramString2, String paramString3, String paramString4)
  {
    // Byte code:
    //   0: invokestatic 23	android/os/Parcel:obtain	()Landroid/os/Parcel;
    //   3: astore 6
    //   5: invokestatic 23	android/os/Parcel:obtain	()Landroid/os/Parcel;
    //   8: astore 7
    //   10: aload 6
    //   12: ldc 25
    //   14: invokevirtual 29	android/os/Parcel:writeInterfaceToken	(Ljava/lang/String;)V
    //   17: aload_1
    //   18: ifnull +75 -> 93
    //   21: aload_1
    //   22: invokeinterface 74 1 0
    //   27: astore_1
    //   28: aload 6
    //   30: aload_1
    //   31: invokevirtual 77	android/os/Parcel:writeStrongBinder	(Landroid/os/IBinder;)V
    //   34: aload 6
    //   36: aload_2
    //   37: invokevirtual 80	android/os/Parcel:writeString	(Ljava/lang/String;)V
    //   40: aload 6
    //   42: aload_3
    //   43: invokevirtual 80	android/os/Parcel:writeString	(Ljava/lang/String;)V
    //   46: aload 6
    //   48: aload 4
    //   50: invokevirtual 80	android/os/Parcel:writeString	(Ljava/lang/String;)V
    //   53: aload 6
    //   55: aload 5
    //   57: invokevirtual 80	android/os/Parcel:writeString	(Ljava/lang/String;)V
    //   60: aload_0
    //   61: getfield 15	fwy:a	Landroid/os/IBinder;
    //   64: bipush 27
    //   66: aload 6
    //   68: aload 7
    //   70: iconst_0
    //   71: invokeinterface 45 5 0
    //   76: pop
    //   77: aload 7
    //   79: invokevirtual 48	android/os/Parcel:readException	()V
    //   82: aload 7
    //   84: invokevirtual 67	android/os/Parcel:recycle	()V
    //   87: aload 6
    //   89: invokevirtual 67	android/os/Parcel:recycle	()V
    //   92: return
    //   93: aconst_null
    //   94: astore_1
    //   95: goto -67 -> 28
    //   98: astore_1
    //   99: aload 7
    //   101: invokevirtual 67	android/os/Parcel:recycle	()V
    //   104: aload 6
    //   106: invokevirtual 67	android/os/Parcel:recycle	()V
    //   109: aload_1
    //   110: athrow
    // Local variable table:
    //   start	length	slot	name	signature
    //   0	111	0	this	fwy
    //   0	111	1	paramfwt	fwt
    //   0	111	2	paramString1	String
    //   0	111	3	paramString2	String
    //   0	111	4	paramString3	String
    //   0	111	5	paramString4	String
    //   3	102	6	localParcel1	Parcel
    //   8	92	7	localParcel2	Parcel
    // Exception table:
    //   from	to	target	type
    //   10	17	98	finally
    //   21	28	98	finally
    //   28	82	98	finally
  }
  
  /* Error */
  public final void a(fwt paramfwt, String paramString1, String paramString2, String paramString3, String paramString4, int paramInt, String paramString5)
  {
    // Byte code:
    //   0: invokestatic 23	android/os/Parcel:obtain	()Landroid/os/Parcel;
    //   3: astore 8
    //   5: invokestatic 23	android/os/Parcel:obtain	()Landroid/os/Parcel;
    //   8: astore 9
    //   10: aload 8
    //   12: ldc 25
    //   14: invokevirtual 29	android/os/Parcel:writeInterfaceToken	(Ljava/lang/String;)V
    //   17: aload_1
    //   18: ifnull +90 -> 108
    //   21: aload_1
    //   22: invokeinterface 74 1 0
    //   27: astore_1
    //   28: aload 8
    //   30: aload_1
    //   31: invokevirtual 77	android/os/Parcel:writeStrongBinder	(Landroid/os/IBinder;)V
    //   34: aload 8
    //   36: aload_2
    //   37: invokevirtual 80	android/os/Parcel:writeString	(Ljava/lang/String;)V
    //   40: aload 8
    //   42: aload_3
    //   43: invokevirtual 80	android/os/Parcel:writeString	(Ljava/lang/String;)V
    //   46: aload 8
    //   48: aload 4
    //   50: invokevirtual 80	android/os/Parcel:writeString	(Ljava/lang/String;)V
    //   53: aload 8
    //   55: aload 5
    //   57: invokevirtual 80	android/os/Parcel:writeString	(Ljava/lang/String;)V
    //   60: aload 8
    //   62: iload 6
    //   64: invokevirtual 33	android/os/Parcel:writeInt	(I)V
    //   67: aload 8
    //   69: aload 7
    //   71: invokevirtual 80	android/os/Parcel:writeString	(Ljava/lang/String;)V
    //   74: aload_0
    //   75: getfield 15	fwy:a	Landroid/os/IBinder;
    //   78: sipush 303
    //   81: aload 8
    //   83: aload 9
    //   85: iconst_0
    //   86: invokeinterface 45 5 0
    //   91: pop
    //   92: aload 9
    //   94: invokevirtual 48	android/os/Parcel:readException	()V
    //   97: aload 9
    //   99: invokevirtual 67	android/os/Parcel:recycle	()V
    //   102: aload 8
    //   104: invokevirtual 67	android/os/Parcel:recycle	()V
    //   107: return
    //   108: aconst_null
    //   109: astore_1
    //   110: goto -82 -> 28
    //   113: astore_1
    //   114: aload 9
    //   116: invokevirtual 67	android/os/Parcel:recycle	()V
    //   119: aload 8
    //   121: invokevirtual 67	android/os/Parcel:recycle	()V
    //   124: aload_1
    //   125: athrow
    // Local variable table:
    //   start	length	slot	name	signature
    //   0	126	0	this	fwy
    //   0	126	1	paramfwt	fwt
    //   0	126	2	paramString1	String
    //   0	126	3	paramString2	String
    //   0	126	4	paramString3	String
    //   0	126	5	paramString4	String
    //   0	126	6	paramInt	int
    //   0	126	7	paramString5	String
    //   3	117	8	localParcel1	Parcel
    //   8	107	9	localParcel2	Parcel
    // Exception table:
    //   from	to	target	type
    //   10	17	113	finally
    //   21	28	113	finally
    //   28	97	113	finally
  }
  
  /* Error */
  public final void a(fwt paramfwt, String paramString1, String paramString2, String paramString3, String paramString4, boolean paramBoolean)
  {
    // Byte code:
    //   0: iconst_0
    //   1: istore 7
    //   3: invokestatic 23	android/os/Parcel:obtain	()Landroid/os/Parcel;
    //   6: astore 8
    //   8: invokestatic 23	android/os/Parcel:obtain	()Landroid/os/Parcel;
    //   11: astore 9
    //   13: aload 8
    //   15: ldc 25
    //   17: invokevirtual 29	android/os/Parcel:writeInterfaceToken	(Ljava/lang/String;)V
    //   20: aload_1
    //   21: ifnull +91 -> 112
    //   24: aload_1
    //   25: invokeinterface 74 1 0
    //   30: astore_1
    //   31: aload 8
    //   33: aload_1
    //   34: invokevirtual 77	android/os/Parcel:writeStrongBinder	(Landroid/os/IBinder;)V
    //   37: aload 8
    //   39: aload_2
    //   40: invokevirtual 80	android/os/Parcel:writeString	(Ljava/lang/String;)V
    //   43: aload 8
    //   45: aload_3
    //   46: invokevirtual 80	android/os/Parcel:writeString	(Ljava/lang/String;)V
    //   49: aload 8
    //   51: aload 4
    //   53: invokevirtual 80	android/os/Parcel:writeString	(Ljava/lang/String;)V
    //   56: aload 8
    //   58: aload 5
    //   60: invokevirtual 80	android/os/Parcel:writeString	(Ljava/lang/String;)V
    //   63: iload 6
    //   65: ifeq +6 -> 71
    //   68: iconst_1
    //   69: istore 7
    //   71: aload 8
    //   73: iload 7
    //   75: invokevirtual 33	android/os/Parcel:writeInt	(I)V
    //   78: aload_0
    //   79: getfield 15	fwy:a	Landroid/os/IBinder;
    //   82: sipush 701
    //   85: aload 8
    //   87: aload 9
    //   89: iconst_0
    //   90: invokeinterface 45 5 0
    //   95: pop
    //   96: aload 9
    //   98: invokevirtual 48	android/os/Parcel:readException	()V
    //   101: aload 9
    //   103: invokevirtual 67	android/os/Parcel:recycle	()V
    //   106: aload 8
    //   108: invokevirtual 67	android/os/Parcel:recycle	()V
    //   111: return
    //   112: aconst_null
    //   113: astore_1
    //   114: goto -83 -> 31
    //   117: astore_1
    //   118: aload 9
    //   120: invokevirtual 67	android/os/Parcel:recycle	()V
    //   123: aload 8
    //   125: invokevirtual 67	android/os/Parcel:recycle	()V
    //   128: aload_1
    //   129: athrow
    // Local variable table:
    //   start	length	slot	name	signature
    //   0	130	0	this	fwy
    //   0	130	1	paramfwt	fwt
    //   0	130	2	paramString1	String
    //   0	130	3	paramString2	String
    //   0	130	4	paramString3	String
    //   0	130	5	paramString4	String
    //   0	130	6	paramBoolean	boolean
    //   1	73	7	i	int
    //   6	118	8	localParcel1	Parcel
    //   11	108	9	localParcel2	Parcel
    // Exception table:
    //   from	to	target	type
    //   13	20	117	finally
    //   24	31	117	finally
    //   31	63	117	finally
    //   71	101	117	finally
  }
  
  /* Error */
  public final void a(fwt paramfwt, String paramString1, String paramString2, String paramString3, List<String> paramList)
  {
    // Byte code:
    //   0: invokestatic 23	android/os/Parcel:obtain	()Landroid/os/Parcel;
    //   3: astore 6
    //   5: invokestatic 23	android/os/Parcel:obtain	()Landroid/os/Parcel;
    //   8: astore 7
    //   10: aload 6
    //   12: ldc 25
    //   14: invokevirtual 29	android/os/Parcel:writeInterfaceToken	(Ljava/lang/String;)V
    //   17: aload_1
    //   18: ifnull +75 -> 93
    //   21: aload_1
    //   22: invokeinterface 74 1 0
    //   27: astore_1
    //   28: aload 6
    //   30: aload_1
    //   31: invokevirtual 77	android/os/Parcel:writeStrongBinder	(Landroid/os/IBinder;)V
    //   34: aload 6
    //   36: aload_2
    //   37: invokevirtual 80	android/os/Parcel:writeString	(Ljava/lang/String;)V
    //   40: aload 6
    //   42: aload_3
    //   43: invokevirtual 80	android/os/Parcel:writeString	(Ljava/lang/String;)V
    //   46: aload 6
    //   48: aload 4
    //   50: invokevirtual 80	android/os/Parcel:writeString	(Ljava/lang/String;)V
    //   53: aload 6
    //   55: aload 5
    //   57: invokevirtual 124	android/os/Parcel:writeStringList	(Ljava/util/List;)V
    //   60: aload_0
    //   61: getfield 15	fwy:a	Landroid/os/IBinder;
    //   64: bipush 28
    //   66: aload 6
    //   68: aload 7
    //   70: iconst_0
    //   71: invokeinterface 45 5 0
    //   76: pop
    //   77: aload 7
    //   79: invokevirtual 48	android/os/Parcel:readException	()V
    //   82: aload 7
    //   84: invokevirtual 67	android/os/Parcel:recycle	()V
    //   87: aload 6
    //   89: invokevirtual 67	android/os/Parcel:recycle	()V
    //   92: return
    //   93: aconst_null
    //   94: astore_1
    //   95: goto -67 -> 28
    //   98: astore_1
    //   99: aload 7
    //   101: invokevirtual 67	android/os/Parcel:recycle	()V
    //   104: aload 6
    //   106: invokevirtual 67	android/os/Parcel:recycle	()V
    //   109: aload_1
    //   110: athrow
    // Local variable table:
    //   start	length	slot	name	signature
    //   0	111	0	this	fwy
    //   0	111	1	paramfwt	fwt
    //   0	111	2	paramString1	String
    //   0	111	3	paramString2	String
    //   0	111	4	paramString3	String
    //   0	111	5	paramList	List<String>
    //   3	102	6	localParcel1	Parcel
    //   8	92	7	localParcel2	Parcel
    // Exception table:
    //   from	to	target	type
    //   10	17	98	finally
    //   21	28	98	finally
    //   28	82	98	finally
  }
  
  /* Error */
  public final void a(fwt paramfwt, String paramString1, String paramString2, String paramString3, List<String> paramList, int paramInt, boolean paramBoolean, long paramLong)
  {
    // Byte code:
    //   0: iconst_0
    //   1: istore 10
    //   3: invokestatic 23	android/os/Parcel:obtain	()Landroid/os/Parcel;
    //   6: astore 11
    //   8: invokestatic 23	android/os/Parcel:obtain	()Landroid/os/Parcel;
    //   11: astore 12
    //   13: aload 11
    //   15: ldc 25
    //   17: invokevirtual 29	android/os/Parcel:writeInterfaceToken	(Ljava/lang/String;)V
    //   20: aload_1
    //   21: ifnull +107 -> 128
    //   24: aload_1
    //   25: invokeinterface 74 1 0
    //   30: astore_1
    //   31: aload 11
    //   33: aload_1
    //   34: invokevirtual 77	android/os/Parcel:writeStrongBinder	(Landroid/os/IBinder;)V
    //   37: aload 11
    //   39: aload_2
    //   40: invokevirtual 80	android/os/Parcel:writeString	(Ljava/lang/String;)V
    //   43: aload 11
    //   45: aload_3
    //   46: invokevirtual 80	android/os/Parcel:writeString	(Ljava/lang/String;)V
    //   49: aload 11
    //   51: aload 4
    //   53: invokevirtual 80	android/os/Parcel:writeString	(Ljava/lang/String;)V
    //   56: aload 11
    //   58: aload 5
    //   60: invokevirtual 124	android/os/Parcel:writeStringList	(Ljava/util/List;)V
    //   63: aload 11
    //   65: iload 6
    //   67: invokevirtual 33	android/os/Parcel:writeInt	(I)V
    //   70: iload 10
    //   72: istore 6
    //   74: iload 7
    //   76: ifeq +6 -> 82
    //   79: iconst_1
    //   80: istore 6
    //   82: aload 11
    //   84: iload 6
    //   86: invokevirtual 33	android/os/Parcel:writeInt	(I)V
    //   89: aload 11
    //   91: lload 8
    //   93: invokevirtual 86	android/os/Parcel:writeLong	(J)V
    //   96: aload_0
    //   97: getfield 15	fwy:a	Landroid/os/IBinder;
    //   100: iconst_4
    //   101: aload 11
    //   103: aload 12
    //   105: iconst_0
    //   106: invokeinterface 45 5 0
    //   111: pop
    //   112: aload 12
    //   114: invokevirtual 48	android/os/Parcel:readException	()V
    //   117: aload 12
    //   119: invokevirtual 67	android/os/Parcel:recycle	()V
    //   122: aload 11
    //   124: invokevirtual 67	android/os/Parcel:recycle	()V
    //   127: return
    //   128: aconst_null
    //   129: astore_1
    //   130: goto -99 -> 31
    //   133: astore_1
    //   134: aload 12
    //   136: invokevirtual 67	android/os/Parcel:recycle	()V
    //   139: aload 11
    //   141: invokevirtual 67	android/os/Parcel:recycle	()V
    //   144: aload_1
    //   145: athrow
    // Local variable table:
    //   start	length	slot	name	signature
    //   0	146	0	this	fwy
    //   0	146	1	paramfwt	fwt
    //   0	146	2	paramString1	String
    //   0	146	3	paramString2	String
    //   0	146	4	paramString3	String
    //   0	146	5	paramList	List<String>
    //   0	146	6	paramInt	int
    //   0	146	7	paramBoolean	boolean
    //   0	146	8	paramLong	long
    //   1	70	10	i	int
    //   6	134	11	localParcel1	Parcel
    //   11	124	12	localParcel2	Parcel
    // Exception table:
    //   from	to	target	type
    //   13	20	133	finally
    //   24	31	133	finally
    //   31	70	133	finally
    //   82	117	133	finally
  }
  
  /* Error */
  public final void a(fwt paramfwt, String paramString1, String paramString2, String paramString3, List<String> paramList, int paramInt1, boolean paramBoolean, long paramLong, String paramString4, int paramInt2)
  {
    // Byte code:
    //   0: invokestatic 23	android/os/Parcel:obtain	()Landroid/os/Parcel;
    //   3: astore 12
    //   5: invokestatic 23	android/os/Parcel:obtain	()Landroid/os/Parcel;
    //   8: astore 13
    //   10: aload 12
    //   12: ldc 25
    //   14: invokevirtual 29	android/os/Parcel:writeInterfaceToken	(Ljava/lang/String;)V
    //   17: aload_1
    //   18: ifnull +118 -> 136
    //   21: aload_1
    //   22: invokeinterface 74 1 0
    //   27: astore_1
    //   28: aload 12
    //   30: aload_1
    //   31: invokevirtual 77	android/os/Parcel:writeStrongBinder	(Landroid/os/IBinder;)V
    //   34: aload 12
    //   36: aload_2
    //   37: invokevirtual 80	android/os/Parcel:writeString	(Ljava/lang/String;)V
    //   40: aload 12
    //   42: aload_3
    //   43: invokevirtual 80	android/os/Parcel:writeString	(Ljava/lang/String;)V
    //   46: aload 12
    //   48: aload 4
    //   50: invokevirtual 80	android/os/Parcel:writeString	(Ljava/lang/String;)V
    //   53: aload 12
    //   55: aload 5
    //   57: invokevirtual 124	android/os/Parcel:writeStringList	(Ljava/util/List;)V
    //   60: aload 12
    //   62: iload 6
    //   64: invokevirtual 33	android/os/Parcel:writeInt	(I)V
    //   67: iload 7
    //   69: ifeq +72 -> 141
    //   72: iconst_1
    //   73: istore 6
    //   75: aload 12
    //   77: iload 6
    //   79: invokevirtual 33	android/os/Parcel:writeInt	(I)V
    //   82: aload 12
    //   84: lload 8
    //   86: invokevirtual 86	android/os/Parcel:writeLong	(J)V
    //   89: aload 12
    //   91: aload 10
    //   93: invokevirtual 80	android/os/Parcel:writeString	(Ljava/lang/String;)V
    //   96: aload 12
    //   98: iload 11
    //   100: invokevirtual 33	android/os/Parcel:writeInt	(I)V
    //   103: aload_0
    //   104: getfield 15	fwy:a	Landroid/os/IBinder;
    //   107: bipush 21
    //   109: aload 12
    //   111: aload 13
    //   113: iconst_0
    //   114: invokeinterface 45 5 0
    //   119: pop
    //   120: aload 13
    //   122: invokevirtual 48	android/os/Parcel:readException	()V
    //   125: aload 13
    //   127: invokevirtual 67	android/os/Parcel:recycle	()V
    //   130: aload 12
    //   132: invokevirtual 67	android/os/Parcel:recycle	()V
    //   135: return
    //   136: aconst_null
    //   137: astore_1
    //   138: goto -110 -> 28
    //   141: iconst_0
    //   142: istore 6
    //   144: goto -69 -> 75
    //   147: astore_1
    //   148: aload 13
    //   150: invokevirtual 67	android/os/Parcel:recycle	()V
    //   153: aload 12
    //   155: invokevirtual 67	android/os/Parcel:recycle	()V
    //   158: aload_1
    //   159: athrow
    // Local variable table:
    //   start	length	slot	name	signature
    //   0	160	0	this	fwy
    //   0	160	1	paramfwt	fwt
    //   0	160	2	paramString1	String
    //   0	160	3	paramString2	String
    //   0	160	4	paramString3	String
    //   0	160	5	paramList	List<String>
    //   0	160	6	paramInt1	int
    //   0	160	7	paramBoolean	boolean
    //   0	160	8	paramLong	long
    //   0	160	10	paramString4	String
    //   0	160	11	paramInt2	int
    //   3	151	12	localParcel1	Parcel
    //   8	141	13	localParcel2	Parcel
    // Exception table:
    //   from	to	target	type
    //   10	17	147	finally
    //   21	28	147	finally
    //   28	67	147	finally
    //   75	125	147	finally
  }
  
  /* Error */
  public final void a(fwt paramfwt, String paramString1, String paramString2, String paramString3, List<String> paramList, int paramInt1, boolean paramBoolean, long paramLong, String paramString4, int paramInt2, int paramInt3)
  {
    // Byte code:
    //   0: invokestatic 23	android/os/Parcel:obtain	()Landroid/os/Parcel;
    //   3: astore 13
    //   5: invokestatic 23	android/os/Parcel:obtain	()Landroid/os/Parcel;
    //   8: astore 14
    //   10: aload 13
    //   12: ldc 25
    //   14: invokevirtual 29	android/os/Parcel:writeInterfaceToken	(Ljava/lang/String;)V
    //   17: aload_1
    //   18: ifnull +126 -> 144
    //   21: aload_1
    //   22: invokeinterface 74 1 0
    //   27: astore_1
    //   28: aload 13
    //   30: aload_1
    //   31: invokevirtual 77	android/os/Parcel:writeStrongBinder	(Landroid/os/IBinder;)V
    //   34: aload 13
    //   36: aload_2
    //   37: invokevirtual 80	android/os/Parcel:writeString	(Ljava/lang/String;)V
    //   40: aload 13
    //   42: aload_3
    //   43: invokevirtual 80	android/os/Parcel:writeString	(Ljava/lang/String;)V
    //   46: aload 13
    //   48: aload 4
    //   50: invokevirtual 80	android/os/Parcel:writeString	(Ljava/lang/String;)V
    //   53: aload 13
    //   55: aload 5
    //   57: invokevirtual 124	android/os/Parcel:writeStringList	(Ljava/util/List;)V
    //   60: aload 13
    //   62: iload 6
    //   64: invokevirtual 33	android/os/Parcel:writeInt	(I)V
    //   67: iload 7
    //   69: ifeq +80 -> 149
    //   72: iconst_1
    //   73: istore 6
    //   75: aload 13
    //   77: iload 6
    //   79: invokevirtual 33	android/os/Parcel:writeInt	(I)V
    //   82: aload 13
    //   84: lload 8
    //   86: invokevirtual 86	android/os/Parcel:writeLong	(J)V
    //   89: aload 13
    //   91: aload 10
    //   93: invokevirtual 80	android/os/Parcel:writeString	(Ljava/lang/String;)V
    //   96: aload 13
    //   98: iload 11
    //   100: invokevirtual 33	android/os/Parcel:writeInt	(I)V
    //   103: aload 13
    //   105: iload 12
    //   107: invokevirtual 33	android/os/Parcel:writeInt	(I)V
    //   110: aload_0
    //   111: getfield 15	fwy:a	Landroid/os/IBinder;
    //   114: sipush 401
    //   117: aload 13
    //   119: aload 14
    //   121: iconst_0
    //   122: invokeinterface 45 5 0
    //   127: pop
    //   128: aload 14
    //   130: invokevirtual 48	android/os/Parcel:readException	()V
    //   133: aload 14
    //   135: invokevirtual 67	android/os/Parcel:recycle	()V
    //   138: aload 13
    //   140: invokevirtual 67	android/os/Parcel:recycle	()V
    //   143: return
    //   144: aconst_null
    //   145: astore_1
    //   146: goto -118 -> 28
    //   149: iconst_0
    //   150: istore 6
    //   152: goto -77 -> 75
    //   155: astore_1
    //   156: aload 14
    //   158: invokevirtual 67	android/os/Parcel:recycle	()V
    //   161: aload 13
    //   163: invokevirtual 67	android/os/Parcel:recycle	()V
    //   166: aload_1
    //   167: athrow
    // Local variable table:
    //   start	length	slot	name	signature
    //   0	168	0	this	fwy
    //   0	168	1	paramfwt	fwt
    //   0	168	2	paramString1	String
    //   0	168	3	paramString2	String
    //   0	168	4	paramString3	String
    //   0	168	5	paramList	List<String>
    //   0	168	6	paramInt1	int
    //   0	168	7	paramBoolean	boolean
    //   0	168	8	paramLong	long
    //   0	168	10	paramString4	String
    //   0	168	11	paramInt2	int
    //   0	168	12	paramInt3	int
    //   3	159	13	localParcel1	Parcel
    //   8	149	14	localParcel2	Parcel
    // Exception table:
    //   from	to	target	type
    //   10	17	155	finally
    //   21	28	155	finally
    //   28	67	155	finally
    //   75	133	155	finally
  }
  
  /* Error */
  public final void a(fwt paramfwt, String paramString1, String paramString2, String paramString3, List<String> paramList, int paramInt1, boolean paramBoolean, long paramLong, String paramString4, int paramInt2, int paramInt3, int paramInt4)
  {
    // Byte code:
    //   0: invokestatic 23	android/os/Parcel:obtain	()Landroid/os/Parcel;
    //   3: astore 14
    //   5: invokestatic 23	android/os/Parcel:obtain	()Landroid/os/Parcel;
    //   8: astore 15
    //   10: aload 14
    //   12: ldc 25
    //   14: invokevirtual 29	android/os/Parcel:writeInterfaceToken	(Ljava/lang/String;)V
    //   17: aload_1
    //   18: ifnull +133 -> 151
    //   21: aload_1
    //   22: invokeinterface 74 1 0
    //   27: astore_1
    //   28: aload 14
    //   30: aload_1
    //   31: invokevirtual 77	android/os/Parcel:writeStrongBinder	(Landroid/os/IBinder;)V
    //   34: aload 14
    //   36: aload_2
    //   37: invokevirtual 80	android/os/Parcel:writeString	(Ljava/lang/String;)V
    //   40: aload 14
    //   42: aload_3
    //   43: invokevirtual 80	android/os/Parcel:writeString	(Ljava/lang/String;)V
    //   46: aload 14
    //   48: aload 4
    //   50: invokevirtual 80	android/os/Parcel:writeString	(Ljava/lang/String;)V
    //   53: aload 14
    //   55: aload 5
    //   57: invokevirtual 124	android/os/Parcel:writeStringList	(Ljava/util/List;)V
    //   60: aload 14
    //   62: iload 6
    //   64: invokevirtual 33	android/os/Parcel:writeInt	(I)V
    //   67: iload 7
    //   69: ifeq +87 -> 156
    //   72: iconst_1
    //   73: istore 6
    //   75: aload 14
    //   77: iload 6
    //   79: invokevirtual 33	android/os/Parcel:writeInt	(I)V
    //   82: aload 14
    //   84: lload 8
    //   86: invokevirtual 86	android/os/Parcel:writeLong	(J)V
    //   89: aload 14
    //   91: aload 10
    //   93: invokevirtual 80	android/os/Parcel:writeString	(Ljava/lang/String;)V
    //   96: aload 14
    //   98: iload 11
    //   100: invokevirtual 33	android/os/Parcel:writeInt	(I)V
    //   103: aload 14
    //   105: iload 12
    //   107: invokevirtual 33	android/os/Parcel:writeInt	(I)V
    //   110: aload 14
    //   112: iload 13
    //   114: invokevirtual 33	android/os/Parcel:writeInt	(I)V
    //   117: aload_0
    //   118: getfield 15	fwy:a	Landroid/os/IBinder;
    //   121: sipush 404
    //   124: aload 14
    //   126: aload 15
    //   128: iconst_0
    //   129: invokeinterface 45 5 0
    //   134: pop
    //   135: aload 15
    //   137: invokevirtual 48	android/os/Parcel:readException	()V
    //   140: aload 15
    //   142: invokevirtual 67	android/os/Parcel:recycle	()V
    //   145: aload 14
    //   147: invokevirtual 67	android/os/Parcel:recycle	()V
    //   150: return
    //   151: aconst_null
    //   152: astore_1
    //   153: goto -125 -> 28
    //   156: iconst_0
    //   157: istore 6
    //   159: goto -84 -> 75
    //   162: astore_1
    //   163: aload 15
    //   165: invokevirtual 67	android/os/Parcel:recycle	()V
    //   168: aload 14
    //   170: invokevirtual 67	android/os/Parcel:recycle	()V
    //   173: aload_1
    //   174: athrow
    // Local variable table:
    //   start	length	slot	name	signature
    //   0	175	0	this	fwy
    //   0	175	1	paramfwt	fwt
    //   0	175	2	paramString1	String
    //   0	175	3	paramString2	String
    //   0	175	4	paramString3	String
    //   0	175	5	paramList	List<String>
    //   0	175	6	paramInt1	int
    //   0	175	7	paramBoolean	boolean
    //   0	175	8	paramLong	long
    //   0	175	10	paramString4	String
    //   0	175	11	paramInt2	int
    //   0	175	12	paramInt3	int
    //   0	175	13	paramInt4	int
    //   3	166	14	localParcel1	Parcel
    //   8	156	15	localParcel2	Parcel
    // Exception table:
    //   from	to	target	type
    //   10	17	162	finally
    //   21	28	162	finally
    //   28	67	162	finally
    //   75	140	162	finally
  }
  
  /* Error */
  public final void a(fwt paramfwt, String paramString1, String paramString2, String paramString3, List<String> paramList1, List<String> paramList2)
  {
    // Byte code:
    //   0: invokestatic 23	android/os/Parcel:obtain	()Landroid/os/Parcel;
    //   3: astore 7
    //   5: invokestatic 23	android/os/Parcel:obtain	()Landroid/os/Parcel;
    //   8: astore 8
    //   10: aload 7
    //   12: ldc 25
    //   14: invokevirtual 29	android/os/Parcel:writeInterfaceToken	(Ljava/lang/String;)V
    //   17: aload_1
    //   18: ifnull +82 -> 100
    //   21: aload_1
    //   22: invokeinterface 74 1 0
    //   27: astore_1
    //   28: aload 7
    //   30: aload_1
    //   31: invokevirtual 77	android/os/Parcel:writeStrongBinder	(Landroid/os/IBinder;)V
    //   34: aload 7
    //   36: aload_2
    //   37: invokevirtual 80	android/os/Parcel:writeString	(Ljava/lang/String;)V
    //   40: aload 7
    //   42: aload_3
    //   43: invokevirtual 80	android/os/Parcel:writeString	(Ljava/lang/String;)V
    //   46: aload 7
    //   48: aload 4
    //   50: invokevirtual 80	android/os/Parcel:writeString	(Ljava/lang/String;)V
    //   53: aload 7
    //   55: aload 5
    //   57: invokevirtual 124	android/os/Parcel:writeStringList	(Ljava/util/List;)V
    //   60: aload 7
    //   62: aload 6
    //   64: invokevirtual 124	android/os/Parcel:writeStringList	(Ljava/util/List;)V
    //   67: aload_0
    //   68: getfield 15	fwy:a	Landroid/os/IBinder;
    //   71: bipush 14
    //   73: aload 7
    //   75: aload 8
    //   77: iconst_0
    //   78: invokeinterface 45 5 0
    //   83: pop
    //   84: aload 8
    //   86: invokevirtual 48	android/os/Parcel:readException	()V
    //   89: aload 8
    //   91: invokevirtual 67	android/os/Parcel:recycle	()V
    //   94: aload 7
    //   96: invokevirtual 67	android/os/Parcel:recycle	()V
    //   99: return
    //   100: aconst_null
    //   101: astore_1
    //   102: goto -74 -> 28
    //   105: astore_1
    //   106: aload 8
    //   108: invokevirtual 67	android/os/Parcel:recycle	()V
    //   111: aload 7
    //   113: invokevirtual 67	android/os/Parcel:recycle	()V
    //   116: aload_1
    //   117: athrow
    // Local variable table:
    //   start	length	slot	name	signature
    //   0	118	0	this	fwy
    //   0	118	1	paramfwt	fwt
    //   0	118	2	paramString1	String
    //   0	118	3	paramString2	String
    //   0	118	4	paramString3	String
    //   0	118	5	paramList1	List<String>
    //   0	118	6	paramList2	List<String>
    //   3	109	7	localParcel1	Parcel
    //   8	99	8	localParcel2	Parcel
    // Exception table:
    //   from	to	target	type
    //   10	17	105	finally
    //   21	28	105	finally
    //   28	89	105	finally
  }
  
  /* Error */
  public final void a(fwt paramfwt, String paramString1, String paramString2, String paramString3, List<String> paramList1, List<String> paramList2, com.google.android.gms.common.server.FavaDiagnosticsEntity paramFavaDiagnosticsEntity)
  {
    // Byte code:
    //   0: invokestatic 23	android/os/Parcel:obtain	()Landroid/os/Parcel;
    //   3: astore 8
    //   5: invokestatic 23	android/os/Parcel:obtain	()Landroid/os/Parcel;
    //   8: astore 9
    //   10: aload 8
    //   12: ldc 25
    //   14: invokevirtual 29	android/os/Parcel:writeInterfaceToken	(Ljava/lang/String;)V
    //   17: aload_1
    //   18: ifnull +101 -> 119
    //   21: aload_1
    //   22: invokeinterface 74 1 0
    //   27: astore_1
    //   28: aload 8
    //   30: aload_1
    //   31: invokevirtual 77	android/os/Parcel:writeStrongBinder	(Landroid/os/IBinder;)V
    //   34: aload 8
    //   36: aload_2
    //   37: invokevirtual 80	android/os/Parcel:writeString	(Ljava/lang/String;)V
    //   40: aload 8
    //   42: aload_3
    //   43: invokevirtual 80	android/os/Parcel:writeString	(Ljava/lang/String;)V
    //   46: aload 8
    //   48: aload 4
    //   50: invokevirtual 80	android/os/Parcel:writeString	(Ljava/lang/String;)V
    //   53: aload 8
    //   55: aload 5
    //   57: invokevirtual 124	android/os/Parcel:writeStringList	(Ljava/util/List;)V
    //   60: aload 8
    //   62: aload 6
    //   64: invokevirtual 124	android/os/Parcel:writeStringList	(Ljava/util/List;)V
    //   67: aload 7
    //   69: ifnull +55 -> 124
    //   72: aload 8
    //   74: iconst_1
    //   75: invokevirtual 33	android/os/Parcel:writeInt	(I)V
    //   78: aload 7
    //   80: aload 8
    //   82: iconst_0
    //   83: invokevirtual 161	com/google/android/gms/common/server/FavaDiagnosticsEntity:writeToParcel	(Landroid/os/Parcel;I)V
    //   86: aload_0
    //   87: getfield 15	fwy:a	Landroid/os/IBinder;
    //   90: bipush 23
    //   92: aload 8
    //   94: aload 9
    //   96: iconst_0
    //   97: invokeinterface 45 5 0
    //   102: pop
    //   103: aload 9
    //   105: invokevirtual 48	android/os/Parcel:readException	()V
    //   108: aload 9
    //   110: invokevirtual 67	android/os/Parcel:recycle	()V
    //   113: aload 8
    //   115: invokevirtual 67	android/os/Parcel:recycle	()V
    //   118: return
    //   119: aconst_null
    //   120: astore_1
    //   121: goto -93 -> 28
    //   124: aload 8
    //   126: iconst_0
    //   127: invokevirtual 33	android/os/Parcel:writeInt	(I)V
    //   130: goto -44 -> 86
    //   133: astore_1
    //   134: aload 9
    //   136: invokevirtual 67	android/os/Parcel:recycle	()V
    //   139: aload 8
    //   141: invokevirtual 67	android/os/Parcel:recycle	()V
    //   144: aload_1
    //   145: athrow
    // Local variable table:
    //   start	length	slot	name	signature
    //   0	146	0	this	fwy
    //   0	146	1	paramfwt	fwt
    //   0	146	2	paramString1	String
    //   0	146	3	paramString2	String
    //   0	146	4	paramString3	String
    //   0	146	5	paramList1	List<String>
    //   0	146	6	paramList2	List<String>
    //   0	146	7	paramFavaDiagnosticsEntity	com.google.android.gms.common.server.FavaDiagnosticsEntity
    //   3	137	8	localParcel1	Parcel
    //   8	127	9	localParcel2	Parcel
    // Exception table:
    //   from	to	target	type
    //   10	17	133	finally
    //   21	28	133	finally
    //   28	67	133	finally
    //   72	86	133	finally
    //   86	108	133	finally
    //   124	130	133	finally
  }
  
  /* Error */
  public final void a(fwt paramfwt, String paramString1, String paramString2, String paramString3, boolean paramBoolean)
  {
    // Byte code:
    //   0: iconst_0
    //   1: istore 6
    //   3: invokestatic 23	android/os/Parcel:obtain	()Landroid/os/Parcel;
    //   6: astore 7
    //   8: invokestatic 23	android/os/Parcel:obtain	()Landroid/os/Parcel;
    //   11: astore 8
    //   13: aload 7
    //   15: ldc 25
    //   17: invokevirtual 29	android/os/Parcel:writeInterfaceToken	(Ljava/lang/String;)V
    //   20: aload_1
    //   21: ifnull +83 -> 104
    //   24: aload_1
    //   25: invokeinterface 74 1 0
    //   30: astore_1
    //   31: aload 7
    //   33: aload_1
    //   34: invokevirtual 77	android/os/Parcel:writeStrongBinder	(Landroid/os/IBinder;)V
    //   37: aload 7
    //   39: aload_2
    //   40: invokevirtual 80	android/os/Parcel:writeString	(Ljava/lang/String;)V
    //   43: aload 7
    //   45: aload_3
    //   46: invokevirtual 80	android/os/Parcel:writeString	(Ljava/lang/String;)V
    //   49: aload 7
    //   51: aload 4
    //   53: invokevirtual 80	android/os/Parcel:writeString	(Ljava/lang/String;)V
    //   56: iload 5
    //   58: ifeq +6 -> 64
    //   61: iconst_1
    //   62: istore 6
    //   64: aload 7
    //   66: iload 6
    //   68: invokevirtual 33	android/os/Parcel:writeInt	(I)V
    //   71: aload_0
    //   72: getfield 15	fwy:a	Landroid/os/IBinder;
    //   75: bipush 7
    //   77: aload 7
    //   79: aload 8
    //   81: iconst_0
    //   82: invokeinterface 45 5 0
    //   87: pop
    //   88: aload 8
    //   90: invokevirtual 48	android/os/Parcel:readException	()V
    //   93: aload 8
    //   95: invokevirtual 67	android/os/Parcel:recycle	()V
    //   98: aload 7
    //   100: invokevirtual 67	android/os/Parcel:recycle	()V
    //   103: return
    //   104: aconst_null
    //   105: astore_1
    //   106: goto -75 -> 31
    //   109: astore_1
    //   110: aload 8
    //   112: invokevirtual 67	android/os/Parcel:recycle	()V
    //   115: aload 7
    //   117: invokevirtual 67	android/os/Parcel:recycle	()V
    //   120: aload_1
    //   121: athrow
    // Local variable table:
    //   start	length	slot	name	signature
    //   0	122	0	this	fwy
    //   0	122	1	paramfwt	fwt
    //   0	122	2	paramString1	String
    //   0	122	3	paramString2	String
    //   0	122	4	paramString3	String
    //   0	122	5	paramBoolean	boolean
    //   1	66	6	i	int
    //   6	110	7	localParcel1	Parcel
    //   11	100	8	localParcel2	Parcel
    // Exception table:
    //   from	to	target	type
    //   13	20	109	finally
    //   24	31	109	finally
    //   31	56	109	finally
    //   64	93	109	finally
  }
  
  /* Error */
  public final void a(fwt paramfwt, String paramString1, String paramString2, String paramString3, boolean paramBoolean, int paramInt)
  {
    // Byte code:
    //   0: iconst_0
    //   1: istore 7
    //   3: invokestatic 23	android/os/Parcel:obtain	()Landroid/os/Parcel;
    //   6: astore 8
    //   8: invokestatic 23	android/os/Parcel:obtain	()Landroid/os/Parcel;
    //   11: astore 9
    //   13: aload 8
    //   15: ldc 25
    //   17: invokevirtual 29	android/os/Parcel:writeInterfaceToken	(Ljava/lang/String;)V
    //   20: aload_1
    //   21: ifnull +90 -> 111
    //   24: aload_1
    //   25: invokeinterface 74 1 0
    //   30: astore_1
    //   31: aload 8
    //   33: aload_1
    //   34: invokevirtual 77	android/os/Parcel:writeStrongBinder	(Landroid/os/IBinder;)V
    //   37: aload 8
    //   39: aload_2
    //   40: invokevirtual 80	android/os/Parcel:writeString	(Ljava/lang/String;)V
    //   43: aload 8
    //   45: aload_3
    //   46: invokevirtual 80	android/os/Parcel:writeString	(Ljava/lang/String;)V
    //   49: aload 8
    //   51: aload 4
    //   53: invokevirtual 80	android/os/Parcel:writeString	(Ljava/lang/String;)V
    //   56: iload 5
    //   58: ifeq +6 -> 64
    //   61: iconst_1
    //   62: istore 7
    //   64: aload 8
    //   66: iload 7
    //   68: invokevirtual 33	android/os/Parcel:writeInt	(I)V
    //   71: aload 8
    //   73: iload 6
    //   75: invokevirtual 33	android/os/Parcel:writeInt	(I)V
    //   78: aload_0
    //   79: getfield 15	fwy:a	Landroid/os/IBinder;
    //   82: bipush 9
    //   84: aload 8
    //   86: aload 9
    //   88: iconst_0
    //   89: invokeinterface 45 5 0
    //   94: pop
    //   95: aload 9
    //   97: invokevirtual 48	android/os/Parcel:readException	()V
    //   100: aload 9
    //   102: invokevirtual 67	android/os/Parcel:recycle	()V
    //   105: aload 8
    //   107: invokevirtual 67	android/os/Parcel:recycle	()V
    //   110: return
    //   111: aconst_null
    //   112: astore_1
    //   113: goto -82 -> 31
    //   116: astore_1
    //   117: aload 9
    //   119: invokevirtual 67	android/os/Parcel:recycle	()V
    //   122: aload 8
    //   124: invokevirtual 67	android/os/Parcel:recycle	()V
    //   127: aload_1
    //   128: athrow
    // Local variable table:
    //   start	length	slot	name	signature
    //   0	129	0	this	fwy
    //   0	129	1	paramfwt	fwt
    //   0	129	2	paramString1	String
    //   0	129	3	paramString2	String
    //   0	129	4	paramString3	String
    //   0	129	5	paramBoolean	boolean
    //   0	129	6	paramInt	int
    //   1	66	7	i	int
    //   6	117	8	localParcel1	Parcel
    //   11	107	9	localParcel2	Parcel
    // Exception table:
    //   from	to	target	type
    //   13	20	116	finally
    //   24	31	116	finally
    //   31	56	116	finally
    //   64	100	116	finally
  }
  
  /* Error */
  public final void a(fwt paramfwt, String paramString1, String paramString2, String paramString3, boolean paramBoolean, int paramInt1, int paramInt2)
  {
    // Byte code:
    //   0: iconst_0
    //   1: istore 8
    //   3: invokestatic 23	android/os/Parcel:obtain	()Landroid/os/Parcel;
    //   6: astore 9
    //   8: invokestatic 23	android/os/Parcel:obtain	()Landroid/os/Parcel;
    //   11: astore 10
    //   13: aload 9
    //   15: ldc 25
    //   17: invokevirtual 29	android/os/Parcel:writeInterfaceToken	(Ljava/lang/String;)V
    //   20: aload_1
    //   21: ifnull +98 -> 119
    //   24: aload_1
    //   25: invokeinterface 74 1 0
    //   30: astore_1
    //   31: aload 9
    //   33: aload_1
    //   34: invokevirtual 77	android/os/Parcel:writeStrongBinder	(Landroid/os/IBinder;)V
    //   37: aload 9
    //   39: aload_2
    //   40: invokevirtual 80	android/os/Parcel:writeString	(Ljava/lang/String;)V
    //   43: aload 9
    //   45: aload_3
    //   46: invokevirtual 80	android/os/Parcel:writeString	(Ljava/lang/String;)V
    //   49: aload 9
    //   51: aload 4
    //   53: invokevirtual 80	android/os/Parcel:writeString	(Ljava/lang/String;)V
    //   56: iload 5
    //   58: ifeq +6 -> 64
    //   61: iconst_1
    //   62: istore 8
    //   64: aload 9
    //   66: iload 8
    //   68: invokevirtual 33	android/os/Parcel:writeInt	(I)V
    //   71: aload 9
    //   73: iload 6
    //   75: invokevirtual 33	android/os/Parcel:writeInt	(I)V
    //   78: aload 9
    //   80: iload 7
    //   82: invokevirtual 33	android/os/Parcel:writeInt	(I)V
    //   85: aload_0
    //   86: getfield 15	fwy:a	Landroid/os/IBinder;
    //   89: sipush 201
    //   92: aload 9
    //   94: aload 10
    //   96: iconst_0
    //   97: invokeinterface 45 5 0
    //   102: pop
    //   103: aload 10
    //   105: invokevirtual 48	android/os/Parcel:readException	()V
    //   108: aload 10
    //   110: invokevirtual 67	android/os/Parcel:recycle	()V
    //   113: aload 9
    //   115: invokevirtual 67	android/os/Parcel:recycle	()V
    //   118: return
    //   119: aconst_null
    //   120: astore_1
    //   121: goto -90 -> 31
    //   124: astore_1
    //   125: aload 10
    //   127: invokevirtual 67	android/os/Parcel:recycle	()V
    //   130: aload 9
    //   132: invokevirtual 67	android/os/Parcel:recycle	()V
    //   135: aload_1
    //   136: athrow
    // Local variable table:
    //   start	length	slot	name	signature
    //   0	137	0	this	fwy
    //   0	137	1	paramfwt	fwt
    //   0	137	2	paramString1	String
    //   0	137	3	paramString2	String
    //   0	137	4	paramString3	String
    //   0	137	5	paramBoolean	boolean
    //   0	137	6	paramInt1	int
    //   0	137	7	paramInt2	int
    //   1	66	8	i	int
    //   6	125	9	localParcel1	Parcel
    //   11	115	10	localParcel2	Parcel
    // Exception table:
    //   from	to	target	type
    //   13	20	124	finally
    //   24	31	124	finally
    //   31	56	124	finally
    //   64	108	124	finally
  }
  
  /* Error */
  public final void a(fwt paramfwt, String paramString, boolean paramBoolean, String[] paramArrayOfString)
  {
    // Byte code:
    //   0: iconst_0
    //   1: istore 5
    //   3: invokestatic 23	android/os/Parcel:obtain	()Landroid/os/Parcel;
    //   6: astore 6
    //   8: invokestatic 23	android/os/Parcel:obtain	()Landroid/os/Parcel;
    //   11: astore 7
    //   13: aload 6
    //   15: ldc 25
    //   17: invokevirtual 29	android/os/Parcel:writeInterfaceToken	(Ljava/lang/String;)V
    //   20: aload_1
    //   21: ifnull +76 -> 97
    //   24: aload_1
    //   25: invokeinterface 74 1 0
    //   30: astore_1
    //   31: aload 6
    //   33: aload_1
    //   34: invokevirtual 77	android/os/Parcel:writeStrongBinder	(Landroid/os/IBinder;)V
    //   37: aload 6
    //   39: aload_2
    //   40: invokevirtual 80	android/os/Parcel:writeString	(Ljava/lang/String;)V
    //   43: iload_3
    //   44: ifeq +6 -> 50
    //   47: iconst_1
    //   48: istore 5
    //   50: aload 6
    //   52: iload 5
    //   54: invokevirtual 33	android/os/Parcel:writeInt	(I)V
    //   57: aload 6
    //   59: aload 4
    //   61: invokevirtual 170	android/os/Parcel:writeStringArray	([Ljava/lang/String;)V
    //   64: aload_0
    //   65: getfield 15	fwy:a	Landroid/os/IBinder;
    //   68: bipush 10
    //   70: aload 6
    //   72: aload 7
    //   74: iconst_0
    //   75: invokeinterface 45 5 0
    //   80: pop
    //   81: aload 7
    //   83: invokevirtual 48	android/os/Parcel:readException	()V
    //   86: aload 7
    //   88: invokevirtual 67	android/os/Parcel:recycle	()V
    //   91: aload 6
    //   93: invokevirtual 67	android/os/Parcel:recycle	()V
    //   96: return
    //   97: aconst_null
    //   98: astore_1
    //   99: goto -68 -> 31
    //   102: astore_1
    //   103: aload 7
    //   105: invokevirtual 67	android/os/Parcel:recycle	()V
    //   108: aload 6
    //   110: invokevirtual 67	android/os/Parcel:recycle	()V
    //   113: aload_1
    //   114: athrow
    // Local variable table:
    //   start	length	slot	name	signature
    //   0	115	0	this	fwy
    //   0	115	1	paramfwt	fwt
    //   0	115	2	paramString	String
    //   0	115	3	paramBoolean	boolean
    //   0	115	4	paramArrayOfString	String[]
    //   1	52	5	i	int
    //   6	103	6	localParcel1	Parcel
    //   11	93	7	localParcel2	Parcel
    // Exception table:
    //   from	to	target	type
    //   13	20	102	finally
    //   24	31	102	finally
    //   31	43	102	finally
    //   50	86	102	finally
  }
  
  /* Error */
  public final void a(fwt paramfwt, boolean paramBoolean1, boolean paramBoolean2, String paramString1, String paramString2)
  {
    // Byte code:
    //   0: iconst_1
    //   1: istore 7
    //   3: invokestatic 23	android/os/Parcel:obtain	()Landroid/os/Parcel;
    //   6: astore 8
    //   8: invokestatic 23	android/os/Parcel:obtain	()Landroid/os/Parcel;
    //   11: astore 9
    //   13: aload 8
    //   15: ldc 25
    //   17: invokevirtual 29	android/os/Parcel:writeInterfaceToken	(Ljava/lang/String;)V
    //   20: aload_1
    //   21: ifnull +91 -> 112
    //   24: aload_1
    //   25: invokeinterface 74 1 0
    //   30: astore_1
    //   31: aload 8
    //   33: aload_1
    //   34: invokevirtual 77	android/os/Parcel:writeStrongBinder	(Landroid/os/IBinder;)V
    //   37: iload_2
    //   38: ifeq +79 -> 117
    //   41: iconst_1
    //   42: istore 6
    //   44: aload 8
    //   46: iload 6
    //   48: invokevirtual 33	android/os/Parcel:writeInt	(I)V
    //   51: iload_3
    //   52: ifeq +71 -> 123
    //   55: iload 7
    //   57: istore 6
    //   59: aload 8
    //   61: iload 6
    //   63: invokevirtual 33	android/os/Parcel:writeInt	(I)V
    //   66: aload 8
    //   68: aload 4
    //   70: invokevirtual 80	android/os/Parcel:writeString	(Ljava/lang/String;)V
    //   73: aload 8
    //   75: aload 5
    //   77: invokevirtual 80	android/os/Parcel:writeString	(Ljava/lang/String;)V
    //   80: aload_0
    //   81: getfield 15	fwy:a	Landroid/os/IBinder;
    //   84: iconst_2
    //   85: aload 8
    //   87: aload 9
    //   89: iconst_0
    //   90: invokeinterface 45 5 0
    //   95: pop
    //   96: aload 9
    //   98: invokevirtual 48	android/os/Parcel:readException	()V
    //   101: aload 9
    //   103: invokevirtual 67	android/os/Parcel:recycle	()V
    //   106: aload 8
    //   108: invokevirtual 67	android/os/Parcel:recycle	()V
    //   111: return
    //   112: aconst_null
    //   113: astore_1
    //   114: goto -83 -> 31
    //   117: iconst_0
    //   118: istore 6
    //   120: goto -76 -> 44
    //   123: iconst_0
    //   124: istore 6
    //   126: goto -67 -> 59
    //   129: astore_1
    //   130: aload 9
    //   132: invokevirtual 67	android/os/Parcel:recycle	()V
    //   135: aload 8
    //   137: invokevirtual 67	android/os/Parcel:recycle	()V
    //   140: aload_1
    //   141: athrow
    // Local variable table:
    //   start	length	slot	name	signature
    //   0	142	0	this	fwy
    //   0	142	1	paramfwt	fwt
    //   0	142	2	paramBoolean1	boolean
    //   0	142	3	paramBoolean2	boolean
    //   0	142	4	paramString1	String
    //   0	142	5	paramString2	String
    //   42	83	6	i	int
    //   1	55	7	j	int
    //   6	130	8	localParcel1	Parcel
    //   11	120	9	localParcel2	Parcel
    // Exception table:
    //   from	to	target	type
    //   13	20	129	finally
    //   24	31	129	finally
    //   31	37	129	finally
    //   44	51	129	finally
    //   59	101	129	finally
  }
  
  /* Error */
  public final void a(fwt paramfwt, boolean paramBoolean1, boolean paramBoolean2, String paramString1, String paramString2, int paramInt)
  {
    // Byte code:
    //   0: iconst_1
    //   1: istore 8
    //   3: invokestatic 23	android/os/Parcel:obtain	()Landroid/os/Parcel;
    //   6: astore 9
    //   8: invokestatic 23	android/os/Parcel:obtain	()Landroid/os/Parcel;
    //   11: astore 10
    //   13: aload 9
    //   15: ldc 25
    //   17: invokevirtual 29	android/os/Parcel:writeInterfaceToken	(Ljava/lang/String;)V
    //   20: aload_1
    //   21: ifnull +100 -> 121
    //   24: aload_1
    //   25: invokeinterface 74 1 0
    //   30: astore_1
    //   31: aload 9
    //   33: aload_1
    //   34: invokevirtual 77	android/os/Parcel:writeStrongBinder	(Landroid/os/IBinder;)V
    //   37: iload_2
    //   38: ifeq +88 -> 126
    //   41: iconst_1
    //   42: istore 7
    //   44: aload 9
    //   46: iload 7
    //   48: invokevirtual 33	android/os/Parcel:writeInt	(I)V
    //   51: iload_3
    //   52: ifeq +80 -> 132
    //   55: iload 8
    //   57: istore 7
    //   59: aload 9
    //   61: iload 7
    //   63: invokevirtual 33	android/os/Parcel:writeInt	(I)V
    //   66: aload 9
    //   68: aload 4
    //   70: invokevirtual 80	android/os/Parcel:writeString	(Ljava/lang/String;)V
    //   73: aload 9
    //   75: aload 5
    //   77: invokevirtual 80	android/os/Parcel:writeString	(Ljava/lang/String;)V
    //   80: aload 9
    //   82: iload 6
    //   84: invokevirtual 33	android/os/Parcel:writeInt	(I)V
    //   87: aload_0
    //   88: getfield 15	fwy:a	Landroid/os/IBinder;
    //   91: sipush 305
    //   94: aload 9
    //   96: aload 10
    //   98: iconst_0
    //   99: invokeinterface 45 5 0
    //   104: pop
    //   105: aload 10
    //   107: invokevirtual 48	android/os/Parcel:readException	()V
    //   110: aload 10
    //   112: invokevirtual 67	android/os/Parcel:recycle	()V
    //   115: aload 9
    //   117: invokevirtual 67	android/os/Parcel:recycle	()V
    //   120: return
    //   121: aconst_null
    //   122: astore_1
    //   123: goto -92 -> 31
    //   126: iconst_0
    //   127: istore 7
    //   129: goto -85 -> 44
    //   132: iconst_0
    //   133: istore 7
    //   135: goto -76 -> 59
    //   138: astore_1
    //   139: aload 10
    //   141: invokevirtual 67	android/os/Parcel:recycle	()V
    //   144: aload 9
    //   146: invokevirtual 67	android/os/Parcel:recycle	()V
    //   149: aload_1
    //   150: athrow
    // Local variable table:
    //   start	length	slot	name	signature
    //   0	151	0	this	fwy
    //   0	151	1	paramfwt	fwt
    //   0	151	2	paramBoolean1	boolean
    //   0	151	3	paramBoolean2	boolean
    //   0	151	4	paramString1	String
    //   0	151	5	paramString2	String
    //   0	151	6	paramInt	int
    //   42	92	7	i	int
    //   1	55	8	j	int
    //   6	139	9	localParcel1	Parcel
    //   11	129	10	localParcel2	Parcel
    // Exception table:
    //   from	to	target	type
    //   13	20	138	finally
    //   24	31	138	finally
    //   31	37	138	finally
    //   44	51	138	finally
    //   59	110	138	finally
  }
  
  public final void a(boolean paramBoolean)
  {
    int i = 0;
    Parcel localParcel1 = Parcel.obtain();
    Parcel localParcel2 = Parcel.obtain();
    try
    {
      localParcel1.writeInterfaceToken("com.google.android.gms.people.internal.IPeopleService");
      if (paramBoolean) {
        i = 1;
      }
      localParcel1.writeInt(i);
      a.transact(15, localParcel1, localParcel2, 0);
      localParcel2.readException();
      return;
    }
    finally
    {
      localParcel2.recycle();
      localParcel1.recycle();
    }
  }
  
  public final boolean a()
  {
    boolean bool = false;
    Parcel localParcel1 = Parcel.obtain();
    Parcel localParcel2 = Parcel.obtain();
    try
    {
      localParcel1.writeInterfaceToken("com.google.android.gms.people.internal.IPeopleService");
      a.transact(16, localParcel1, localParcel2, 0);
      localParcel2.readException();
      int i = localParcel2.readInt();
      if (i != 0) {
        bool = true;
      }
      return bool;
    }
    finally
    {
      localParcel2.recycle();
      localParcel1.recycle();
    }
  }
  
  public final IBinder asBinder()
  {
    return a;
  }
  
  /* Error */
  public final Bundle b(String paramString1, String paramString2)
  {
    // Byte code:
    //   0: invokestatic 23	android/os/Parcel:obtain	()Landroid/os/Parcel;
    //   3: astore_3
    //   4: invokestatic 23	android/os/Parcel:obtain	()Landroid/os/Parcel;
    //   7: astore 4
    //   9: aload_3
    //   10: ldc 25
    //   12: invokevirtual 29	android/os/Parcel:writeInterfaceToken	(Ljava/lang/String;)V
    //   15: aload_3
    //   16: aload_1
    //   17: invokevirtual 80	android/os/Parcel:writeString	(Ljava/lang/String;)V
    //   20: aload_3
    //   21: aload_2
    //   22: invokevirtual 80	android/os/Parcel:writeString	(Ljava/lang/String;)V
    //   25: aload_0
    //   26: getfield 15	fwy:a	Landroid/os/IBinder;
    //   29: bipush 17
    //   31: aload_3
    //   32: aload 4
    //   34: iconst_0
    //   35: invokeinterface 45 5 0
    //   40: pop
    //   41: aload 4
    //   43: invokevirtual 48	android/os/Parcel:readException	()V
    //   46: aload 4
    //   48: invokevirtual 52	android/os/Parcel:readInt	()I
    //   51: ifeq +28 -> 79
    //   54: getstatic 58	android/os/Bundle:CREATOR	Landroid/os/Parcelable$Creator;
    //   57: aload 4
    //   59: invokeinterface 64 2 0
    //   64: checkcast 54	android/os/Bundle
    //   67: astore_1
    //   68: aload 4
    //   70: invokevirtual 67	android/os/Parcel:recycle	()V
    //   73: aload_3
    //   74: invokevirtual 67	android/os/Parcel:recycle	()V
    //   77: aload_1
    //   78: areturn
    //   79: aconst_null
    //   80: astore_1
    //   81: goto -13 -> 68
    //   84: astore_1
    //   85: aload 4
    //   87: invokevirtual 67	android/os/Parcel:recycle	()V
    //   90: aload_3
    //   91: invokevirtual 67	android/os/Parcel:recycle	()V
    //   94: aload_1
    //   95: athrow
    // Local variable table:
    //   start	length	slot	name	signature
    //   0	96	0	this	fwy
    //   0	96	1	paramString1	String
    //   0	96	2	paramString2	String
    //   3	88	3	localParcel1	Parcel
    //   7	79	4	localParcel2	Parcel
    // Exception table:
    //   from	to	target	type
    //   9	68	84	finally
  }
  
  /* Error */
  public final enk b(fwt paramfwt, long paramLong, boolean paramBoolean)
  {
    // Byte code:
    //   0: iconst_0
    //   1: istore 5
    //   3: invokestatic 23	android/os/Parcel:obtain	()Landroid/os/Parcel;
    //   6: astore 6
    //   8: invokestatic 23	android/os/Parcel:obtain	()Landroid/os/Parcel;
    //   11: astore 7
    //   13: aload 6
    //   15: ldc 25
    //   17: invokevirtual 29	android/os/Parcel:writeInterfaceToken	(Ljava/lang/String;)V
    //   20: aload_1
    //   21: ifnull +81 -> 102
    //   24: aload_1
    //   25: invokeinterface 74 1 0
    //   30: astore_1
    //   31: aload 6
    //   33: aload_1
    //   34: invokevirtual 77	android/os/Parcel:writeStrongBinder	(Landroid/os/IBinder;)V
    //   37: aload 6
    //   39: lload_2
    //   40: invokevirtual 86	android/os/Parcel:writeLong	(J)V
    //   43: iload 4
    //   45: ifeq +6 -> 51
    //   48: iconst_1
    //   49: istore 5
    //   51: aload 6
    //   53: iload 5
    //   55: invokevirtual 33	android/os/Parcel:writeInt	(I)V
    //   58: aload_0
    //   59: getfield 15	fwy:a	Landroid/os/IBinder;
    //   62: sipush 503
    //   65: aload 6
    //   67: aload 7
    //   69: iconst_0
    //   70: invokeinterface 45 5 0
    //   75: pop
    //   76: aload 7
    //   78: invokevirtual 48	android/os/Parcel:readException	()V
    //   81: aload 7
    //   83: invokevirtual 95	android/os/Parcel:readStrongBinder	()Landroid/os/IBinder;
    //   86: invokestatic 100	enl:a	(Landroid/os/IBinder;)Lenk;
    //   89: astore_1
    //   90: aload 7
    //   92: invokevirtual 67	android/os/Parcel:recycle	()V
    //   95: aload 6
    //   97: invokevirtual 67	android/os/Parcel:recycle	()V
    //   100: aload_1
    //   101: areturn
    //   102: aconst_null
    //   103: astore_1
    //   104: goto -73 -> 31
    //   107: astore_1
    //   108: aload 7
    //   110: invokevirtual 67	android/os/Parcel:recycle	()V
    //   113: aload 6
    //   115: invokevirtual 67	android/os/Parcel:recycle	()V
    //   118: aload_1
    //   119: athrow
    // Local variable table:
    //   start	length	slot	name	signature
    //   0	120	0	this	fwy
    //   0	120	1	paramfwt	fwt
    //   0	120	2	paramLong	long
    //   0	120	4	paramBoolean	boolean
    //   1	53	5	i	int
    //   6	108	6	localParcel1	Parcel
    //   11	98	7	localParcel2	Parcel
    // Exception table:
    //   from	to	target	type
    //   13	20	107	finally
    //   24	31	107	finally
    //   31	43	107	finally
    //   51	90	107	finally
  }
  
  /* Error */
  public final enk b(fwt paramfwt, String paramString)
  {
    // Byte code:
    //   0: invokestatic 23	android/os/Parcel:obtain	()Landroid/os/Parcel;
    //   3: astore_3
    //   4: invokestatic 23	android/os/Parcel:obtain	()Landroid/os/Parcel;
    //   7: astore 4
    //   9: aload_3
    //   10: ldc 25
    //   12: invokevirtual 29	android/os/Parcel:writeInterfaceToken	(Ljava/lang/String;)V
    //   15: aload_1
    //   16: ifnull +62 -> 78
    //   19: aload_1
    //   20: invokeinterface 74 1 0
    //   25: astore_1
    //   26: aload_3
    //   27: aload_1
    //   28: invokevirtual 77	android/os/Parcel:writeStrongBinder	(Landroid/os/IBinder;)V
    //   31: aload_3
    //   32: aload_2
    //   33: invokevirtual 80	android/os/Parcel:writeString	(Ljava/lang/String;)V
    //   36: aload_0
    //   37: getfield 15	fwy:a	Landroid/os/IBinder;
    //   40: sipush 504
    //   43: aload_3
    //   44: aload 4
    //   46: iconst_0
    //   47: invokeinterface 45 5 0
    //   52: pop
    //   53: aload 4
    //   55: invokevirtual 48	android/os/Parcel:readException	()V
    //   58: aload 4
    //   60: invokevirtual 95	android/os/Parcel:readStrongBinder	()Landroid/os/IBinder;
    //   63: invokestatic 100	enl:a	(Landroid/os/IBinder;)Lenk;
    //   66: astore_1
    //   67: aload 4
    //   69: invokevirtual 67	android/os/Parcel:recycle	()V
    //   72: aload_3
    //   73: invokevirtual 67	android/os/Parcel:recycle	()V
    //   76: aload_1
    //   77: areturn
    //   78: aconst_null
    //   79: astore_1
    //   80: goto -54 -> 26
    //   83: astore_1
    //   84: aload 4
    //   86: invokevirtual 67	android/os/Parcel:recycle	()V
    //   89: aload_3
    //   90: invokevirtual 67	android/os/Parcel:recycle	()V
    //   93: aload_1
    //   94: athrow
    // Local variable table:
    //   start	length	slot	name	signature
    //   0	95	0	this	fwy
    //   0	95	1	paramfwt	fwt
    //   0	95	2	paramString	String
    //   3	87	3	localParcel1	Parcel
    //   7	78	4	localParcel2	Parcel
    // Exception table:
    //   from	to	target	type
    //   9	15	83	finally
    //   19	26	83	finally
    //   26	67	83	finally
  }
  
  /* Error */
  public final enk b(fwt paramfwt, String paramString, int paramInt1, int paramInt2)
  {
    // Byte code:
    //   0: invokestatic 23	android/os/Parcel:obtain	()Landroid/os/Parcel;
    //   3: astore 5
    //   5: invokestatic 23	android/os/Parcel:obtain	()Landroid/os/Parcel;
    //   8: astore 6
    //   10: aload 5
    //   12: ldc 25
    //   14: invokevirtual 29	android/os/Parcel:writeInterfaceToken	(Ljava/lang/String;)V
    //   17: aload_1
    //   18: ifnull +79 -> 97
    //   21: aload_1
    //   22: invokeinterface 74 1 0
    //   27: astore_1
    //   28: aload 5
    //   30: aload_1
    //   31: invokevirtual 77	android/os/Parcel:writeStrongBinder	(Landroid/os/IBinder;)V
    //   34: aload 5
    //   36: aload_2
    //   37: invokevirtual 80	android/os/Parcel:writeString	(Ljava/lang/String;)V
    //   40: aload 5
    //   42: iload_3
    //   43: invokevirtual 33	android/os/Parcel:writeInt	(I)V
    //   46: aload 5
    //   48: iload 4
    //   50: invokevirtual 33	android/os/Parcel:writeInt	(I)V
    //   53: aload_0
    //   54: getfield 15	fwy:a	Landroid/os/IBinder;
    //   57: sipush 502
    //   60: aload 5
    //   62: aload 6
    //   64: iconst_0
    //   65: invokeinterface 45 5 0
    //   70: pop
    //   71: aload 6
    //   73: invokevirtual 48	android/os/Parcel:readException	()V
    //   76: aload 6
    //   78: invokevirtual 95	android/os/Parcel:readStrongBinder	()Landroid/os/IBinder;
    //   81: invokestatic 100	enl:a	(Landroid/os/IBinder;)Lenk;
    //   84: astore_1
    //   85: aload 6
    //   87: invokevirtual 67	android/os/Parcel:recycle	()V
    //   90: aload 5
    //   92: invokevirtual 67	android/os/Parcel:recycle	()V
    //   95: aload_1
    //   96: areturn
    //   97: aconst_null
    //   98: astore_1
    //   99: goto -71 -> 28
    //   102: astore_1
    //   103: aload 6
    //   105: invokevirtual 67	android/os/Parcel:recycle	()V
    //   108: aload 5
    //   110: invokevirtual 67	android/os/Parcel:recycle	()V
    //   113: aload_1
    //   114: athrow
    // Local variable table:
    //   start	length	slot	name	signature
    //   0	115	0	this	fwy
    //   0	115	1	paramfwt	fwt
    //   0	115	2	paramString	String
    //   0	115	3	paramInt1	int
    //   0	115	4	paramInt2	int
    //   3	106	5	localParcel1	Parcel
    //   8	96	6	localParcel2	Parcel
    // Exception table:
    //   from	to	target	type
    //   10	17	102	finally
    //   21	28	102	finally
    //   28	85	102	finally
  }
  
  /* Error */
  public final enk b(fwt paramfwt, String paramString1, String paramString2, int paramInt1, int paramInt2)
  {
    // Byte code:
    //   0: invokestatic 23	android/os/Parcel:obtain	()Landroid/os/Parcel;
    //   3: astore 6
    //   5: invokestatic 23	android/os/Parcel:obtain	()Landroid/os/Parcel;
    //   8: astore 7
    //   10: aload 6
    //   12: ldc 25
    //   14: invokevirtual 29	android/os/Parcel:writeInterfaceToken	(Ljava/lang/String;)V
    //   17: aload_1
    //   18: ifnull +86 -> 104
    //   21: aload_1
    //   22: invokeinterface 74 1 0
    //   27: astore_1
    //   28: aload 6
    //   30: aload_1
    //   31: invokevirtual 77	android/os/Parcel:writeStrongBinder	(Landroid/os/IBinder;)V
    //   34: aload 6
    //   36: aload_2
    //   37: invokevirtual 80	android/os/Parcel:writeString	(Ljava/lang/String;)V
    //   40: aload 6
    //   42: aload_3
    //   43: invokevirtual 80	android/os/Parcel:writeString	(Ljava/lang/String;)V
    //   46: aload 6
    //   48: iload 4
    //   50: invokevirtual 33	android/os/Parcel:writeInt	(I)V
    //   53: aload 6
    //   55: iload 5
    //   57: invokevirtual 33	android/os/Parcel:writeInt	(I)V
    //   60: aload_0
    //   61: getfield 15	fwy:a	Landroid/os/IBinder;
    //   64: sipush 505
    //   67: aload 6
    //   69: aload 7
    //   71: iconst_0
    //   72: invokeinterface 45 5 0
    //   77: pop
    //   78: aload 7
    //   80: invokevirtual 48	android/os/Parcel:readException	()V
    //   83: aload 7
    //   85: invokevirtual 95	android/os/Parcel:readStrongBinder	()Landroid/os/IBinder;
    //   88: invokestatic 100	enl:a	(Landroid/os/IBinder;)Lenk;
    //   91: astore_1
    //   92: aload 7
    //   94: invokevirtual 67	android/os/Parcel:recycle	()V
    //   97: aload 6
    //   99: invokevirtual 67	android/os/Parcel:recycle	()V
    //   102: aload_1
    //   103: areturn
    //   104: aconst_null
    //   105: astore_1
    //   106: goto -78 -> 28
    //   109: astore_1
    //   110: aload 7
    //   112: invokevirtual 67	android/os/Parcel:recycle	()V
    //   115: aload 6
    //   117: invokevirtual 67	android/os/Parcel:recycle	()V
    //   120: aload_1
    //   121: athrow
    // Local variable table:
    //   start	length	slot	name	signature
    //   0	122	0	this	fwy
    //   0	122	1	paramfwt	fwt
    //   0	122	2	paramString1	String
    //   0	122	3	paramString2	String
    //   0	122	4	paramInt1	int
    //   0	122	5	paramInt2	int
    //   3	113	6	localParcel1	Parcel
    //   8	103	7	localParcel2	Parcel
    // Exception table:
    //   from	to	target	type
    //   10	17	109	finally
    //   21	28	109	finally
    //   28	92	109	finally
  }
  
  /* Error */
  public final void b(fwt paramfwt, Bundle paramBundle)
  {
    // Byte code:
    //   0: invokestatic 23	android/os/Parcel:obtain	()Landroid/os/Parcel;
    //   3: astore_3
    //   4: invokestatic 23	android/os/Parcel:obtain	()Landroid/os/Parcel;
    //   7: astore 4
    //   9: aload_3
    //   10: ldc 25
    //   12: invokevirtual 29	android/os/Parcel:writeInterfaceToken	(Ljava/lang/String;)V
    //   15: aload_1
    //   16: ifnull +62 -> 78
    //   19: aload_1
    //   20: invokeinterface 74 1 0
    //   25: astore_1
    //   26: aload_3
    //   27: aload_1
    //   28: invokevirtual 77	android/os/Parcel:writeStrongBinder	(Landroid/os/IBinder;)V
    //   31: aload_2
    //   32: ifnull +51 -> 83
    //   35: aload_3
    //   36: iconst_1
    //   37: invokevirtual 33	android/os/Parcel:writeInt	(I)V
    //   40: aload_2
    //   41: aload_3
    //   42: iconst_0
    //   43: invokevirtual 119	android/os/Bundle:writeToParcel	(Landroid/os/Parcel;I)V
    //   46: aload_0
    //   47: getfield 15	fwy:a	Landroid/os/IBinder;
    //   50: sipush 304
    //   53: aload_3
    //   54: aload 4
    //   56: iconst_0
    //   57: invokeinterface 45 5 0
    //   62: pop
    //   63: aload 4
    //   65: invokevirtual 48	android/os/Parcel:readException	()V
    //   68: aload 4
    //   70: invokevirtual 67	android/os/Parcel:recycle	()V
    //   73: aload_3
    //   74: invokevirtual 67	android/os/Parcel:recycle	()V
    //   77: return
    //   78: aconst_null
    //   79: astore_1
    //   80: goto -54 -> 26
    //   83: aload_3
    //   84: iconst_0
    //   85: invokevirtual 33	android/os/Parcel:writeInt	(I)V
    //   88: goto -42 -> 46
    //   91: astore_1
    //   92: aload 4
    //   94: invokevirtual 67	android/os/Parcel:recycle	()V
    //   97: aload_3
    //   98: invokevirtual 67	android/os/Parcel:recycle	()V
    //   101: aload_1
    //   102: athrow
    // Local variable table:
    //   start	length	slot	name	signature
    //   0	103	0	this	fwy
    //   0	103	1	paramfwt	fwt
    //   0	103	2	paramBundle	Bundle
    //   3	95	3	localParcel1	Parcel
    //   7	86	4	localParcel2	Parcel
    // Exception table:
    //   from	to	target	type
    //   9	15	91	finally
    //   19	26	91	finally
    //   26	31	91	finally
    //   35	46	91	finally
    //   46	68	91	finally
    //   83	88	91	finally
  }
  
  /* Error */
  public final void b(fwt paramfwt, String paramString1, String paramString2)
  {
    // Byte code:
    //   0: invokestatic 23	android/os/Parcel:obtain	()Landroid/os/Parcel;
    //   3: astore 4
    //   5: invokestatic 23	android/os/Parcel:obtain	()Landroid/os/Parcel;
    //   8: astore 5
    //   10: aload 4
    //   12: ldc 25
    //   14: invokevirtual 29	android/os/Parcel:writeInterfaceToken	(Ljava/lang/String;)V
    //   17: aload_1
    //   18: ifnull +61 -> 79
    //   21: aload_1
    //   22: invokeinterface 74 1 0
    //   27: astore_1
    //   28: aload 4
    //   30: aload_1
    //   31: invokevirtual 77	android/os/Parcel:writeStrongBinder	(Landroid/os/IBinder;)V
    //   34: aload 4
    //   36: aload_2
    //   37: invokevirtual 80	android/os/Parcel:writeString	(Ljava/lang/String;)V
    //   40: aload 4
    //   42: aload_3
    //   43: invokevirtual 80	android/os/Parcel:writeString	(Ljava/lang/String;)V
    //   46: aload_0
    //   47: getfield 15	fwy:a	Landroid/os/IBinder;
    //   50: bipush 101
    //   52: aload 4
    //   54: aload 5
    //   56: iconst_0
    //   57: invokeinterface 45 5 0
    //   62: pop
    //   63: aload 5
    //   65: invokevirtual 48	android/os/Parcel:readException	()V
    //   68: aload 5
    //   70: invokevirtual 67	android/os/Parcel:recycle	()V
    //   73: aload 4
    //   75: invokevirtual 67	android/os/Parcel:recycle	()V
    //   78: return
    //   79: aconst_null
    //   80: astore_1
    //   81: goto -53 -> 28
    //   84: astore_1
    //   85: aload 5
    //   87: invokevirtual 67	android/os/Parcel:recycle	()V
    //   90: aload 4
    //   92: invokevirtual 67	android/os/Parcel:recycle	()V
    //   95: aload_1
    //   96: athrow
    // Local variable table:
    //   start	length	slot	name	signature
    //   0	97	0	this	fwy
    //   0	97	1	paramfwt	fwt
    //   0	97	2	paramString1	String
    //   0	97	3	paramString2	String
    //   3	88	4	localParcel1	Parcel
    //   8	78	5	localParcel2	Parcel
    // Exception table:
    //   from	to	target	type
    //   10	17	84	finally
    //   21	28	84	finally
    //   28	68	84	finally
  }
  
  /* Error */
  public final void b(fwt paramfwt, String paramString1, String paramString2, int paramInt)
  {
    // Byte code:
    //   0: invokestatic 23	android/os/Parcel:obtain	()Landroid/os/Parcel;
    //   3: astore 5
    //   5: invokestatic 23	android/os/Parcel:obtain	()Landroid/os/Parcel;
    //   8: astore 6
    //   10: aload 5
    //   12: ldc 25
    //   14: invokevirtual 29	android/os/Parcel:writeInterfaceToken	(Ljava/lang/String;)V
    //   17: aload_1
    //   18: ifnull +69 -> 87
    //   21: aload_1
    //   22: invokeinterface 74 1 0
    //   27: astore_1
    //   28: aload 5
    //   30: aload_1
    //   31: invokevirtual 77	android/os/Parcel:writeStrongBinder	(Landroid/os/IBinder;)V
    //   34: aload 5
    //   36: aload_2
    //   37: invokevirtual 80	android/os/Parcel:writeString	(Ljava/lang/String;)V
    //   40: aload 5
    //   42: aload_3
    //   43: invokevirtual 80	android/os/Parcel:writeString	(Ljava/lang/String;)V
    //   46: aload 5
    //   48: iload 4
    //   50: invokevirtual 33	android/os/Parcel:writeInt	(I)V
    //   53: aload_0
    //   54: getfield 15	fwy:a	Landroid/os/IBinder;
    //   57: sipush 301
    //   60: aload 5
    //   62: aload 6
    //   64: iconst_0
    //   65: invokeinterface 45 5 0
    //   70: pop
    //   71: aload 6
    //   73: invokevirtual 48	android/os/Parcel:readException	()V
    //   76: aload 6
    //   78: invokevirtual 67	android/os/Parcel:recycle	()V
    //   81: aload 5
    //   83: invokevirtual 67	android/os/Parcel:recycle	()V
    //   86: return
    //   87: aconst_null
    //   88: astore_1
    //   89: goto -61 -> 28
    //   92: astore_1
    //   93: aload 6
    //   95: invokevirtual 67	android/os/Parcel:recycle	()V
    //   98: aload 5
    //   100: invokevirtual 67	android/os/Parcel:recycle	()V
    //   103: aload_1
    //   104: athrow
    // Local variable table:
    //   start	length	slot	name	signature
    //   0	105	0	this	fwy
    //   0	105	1	paramfwt	fwt
    //   0	105	2	paramString1	String
    //   0	105	3	paramString2	String
    //   0	105	4	paramInt	int
    //   3	96	5	localParcel1	Parcel
    //   8	86	6	localParcel2	Parcel
    // Exception table:
    //   from	to	target	type
    //   10	17	92	finally
    //   21	28	92	finally
    //   28	76	92	finally
  }
  
  /* Error */
  public final void b(fwt paramfwt, String paramString1, String paramString2, String paramString3, int paramInt, String paramString4)
  {
    // Byte code:
    //   0: invokestatic 23	android/os/Parcel:obtain	()Landroid/os/Parcel;
    //   3: astore 7
    //   5: invokestatic 23	android/os/Parcel:obtain	()Landroid/os/Parcel;
    //   8: astore 8
    //   10: aload 7
    //   12: ldc 25
    //   14: invokevirtual 29	android/os/Parcel:writeInterfaceToken	(Ljava/lang/String;)V
    //   17: aload_1
    //   18: ifnull +82 -> 100
    //   21: aload_1
    //   22: invokeinterface 74 1 0
    //   27: astore_1
    //   28: aload 7
    //   30: aload_1
    //   31: invokevirtual 77	android/os/Parcel:writeStrongBinder	(Landroid/os/IBinder;)V
    //   34: aload 7
    //   36: aload_2
    //   37: invokevirtual 80	android/os/Parcel:writeString	(Ljava/lang/String;)V
    //   40: aload 7
    //   42: aload_3
    //   43: invokevirtual 80	android/os/Parcel:writeString	(Ljava/lang/String;)V
    //   46: aload 7
    //   48: aload 4
    //   50: invokevirtual 80	android/os/Parcel:writeString	(Ljava/lang/String;)V
    //   53: aload 7
    //   55: iload 5
    //   57: invokevirtual 33	android/os/Parcel:writeInt	(I)V
    //   60: aload 7
    //   62: aload 6
    //   64: invokevirtual 80	android/os/Parcel:writeString	(Ljava/lang/String;)V
    //   67: aload_0
    //   68: getfield 15	fwy:a	Landroid/os/IBinder;
    //   71: bipush 22
    //   73: aload 7
    //   75: aload 8
    //   77: iconst_0
    //   78: invokeinterface 45 5 0
    //   83: pop
    //   84: aload 8
    //   86: invokevirtual 48	android/os/Parcel:readException	()V
    //   89: aload 8
    //   91: invokevirtual 67	android/os/Parcel:recycle	()V
    //   94: aload 7
    //   96: invokevirtual 67	android/os/Parcel:recycle	()V
    //   99: return
    //   100: aconst_null
    //   101: astore_1
    //   102: goto -74 -> 28
    //   105: astore_1
    //   106: aload 8
    //   108: invokevirtual 67	android/os/Parcel:recycle	()V
    //   111: aload 7
    //   113: invokevirtual 67	android/os/Parcel:recycle	()V
    //   116: aload_1
    //   117: athrow
    // Local variable table:
    //   start	length	slot	name	signature
    //   0	118	0	this	fwy
    //   0	118	1	paramfwt	fwt
    //   0	118	2	paramString1	String
    //   0	118	3	paramString2	String
    //   0	118	4	paramString3	String
    //   0	118	5	paramInt	int
    //   0	118	6	paramString4	String
    //   3	109	7	localParcel1	Parcel
    //   8	99	8	localParcel2	Parcel
    // Exception table:
    //   from	to	target	type
    //   10	17	105	finally
    //   21	28	105	finally
    //   28	89	105	finally
  }
  
  /* Error */
  public final void b(fwt paramfwt, String paramString1, String paramString2, String paramString3, boolean paramBoolean)
  {
    // Byte code:
    //   0: iconst_0
    //   1: istore 6
    //   3: invokestatic 23	android/os/Parcel:obtain	()Landroid/os/Parcel;
    //   6: astore 7
    //   8: invokestatic 23	android/os/Parcel:obtain	()Landroid/os/Parcel;
    //   11: astore 8
    //   13: aload 7
    //   15: ldc 25
    //   17: invokevirtual 29	android/os/Parcel:writeInterfaceToken	(Ljava/lang/String;)V
    //   20: aload_1
    //   21: ifnull +84 -> 105
    //   24: aload_1
    //   25: invokeinterface 74 1 0
    //   30: astore_1
    //   31: aload 7
    //   33: aload_1
    //   34: invokevirtual 77	android/os/Parcel:writeStrongBinder	(Landroid/os/IBinder;)V
    //   37: aload 7
    //   39: aload_2
    //   40: invokevirtual 80	android/os/Parcel:writeString	(Ljava/lang/String;)V
    //   43: aload 7
    //   45: aload_3
    //   46: invokevirtual 80	android/os/Parcel:writeString	(Ljava/lang/String;)V
    //   49: aload 7
    //   51: aload 4
    //   53: invokevirtual 80	android/os/Parcel:writeString	(Ljava/lang/String;)V
    //   56: iload 5
    //   58: ifeq +6 -> 64
    //   61: iconst_1
    //   62: istore 6
    //   64: aload 7
    //   66: iload 6
    //   68: invokevirtual 33	android/os/Parcel:writeInt	(I)V
    //   71: aload_0
    //   72: getfield 15	fwy:a	Landroid/os/IBinder;
    //   75: sipush 603
    //   78: aload 7
    //   80: aload 8
    //   82: iconst_0
    //   83: invokeinterface 45 5 0
    //   88: pop
    //   89: aload 8
    //   91: invokevirtual 48	android/os/Parcel:readException	()V
    //   94: aload 8
    //   96: invokevirtual 67	android/os/Parcel:recycle	()V
    //   99: aload 7
    //   101: invokevirtual 67	android/os/Parcel:recycle	()V
    //   104: return
    //   105: aconst_null
    //   106: astore_1
    //   107: goto -76 -> 31
    //   110: astore_1
    //   111: aload 8
    //   113: invokevirtual 67	android/os/Parcel:recycle	()V
    //   116: aload 7
    //   118: invokevirtual 67	android/os/Parcel:recycle	()V
    //   121: aload_1
    //   122: athrow
    // Local variable table:
    //   start	length	slot	name	signature
    //   0	123	0	this	fwy
    //   0	123	1	paramfwt	fwt
    //   0	123	2	paramString1	String
    //   0	123	3	paramString2	String
    //   0	123	4	paramString3	String
    //   0	123	5	paramBoolean	boolean
    //   1	66	6	i	int
    //   6	111	7	localParcel1	Parcel
    //   11	101	8	localParcel2	Parcel
    // Exception table:
    //   from	to	target	type
    //   13	20	110	finally
    //   24	31	110	finally
    //   31	56	110	finally
    //   64	94	110	finally
  }
  
  /* Error */
  public final enk c(fwt paramfwt, String paramString1, String paramString2, int paramInt)
  {
    // Byte code:
    //   0: invokestatic 23	android/os/Parcel:obtain	()Landroid/os/Parcel;
    //   3: astore 5
    //   5: invokestatic 23	android/os/Parcel:obtain	()Landroid/os/Parcel;
    //   8: astore 6
    //   10: aload 5
    //   12: ldc 25
    //   14: invokevirtual 29	android/os/Parcel:writeInterfaceToken	(Ljava/lang/String;)V
    //   17: aload_1
    //   18: ifnull +79 -> 97
    //   21: aload_1
    //   22: invokeinterface 74 1 0
    //   27: astore_1
    //   28: aload 5
    //   30: aload_1
    //   31: invokevirtual 77	android/os/Parcel:writeStrongBinder	(Landroid/os/IBinder;)V
    //   34: aload 5
    //   36: aload_2
    //   37: invokevirtual 80	android/os/Parcel:writeString	(Ljava/lang/String;)V
    //   40: aload 5
    //   42: aload_3
    //   43: invokevirtual 80	android/os/Parcel:writeString	(Ljava/lang/String;)V
    //   46: aload 5
    //   48: iload 4
    //   50: invokevirtual 33	android/os/Parcel:writeInt	(I)V
    //   53: aload_0
    //   54: getfield 15	fwy:a	Landroid/os/IBinder;
    //   57: sipush 506
    //   60: aload 5
    //   62: aload 6
    //   64: iconst_0
    //   65: invokeinterface 45 5 0
    //   70: pop
    //   71: aload 6
    //   73: invokevirtual 48	android/os/Parcel:readException	()V
    //   76: aload 6
    //   78: invokevirtual 95	android/os/Parcel:readStrongBinder	()Landroid/os/IBinder;
    //   81: invokestatic 100	enl:a	(Landroid/os/IBinder;)Lenk;
    //   84: astore_1
    //   85: aload 6
    //   87: invokevirtual 67	android/os/Parcel:recycle	()V
    //   90: aload 5
    //   92: invokevirtual 67	android/os/Parcel:recycle	()V
    //   95: aload_1
    //   96: areturn
    //   97: aconst_null
    //   98: astore_1
    //   99: goto -71 -> 28
    //   102: astore_1
    //   103: aload 6
    //   105: invokevirtual 67	android/os/Parcel:recycle	()V
    //   108: aload 5
    //   110: invokevirtual 67	android/os/Parcel:recycle	()V
    //   113: aload_1
    //   114: athrow
    // Local variable table:
    //   start	length	slot	name	signature
    //   0	115	0	this	fwy
    //   0	115	1	paramfwt	fwt
    //   0	115	2	paramString1	String
    //   0	115	3	paramString2	String
    //   0	115	4	paramInt	int
    //   3	106	5	localParcel1	Parcel
    //   8	96	6	localParcel2	Parcel
    // Exception table:
    //   from	to	target	type
    //   10	17	102	finally
    //   21	28	102	finally
    //   28	85	102	finally
  }
  
  /* Error */
  public final void c(fwt paramfwt, String paramString1, String paramString2)
  {
    // Byte code:
    //   0: invokestatic 23	android/os/Parcel:obtain	()Landroid/os/Parcel;
    //   3: astore 4
    //   5: invokestatic 23	android/os/Parcel:obtain	()Landroid/os/Parcel;
    //   8: astore 5
    //   10: aload 4
    //   12: ldc 25
    //   14: invokevirtual 29	android/os/Parcel:writeInterfaceToken	(Ljava/lang/String;)V
    //   17: aload_1
    //   18: ifnull +61 -> 79
    //   21: aload_1
    //   22: invokeinterface 74 1 0
    //   27: astore_1
    //   28: aload 4
    //   30: aload_1
    //   31: invokevirtual 77	android/os/Parcel:writeStrongBinder	(Landroid/os/IBinder;)V
    //   34: aload 4
    //   36: aload_2
    //   37: invokevirtual 80	android/os/Parcel:writeString	(Ljava/lang/String;)V
    //   40: aload 4
    //   42: aload_3
    //   43: invokevirtual 80	android/os/Parcel:writeString	(Ljava/lang/String;)V
    //   46: aload_0
    //   47: getfield 15	fwy:a	Landroid/os/IBinder;
    //   50: bipush 102
    //   52: aload 4
    //   54: aload 5
    //   56: iconst_0
    //   57: invokeinterface 45 5 0
    //   62: pop
    //   63: aload 5
    //   65: invokevirtual 48	android/os/Parcel:readException	()V
    //   68: aload 5
    //   70: invokevirtual 67	android/os/Parcel:recycle	()V
    //   73: aload 4
    //   75: invokevirtual 67	android/os/Parcel:recycle	()V
    //   78: return
    //   79: aconst_null
    //   80: astore_1
    //   81: goto -53 -> 28
    //   84: astore_1
    //   85: aload 5
    //   87: invokevirtual 67	android/os/Parcel:recycle	()V
    //   90: aload 4
    //   92: invokevirtual 67	android/os/Parcel:recycle	()V
    //   95: aload_1
    //   96: athrow
    // Local variable table:
    //   start	length	slot	name	signature
    //   0	97	0	this	fwy
    //   0	97	1	paramfwt	fwt
    //   0	97	2	paramString1	String
    //   0	97	3	paramString2	String
    //   3	88	4	localParcel1	Parcel
    //   8	78	5	localParcel2	Parcel
    // Exception table:
    //   from	to	target	type
    //   10	17	84	finally
    //   21	28	84	finally
    //   28	68	84	finally
  }
}

/* Location:
 * Qualified Name:     fwy
 * Java Class Version: 6 (50.0)
 * JD-Core Version:    0.7.1
 */