public class gqp
  extends grw
{
  private static final long serialVersionUID = 409811126989994864L;
  public final transient gqn a;
  
  private gqp(grx paramgrx, gqn paramgqn)
  {
    super(paramgrx);
    a = paramgqn;
  }
  
  /* Error */
  public static gqp a(gsu paramgsu, grv paramgrv)
  {
    // Byte code:
    //   0: aconst_null
    //   1: astore_3
    //   2: aconst_null
    //   3: astore_2
    //   4: aconst_null
    //   5: astore 5
    //   7: new 23	grx
    //   10: dup
    //   11: aload_1
    //   12: getfield 29	grv:c	I
    //   15: aload_1
    //   16: getfield 33	grv:d	Ljava/lang/String;
    //   19: aload_1
    //   20: getfield 37	grv:e	Lgrs;
    //   23: getfield 42	grs:c	Lgrn;
    //   26: invokespecial 45	grx:<init>	(ILjava/lang/String;Lgrn;)V
    //   29: astore 6
    //   31: aload_0
    //   32: invokestatic 50	hbe:a	(Ljava/lang/Object;)Ljava/lang/Object;
    //   35: pop
    //   36: aload_1
    //   37: getfield 29	grv:c	I
    //   40: invokestatic 55	grz:a	(I)Z
    //   43: ifne +279 -> 322
    //   46: ldc 57
    //   48: aload_1
    //   49: getfield 59	grv:a	Ljava/lang/String;
    //   52: invokestatic 65	grr:b	(Ljava/lang/String;Ljava/lang/String;)Z
    //   55: ifeq +267 -> 322
    //   58: aload_1
    //   59: invokevirtual 68	grv:a	()Ljava/io/InputStream;
    //   62: astore 4
    //   64: aload 4
    //   66: ifnull +256 -> 322
    //   69: aload_0
    //   70: aload_1
    //   71: invokevirtual 68	grv:a	()Ljava/io/InputStream;
    //   74: invokevirtual 73	gsu:a	(Ljava/io/InputStream;)Lgsy;
    //   77: astore_3
    //   78: aload_3
    //   79: invokevirtual 78	gsy:c	()Lgtd;
    //   82: astore_2
    //   83: aload_2
    //   84: astore_0
    //   85: aload_2
    //   86: ifnonnull +8 -> 94
    //   89: aload_3
    //   90: invokevirtual 81	gsy:n	()Lgtd;
    //   93: astore_0
    //   94: aload_0
    //   95: ifnull +289 -> 384
    //   98: aload_3
    //   99: ldc 83
    //   101: invokestatic 89	java/util/Collections:singleton	(Ljava/lang/Object;)Ljava/util/Set;
    //   104: invokevirtual 92	gsy:a	(Ljava/util/Set;)Ljava/lang/String;
    //   107: pop
    //   108: aload_3
    //   109: invokevirtual 78	gsy:c	()Lgtd;
    //   112: getstatic 97	gtd:d	Lgtd;
    //   115: if_acmpeq +269 -> 384
    //   118: aload_3
    //   119: ldc 99
    //   121: invokevirtual 102	gsy:a	(Ljava/lang/Class;)Ljava/lang/Object;
    //   124: checkcast 99	gqn
    //   127: astore_0
    //   128: aload_0
    //   129: astore 4
    //   131: aload_3
    //   132: astore_2
    //   133: aload_0
    //   134: invokevirtual 105	gqn:c	()Ljava/lang/String;
    //   137: astore 5
    //   139: aload 5
    //   141: astore 4
    //   143: aload_0
    //   144: astore 5
    //   146: aload_3
    //   147: ifnonnull +63 -> 210
    //   150: aload_1
    //   151: invokevirtual 108	grv:b	()V
    //   154: aload 5
    //   156: astore_2
    //   157: aload 4
    //   159: astore_0
    //   160: aload_1
    //   161: invokestatic 111	grw:a	(Lgrv;)Ljava/lang/StringBuilder;
    //   164: astore_1
    //   165: aload_0
    //   166: invokestatic 116	hbw:b	(Ljava/lang/String;)Z
    //   169: ifne +21 -> 190
    //   172: aload_1
    //   173: getstatic 119	gur:a	Ljava/lang/String;
    //   176: invokevirtual 125	java/lang/StringBuilder:append	(Ljava/lang/String;)Ljava/lang/StringBuilder;
    //   179: aload_0
    //   180: invokevirtual 125	java/lang/StringBuilder:append	(Ljava/lang/String;)Ljava/lang/StringBuilder;
    //   183: pop
    //   184: aload 6
    //   186: aload_0
    //   187: putfield 126	grx:d	Ljava/lang/String;
    //   190: aload 6
    //   192: aload_1
    //   193: invokevirtual 129	java/lang/StringBuilder:toString	()Ljava/lang/String;
    //   196: putfield 131	grx:e	Ljava/lang/String;
    //   199: new 2	gqp
    //   202: dup
    //   203: aload 6
    //   205: aload_2
    //   206: invokespecial 133	gqp:<init>	(Lgrx;Lgqn;)V
    //   209: areturn
    //   210: aload 4
    //   212: astore_0
    //   213: aload 5
    //   215: astore_2
    //   216: aload 5
    //   218: ifnonnull -58 -> 160
    //   221: aload_3
    //   222: invokevirtual 135	gsy:a	()V
    //   225: aload 4
    //   227: astore_0
    //   228: aload 5
    //   230: astore_2
    //   231: goto -71 -> 160
    //   234: astore_3
    //   235: aload 5
    //   237: astore_2
    //   238: aload 4
    //   240: astore_0
    //   241: aload_3
    //   242: invokevirtual 138	java/io/IOException:printStackTrace	()V
    //   245: goto -85 -> 160
    //   248: astore 5
    //   250: aconst_null
    //   251: astore_3
    //   252: aconst_null
    //   253: astore_0
    //   254: aload_0
    //   255: astore 4
    //   257: aload_3
    //   258: astore_2
    //   259: aload 5
    //   261: invokevirtual 138	java/io/IOException:printStackTrace	()V
    //   264: aload_3
    //   265: ifnonnull +14 -> 279
    //   268: aload_1
    //   269: invokevirtual 108	grv:b	()V
    //   272: aload_0
    //   273: astore_2
    //   274: aconst_null
    //   275: astore_0
    //   276: goto -116 -> 160
    //   279: aload_0
    //   280: ifnonnull +97 -> 377
    //   283: aload_3
    //   284: invokevirtual 135	gsy:a	()V
    //   287: aload_0
    //   288: astore_2
    //   289: aconst_null
    //   290: astore_0
    //   291: goto -131 -> 160
    //   294: astore 4
    //   296: aconst_null
    //   297: astore_2
    //   298: aconst_null
    //   299: astore_0
    //   300: aload_2
    //   301: ifnonnull +10 -> 311
    //   304: aload_1
    //   305: invokevirtual 108	grv:b	()V
    //   308: aload 4
    //   310: athrow
    //   311: aload_0
    //   312: ifnonnull -4 -> 308
    //   315: aload_2
    //   316: invokevirtual 135	gsy:a	()V
    //   319: goto -11 -> 308
    //   322: aload_1
    //   323: invokevirtual 140	grv:d	()Ljava/lang/String;
    //   326: astore_0
    //   327: aload_3
    //   328: astore_2
    //   329: goto -169 -> 160
    //   332: astore_3
    //   333: aconst_null
    //   334: astore_0
    //   335: goto -94 -> 241
    //   338: astore_3
    //   339: aload_0
    //   340: astore_2
    //   341: aconst_null
    //   342: astore_0
    //   343: goto -102 -> 241
    //   346: astore 4
    //   348: aconst_null
    //   349: astore_0
    //   350: aload_3
    //   351: astore_2
    //   352: goto -52 -> 300
    //   355: astore_3
    //   356: aload 4
    //   358: astore_0
    //   359: aload_3
    //   360: astore 4
    //   362: goto -62 -> 300
    //   365: astore 5
    //   367: aconst_null
    //   368: astore_0
    //   369: goto -115 -> 254
    //   372: astore 5
    //   374: goto -120 -> 254
    //   377: aload_0
    //   378: astore_2
    //   379: aconst_null
    //   380: astore_0
    //   381: goto -221 -> 160
    //   384: aconst_null
    //   385: astore 4
    //   387: goto -241 -> 146
    //   390: astore_3
    //   391: aconst_null
    //   392: astore 4
    //   394: aload_0
    //   395: astore_2
    //   396: aload 4
    //   398: astore_0
    //   399: goto -158 -> 241
    // Local variable table:
    //   start	length	slot	name	signature
    //   0	402	0	paramgsu	gsu
    //   0	402	1	paramgrv	grv
    //   3	393	2	localObject1	Object
    //   1	221	3	localgsy	gsy
    //   234	8	3	localIOException1	java.io.IOException
    //   251	77	3	localObject2	Object
    //   332	1	3	localIOException2	java.io.IOException
    //   338	13	3	localIOException3	java.io.IOException
    //   355	5	3	localObject3	Object
    //   390	1	3	localIOException4	java.io.IOException
    //   62	194	4	localObject4	Object
    //   294	15	4	localObject5	Object
    //   346	11	4	localObject6	Object
    //   360	37	4	localObject7	Object
    //   5	231	5	localObject8	Object
    //   248	12	5	localIOException5	java.io.IOException
    //   365	1	5	localIOException6	java.io.IOException
    //   372	1	5	localIOException7	java.io.IOException
    //   29	175	6	localgrx	grx
    // Exception table:
    //   from	to	target	type
    //   150	154	234	java/io/IOException
    //   221	225	234	java/io/IOException
    //   69	78	248	java/io/IOException
    //   69	78	294	finally
    //   36	64	332	java/io/IOException
    //   322	327	332	java/io/IOException
    //   268	272	338	java/io/IOException
    //   283	287	338	java/io/IOException
    //   78	83	346	finally
    //   89	94	346	finally
    //   98	128	346	finally
    //   133	139	355	finally
    //   259	264	355	finally
    //   78	83	365	java/io/IOException
    //   89	94	365	java/io/IOException
    //   98	128	365	java/io/IOException
    //   133	139	372	java/io/IOException
    //   304	308	390	java/io/IOException
    //   308	311	390	java/io/IOException
    //   315	319	390	java/io/IOException
  }
}

/* Location:
 * Qualified Name:     gqp
 * Java Class Version: 6 (50.0)
 * JD-Core Version:    0.7.1
 */