public final class grs
{
  public grm a;
  public grn b = new grn();
  public grn c = new grn();
  public int d = 10;
  int e = 16384;
  boolean f = true;
  public grj g;
  public final gsa h;
  public String i;
  public gri j;
  public gsb k;
  public grq l;
  public gry m;
  public gum n;
  public grk o;
  public boolean p = true;
  private boolean q = true;
  private int r = 20000;
  private int s = 20000;
  @Deprecated
  private grd t;
  private boolean u = true;
  @Deprecated
  private boolean v = false;
  private boolean w;
  private guo x = guo.a;
  
  grs(gsa paramgsa)
  {
    h = paramgsa;
    a(null);
  }
  
  public final grs a(int paramInt)
  {
    if (paramInt >= 0) {}
    for (boolean bool = true;; bool = false)
    {
      hbe.a(bool);
      r = paramInt;
      return this;
    }
  }
  
  public final grs a(gri paramgri)
  {
    j = ((gri)hbe.a(paramgri));
    return this;
  }
  
  public final grs a(String paramString)
  {
    if ((paramString == null) || (grr.b(paramString))) {}
    for (boolean bool = true;; bool = false)
    {
      hbe.a(bool);
      i = paramString;
      return this;
    }
  }
  
  /* Error */
  public final grv a()
  {
    // Byte code:
    //   0: aload_0
    //   1: getfield 58	grs:d	I
    //   4: iflt +1036 -> 1040
    //   7: iconst_1
    //   8: istore 4
    //   10: iload 4
    //   12: invokestatic 92	hbe:a	(Z)V
    //   15: aload_0
    //   16: getfield 58	grs:d	I
    //   19: istore_1
    //   20: aconst_null
    //   21: astore 9
    //   23: aload_0
    //   24: getfield 107	grs:i	Ljava/lang/String;
    //   27: invokestatic 96	hbe:a	(Ljava/lang/Object;)Ljava/lang/Object;
    //   30: pop
    //   31: aload_0
    //   32: getfield 100	grs:j	Lgri;
    //   35: invokestatic 96	hbe:a	(Ljava/lang/Object;)Ljava/lang/Object;
    //   38: pop
    //   39: aload 9
    //   41: ifnull +8 -> 49
    //   44: aload 9
    //   46: invokevirtual 116	grv:b	()V
    //   49: aconst_null
    //   50: astore 14
    //   52: aload_0
    //   53: getfield 118	grs:a	Lgrm;
    //   56: ifnull +13 -> 69
    //   59: aload_0
    //   60: getfield 118	grs:a	Lgrm;
    //   63: aload_0
    //   64: invokeinterface 123 2 0
    //   69: aload_0
    //   70: getfield 100	grs:j	Lgri;
    //   73: invokevirtual 126	gri:c	()Ljava/lang/String;
    //   76: astore 16
    //   78: aload_0
    //   79: getfield 82	grs:h	Lgsa;
    //   82: aload_0
    //   83: getfield 107	grs:i	Ljava/lang/String;
    //   86: aload 16
    //   88: invokevirtual 131	gsa:a	(Ljava/lang/String;Ljava/lang/String;)Lgsd;
    //   91: astore 17
    //   93: getstatic 134	gsa:a	Ljava/util/logging/Logger;
    //   96: astore 15
    //   98: aload_0
    //   99: getfield 62	grs:f	Z
    //   102: ifeq +944 -> 1046
    //   105: aload 15
    //   107: getstatic 140	java/util/logging/Level:CONFIG	Ljava/util/logging/Level;
    //   110: invokevirtual 146	java/util/logging/Logger:isLoggable	(Ljava/util/logging/Level;)Z
    //   113: ifeq +933 -> 1046
    //   116: iconst_1
    //   117: istore_2
    //   118: iload_2
    //   119: ifeq +1363 -> 1482
    //   122: new 148	java/lang/StringBuilder
    //   125: dup
    //   126: invokespecial 149	java/lang/StringBuilder:<init>	()V
    //   129: astore 11
    //   131: aload 11
    //   133: ldc -105
    //   135: invokevirtual 155	java/lang/StringBuilder:append	(Ljava/lang/String;)Ljava/lang/StringBuilder;
    //   138: getstatic 159	gur:a	Ljava/lang/String;
    //   141: invokevirtual 155	java/lang/StringBuilder:append	(Ljava/lang/String;)Ljava/lang/StringBuilder;
    //   144: pop
    //   145: aload 11
    //   147: aload_0
    //   148: getfield 107	grs:i	Ljava/lang/String;
    //   151: invokevirtual 155	java/lang/StringBuilder:append	(Ljava/lang/String;)Ljava/lang/StringBuilder;
    //   154: bipush 32
    //   156: invokevirtual 162	java/lang/StringBuilder:append	(C)Ljava/lang/StringBuilder;
    //   159: aload 16
    //   161: invokevirtual 155	java/lang/StringBuilder:append	(Ljava/lang/String;)Ljava/lang/StringBuilder;
    //   164: getstatic 159	gur:a	Ljava/lang/String;
    //   167: invokevirtual 155	java/lang/StringBuilder:append	(Ljava/lang/String;)Ljava/lang/StringBuilder;
    //   170: pop
    //   171: aload_0
    //   172: getfield 64	grs:q	Z
    //   175: ifeq +1301 -> 1476
    //   178: new 148	java/lang/StringBuilder
    //   181: dup
    //   182: ldc -92
    //   184: invokespecial 167	java/lang/StringBuilder:<init>	(Ljava/lang/String;)V
    //   187: astore 10
    //   189: aload_0
    //   190: getfield 107	grs:i	Ljava/lang/String;
    //   193: ldc -87
    //   195: invokevirtual 175	java/lang/String:equals	(Ljava/lang/Object;)Z
    //   198: ifne +18 -> 216
    //   201: aload 10
    //   203: ldc -79
    //   205: invokevirtual 155	java/lang/StringBuilder:append	(Ljava/lang/String;)Ljava/lang/StringBuilder;
    //   208: aload_0
    //   209: getfield 107	grs:i	Ljava/lang/String;
    //   212: invokevirtual 155	java/lang/StringBuilder:append	(Ljava/lang/String;)Ljava/lang/StringBuilder;
    //   215: pop
    //   216: aload_0
    //   217: getfield 54	grs:b	Lgrn;
    //   220: getfield 181	grn:userAgent	Ljava/util/List;
    //   223: invokestatic 184	grn:a	(Ljava/util/List;)Ljava/lang/Object;
    //   226: checkcast 171	java/lang/String
    //   229: astore 9
    //   231: aload_0
    //   232: getfield 186	grs:w	Z
    //   235: ifne +18 -> 253
    //   238: aload 9
    //   240: ifnonnull +811 -> 1051
    //   243: aload_0
    //   244: getfield 54	grs:b	Lgrn;
    //   247: ldc -68
    //   249: invokevirtual 191	grn:f	(Ljava/lang/String;)Lgrn;
    //   252: pop
    //   253: aload_0
    //   254: getfield 54	grs:b	Lgrn;
    //   257: aload 11
    //   259: aload 10
    //   261: aload 15
    //   263: aload 17
    //   265: invokestatic 194	grn:a	(Lgrn;Ljava/lang/StringBuilder;Ljava/lang/StringBuilder;Ljava/util/logging/Logger;Lgsd;)V
    //   268: aload_0
    //   269: getfield 186	grs:w	Z
    //   272: ifne +13 -> 285
    //   275: aload_0
    //   276: getfield 54	grs:b	Lgrn;
    //   279: aload 9
    //   281: invokevirtual 191	grn:f	(Ljava/lang/String;)Lgrn;
    //   284: pop
    //   285: aload_0
    //   286: getfield 196	grs:g	Lgrj;
    //   289: astore 9
    //   291: aload 9
    //   293: ifnull +15 -> 308
    //   296: aload_0
    //   297: getfield 196	grs:g	Lgrj;
    //   300: invokeinterface 201 1 0
    //   305: ifeq +813 -> 1118
    //   308: iconst_1
    //   309: istore_3
    //   310: aload 9
    //   312: astore 12
    //   314: aload 9
    //   316: ifnull +330 -> 646
    //   319: aload_0
    //   320: getfield 196	grs:g	Lgrj;
    //   323: invokeinterface 202 1 0
    //   328: astore 18
    //   330: iload_2
    //   331: ifeq +1142 -> 1473
    //   334: new 204	guk
    //   337: dup
    //   338: aload 9
    //   340: getstatic 134	gsa:a	Ljava/util/logging/Logger;
    //   343: getstatic 140	java/util/logging/Level:CONFIG	Ljava/util/logging/Level;
    //   346: aload_0
    //   347: getfield 60	grs:e	I
    //   350: invokespecial 207	guk:<init>	(Lguq;Ljava/util/logging/Logger;Ljava/util/logging/Level;I)V
    //   353: astore 9
    //   355: aload_0
    //   356: getfield 209	grs:o	Lgrk;
    //   359: ifnonnull +764 -> 1123
    //   362: aload_0
    //   363: getfield 196	grs:g	Lgrj;
    //   366: invokeinterface 212 1 0
    //   371: lstore 7
    //   373: aconst_null
    //   374: astore 12
    //   376: iload_2
    //   377: ifeq +224 -> 601
    //   380: aload 18
    //   382: ifnull +88 -> 470
    //   385: aload 18
    //   387: invokestatic 216	java/lang/String:valueOf	(Ljava/lang/Object;)Ljava/lang/String;
    //   390: astore 13
    //   392: aload 13
    //   394: invokevirtual 220	java/lang/String:length	()I
    //   397: ifeq +774 -> 1171
    //   400: ldc -34
    //   402: aload 13
    //   404: invokevirtual 226	java/lang/String:concat	(Ljava/lang/String;)Ljava/lang/String;
    //   407: astore 13
    //   409: aload 11
    //   411: aload 13
    //   413: invokevirtual 155	java/lang/StringBuilder:append	(Ljava/lang/String;)Ljava/lang/StringBuilder;
    //   416: getstatic 159	gur:a	Ljava/lang/String;
    //   419: invokevirtual 155	java/lang/StringBuilder:append	(Ljava/lang/String;)Ljava/lang/StringBuilder;
    //   422: pop
    //   423: aload 10
    //   425: ifnull +45 -> 470
    //   428: aload 10
    //   430: new 148	java/lang/StringBuilder
    //   433: dup
    //   434: aload 13
    //   436: invokestatic 216	java/lang/String:valueOf	(Ljava/lang/Object;)Ljava/lang/String;
    //   439: invokevirtual 220	java/lang/String:length	()I
    //   442: bipush 6
    //   444: iadd
    //   445: invokespecial 229	java/lang/StringBuilder:<init>	(I)V
    //   448: ldc -25
    //   450: invokevirtual 155	java/lang/StringBuilder:append	(Ljava/lang/String;)Ljava/lang/StringBuilder;
    //   453: aload 13
    //   455: invokevirtual 155	java/lang/StringBuilder:append	(Ljava/lang/String;)Ljava/lang/StringBuilder;
    //   458: ldc -23
    //   460: invokevirtual 155	java/lang/StringBuilder:append	(Ljava/lang/String;)Ljava/lang/StringBuilder;
    //   463: invokevirtual 236	java/lang/StringBuilder:toString	()Ljava/lang/String;
    //   466: invokevirtual 155	java/lang/StringBuilder:append	(Ljava/lang/String;)Ljava/lang/StringBuilder;
    //   469: pop
    //   470: aload 12
    //   472: ifnull +88 -> 560
    //   475: aload 12
    //   477: invokestatic 216	java/lang/String:valueOf	(Ljava/lang/Object;)Ljava/lang/String;
    //   480: astore 13
    //   482: aload 13
    //   484: invokevirtual 220	java/lang/String:length	()I
    //   487: ifeq +698 -> 1185
    //   490: ldc -18
    //   492: aload 13
    //   494: invokevirtual 226	java/lang/String:concat	(Ljava/lang/String;)Ljava/lang/String;
    //   497: astore 13
    //   499: aload 11
    //   501: aload 13
    //   503: invokevirtual 155	java/lang/StringBuilder:append	(Ljava/lang/String;)Ljava/lang/StringBuilder;
    //   506: getstatic 159	gur:a	Ljava/lang/String;
    //   509: invokevirtual 155	java/lang/StringBuilder:append	(Ljava/lang/String;)Ljava/lang/StringBuilder;
    //   512: pop
    //   513: aload 10
    //   515: ifnull +45 -> 560
    //   518: aload 10
    //   520: new 148	java/lang/StringBuilder
    //   523: dup
    //   524: aload 13
    //   526: invokestatic 216	java/lang/String:valueOf	(Ljava/lang/Object;)Ljava/lang/String;
    //   529: invokevirtual 220	java/lang/String:length	()I
    //   532: bipush 6
    //   534: iadd
    //   535: invokespecial 229	java/lang/StringBuilder:<init>	(I)V
    //   538: ldc -25
    //   540: invokevirtual 155	java/lang/StringBuilder:append	(Ljava/lang/String;)Ljava/lang/StringBuilder;
    //   543: aload 13
    //   545: invokevirtual 155	java/lang/StringBuilder:append	(Ljava/lang/String;)Ljava/lang/StringBuilder;
    //   548: ldc -23
    //   550: invokevirtual 155	java/lang/StringBuilder:append	(Ljava/lang/String;)Ljava/lang/StringBuilder;
    //   553: invokevirtual 236	java/lang/StringBuilder:toString	()Ljava/lang/String;
    //   556: invokevirtual 155	java/lang/StringBuilder:append	(Ljava/lang/String;)Ljava/lang/StringBuilder;
    //   559: pop
    //   560: lload 7
    //   562: lconst_0
    //   563: lcmp
    //   564: iflt +37 -> 601
    //   567: aload 11
    //   569: new 148	java/lang/StringBuilder
    //   572: dup
    //   573: bipush 36
    //   575: invokespecial 229	java/lang/StringBuilder:<init>	(I)V
    //   578: ldc -16
    //   580: invokevirtual 155	java/lang/StringBuilder:append	(Ljava/lang/String;)Ljava/lang/StringBuilder;
    //   583: lload 7
    //   585: invokevirtual 243	java/lang/StringBuilder:append	(J)Ljava/lang/StringBuilder;
    //   588: invokevirtual 236	java/lang/StringBuilder:toString	()Ljava/lang/String;
    //   591: invokevirtual 155	java/lang/StringBuilder:append	(Ljava/lang/String;)Ljava/lang/StringBuilder;
    //   594: getstatic 159	gur:a	Ljava/lang/String;
    //   597: invokevirtual 155	java/lang/StringBuilder:append	(Ljava/lang/String;)Ljava/lang/StringBuilder;
    //   600: pop
    //   601: aload 10
    //   603: ifnull +11 -> 614
    //   606: aload 10
    //   608: ldc -11
    //   610: invokevirtual 155	java/lang/StringBuilder:append	(Ljava/lang/String;)Ljava/lang/StringBuilder;
    //   613: pop
    //   614: aload 17
    //   616: aload 18
    //   618: putfield 249	gsd:c	Ljava/lang/String;
    //   621: aload 17
    //   623: aload 12
    //   625: putfield 251	gsd:b	Ljava/lang/String;
    //   628: aload 17
    //   630: lload 7
    //   632: putfield 254	gsd:a	J
    //   635: aload 17
    //   637: aload 9
    //   639: putfield 257	gsd:d	Lguq;
    //   642: aload 9
    //   644: astore 12
    //   646: iload_2
    //   647: ifeq +75 -> 722
    //   650: aload 15
    //   652: aload 11
    //   654: invokevirtual 236	java/lang/StringBuilder:toString	()Ljava/lang/String;
    //   657: invokevirtual 260	java/util/logging/Logger:config	(Ljava/lang/String;)V
    //   660: aload 10
    //   662: ifnull +60 -> 722
    //   665: aload 10
    //   667: ldc_w 262
    //   670: invokevirtual 155	java/lang/StringBuilder:append	(Ljava/lang/String;)Ljava/lang/StringBuilder;
    //   673: pop
    //   674: aload 10
    //   676: aload 16
    //   678: ldc -23
    //   680: ldc_w 264
    //   683: invokevirtual 268	java/lang/String:replaceAll	(Ljava/lang/String;Ljava/lang/String;)Ljava/lang/String;
    //   686: invokevirtual 155	java/lang/StringBuilder:append	(Ljava/lang/String;)Ljava/lang/StringBuilder;
    //   689: pop
    //   690: aload 10
    //   692: ldc -23
    //   694: invokevirtual 155	java/lang/StringBuilder:append	(Ljava/lang/String;)Ljava/lang/StringBuilder;
    //   697: pop
    //   698: aload 12
    //   700: ifnull +12 -> 712
    //   703: aload 10
    //   705: ldc_w 270
    //   708: invokevirtual 155	java/lang/StringBuilder:append	(Ljava/lang/String;)Ljava/lang/StringBuilder;
    //   711: pop
    //   712: aload 15
    //   714: aload 10
    //   716: invokevirtual 236	java/lang/StringBuilder:toString	()Ljava/lang/String;
    //   719: invokevirtual 260	java/util/logging/Logger:config	(Ljava/lang/String;)V
    //   722: iload_3
    //   723: ifeq +476 -> 1199
    //   726: iload_1
    //   727: ifle +472 -> 1199
    //   730: iconst_1
    //   731: istore 6
    //   733: aload 17
    //   735: aload_0
    //   736: getfield 66	grs:r	I
    //   739: aload_0
    //   740: getfield 68	grs:s	I
    //   743: invokevirtual 273	gsd:a	(II)V
    //   746: aload 17
    //   748: invokevirtual 276	gsd:a	()Lgse;
    //   751: astore 10
    //   753: new 114	grv
    //   756: dup
    //   757: aload_0
    //   758: aload 10
    //   760: invokespecial 279	grv:<init>	(Lgrs;Lgse;)V
    //   763: astore 9
    //   765: aload 14
    //   767: astore 10
    //   769: aload 9
    //   771: ifnull +596 -> 1367
    //   774: aload 9
    //   776: getfield 281	grv:c	I
    //   779: invokestatic 286	grz:a	(I)Z
    //   782: ifne +585 -> 1367
    //   785: iconst_0
    //   786: istore 4
    //   788: aload_0
    //   789: getfield 288	grs:k	Lgsb;
    //   792: ifnull +19 -> 811
    //   795: aload_0
    //   796: getfield 288	grs:k	Lgsb;
    //   799: aload_0
    //   800: aload 9
    //   802: iload 6
    //   804: invokeinterface 293 4 0
    //   809: istore 4
    //   811: iload 4
    //   813: istore 5
    //   815: iload 4
    //   817: ifne +187 -> 1004
    //   820: aload 9
    //   822: getfield 281	grv:c	I
    //   825: istore_3
    //   826: aload 9
    //   828: getfield 296	grv:e	Lgrs;
    //   831: getfield 56	grs:c	Lgrn;
    //   834: invokevirtual 298	grn:a	()Ljava/lang/String;
    //   837: astore 11
    //   839: aload_0
    //   840: getfield 70	grs:u	Z
    //   843: ifeq +442 -> 1285
    //   846: iload_3
    //   847: tableswitch	default:+644->1491, 301:+433->1280, 302:+433->1280, 303:+433->1280, 304:+644->1491, 305:+644->1491, 306:+644->1491, 307:+433->1280
    //   888: iload_2
    //   889: ifeq +396 -> 1285
    //   892: aload 11
    //   894: ifnull +391 -> 1285
    //   897: aload_0
    //   898: new 98	gri
    //   901: dup
    //   902: aload_0
    //   903: getfield 100	grs:j	Lgri;
    //   906: aload 11
    //   908: invokevirtual 301	gri:a	(Ljava/lang/String;)Ljava/net/URL;
    //   911: invokespecial 304	gri:<init>	(Ljava/net/URL;)V
    //   914: invokevirtual 306	grs:a	(Lgri;)Lgrs;
    //   917: pop
    //   918: iload_3
    //   919: sipush 303
    //   922: if_icmpne +15 -> 937
    //   925: aload_0
    //   926: ldc -87
    //   928: invokevirtual 85	grs:a	(Ljava/lang/String;)Lgrs;
    //   931: pop
    //   932: aload_0
    //   933: aconst_null
    //   934: putfield 196	grs:g	Lgrj;
    //   937: aload_0
    //   938: getfield 54	grs:b	Lgrn;
    //   941: aconst_null
    //   942: invokevirtual 308	grn:a	(Ljava/lang/String;)Lgrn;
    //   945: pop
    //   946: aload_0
    //   947: getfield 54	grs:b	Lgrn;
    //   950: aconst_null
    //   951: invokevirtual 310	grn:e	(Ljava/lang/String;)Lgrn;
    //   954: pop
    //   955: aload_0
    //   956: getfield 54	grs:b	Lgrn;
    //   959: aconst_null
    //   960: invokestatic 313	grn:a	(Ljava/lang/Object;)Ljava/util/List;
    //   963: putfield 316	grn:ifNoneMatch	Ljava/util/List;
    //   966: aload_0
    //   967: getfield 54	grs:b	Lgrn;
    //   970: aconst_null
    //   971: invokestatic 313	grn:a	(Ljava/lang/Object;)Ljava/util/List;
    //   974: putfield 319	grn:ifModifiedSince	Ljava/util/List;
    //   977: aload_0
    //   978: getfield 54	grs:b	Lgrn;
    //   981: aconst_null
    //   982: invokestatic 313	grn:a	(Ljava/lang/Object;)Ljava/util/List;
    //   985: putfield 322	grn:ifUnmodifiedSince	Ljava/util/List;
    //   988: aload_0
    //   989: getfield 54	grs:b	Lgrn;
    //   992: aconst_null
    //   993: invokestatic 313	grn:a	(Ljava/lang/Object;)Ljava/util/List;
    //   996: putfield 325	grn:ifRange	Ljava/util/List;
    //   999: iconst_1
    //   1000: istore_2
    //   1001: goto +495 -> 1496
    //   1004: iload 6
    //   1006: iload 5
    //   1008: iand
    //   1009: istore_3
    //   1010: iload_3
    //   1011: istore_2
    //   1012: iload_3
    //   1013: ifeq +10 -> 1023
    //   1016: aload 9
    //   1018: invokevirtual 116	grv:b	()V
    //   1021: iload_3
    //   1022: istore_2
    //   1023: aload 9
    //   1025: ifnull +3 -> 1028
    //   1028: iload_2
    //   1029: ifne +437 -> 1466
    //   1032: aload 9
    //   1034: ifnonnull +368 -> 1402
    //   1037: aload 10
    //   1039: athrow
    //   1040: iconst_0
    //   1041: istore 4
    //   1043: goto -1033 -> 10
    //   1046: iconst_0
    //   1047: istore_2
    //   1048: goto -930 -> 118
    //   1051: aload_0
    //   1052: getfield 54	grs:b	Lgrn;
    //   1055: astore 12
    //   1057: ldc -68
    //   1059: invokestatic 216	java/lang/String:valueOf	(Ljava/lang/Object;)Ljava/lang/String;
    //   1062: astore 13
    //   1064: aload 12
    //   1066: new 148	java/lang/StringBuilder
    //   1069: dup
    //   1070: aload 9
    //   1072: invokestatic 216	java/lang/String:valueOf	(Ljava/lang/Object;)Ljava/lang/String;
    //   1075: invokevirtual 220	java/lang/String:length	()I
    //   1078: iconst_1
    //   1079: iadd
    //   1080: aload 13
    //   1082: invokestatic 216	java/lang/String:valueOf	(Ljava/lang/Object;)Ljava/lang/String;
    //   1085: invokevirtual 220	java/lang/String:length	()I
    //   1088: iadd
    //   1089: invokespecial 229	java/lang/StringBuilder:<init>	(I)V
    //   1092: aload 9
    //   1094: invokevirtual 155	java/lang/StringBuilder:append	(Ljava/lang/String;)Ljava/lang/StringBuilder;
    //   1097: ldc_w 327
    //   1100: invokevirtual 155	java/lang/StringBuilder:append	(Ljava/lang/String;)Ljava/lang/StringBuilder;
    //   1103: aload 13
    //   1105: invokevirtual 155	java/lang/StringBuilder:append	(Ljava/lang/String;)Ljava/lang/StringBuilder;
    //   1108: invokevirtual 236	java/lang/StringBuilder:toString	()Ljava/lang/String;
    //   1111: invokevirtual 191	grn:f	(Ljava/lang/String;)Lgrn;
    //   1114: pop
    //   1115: goto -862 -> 253
    //   1118: iconst_0
    //   1119: istore_3
    //   1120: goto -810 -> 310
    //   1123: aload_0
    //   1124: getfield 209	grs:o	Lgrk;
    //   1127: invokeinterface 330 1 0
    //   1132: astore 12
    //   1134: new 332	grl
    //   1137: dup
    //   1138: aload 9
    //   1140: aload_0
    //   1141: getfield 209	grs:o	Lgrk;
    //   1144: invokespecial 335	grl:<init>	(Lguq;Lgrk;)V
    //   1147: astore 9
    //   1149: iload_3
    //   1150: ifeq +13 -> 1163
    //   1153: aload 9
    //   1155: invokestatic 340	gue:a	(Lguq;)J
    //   1158: lstore 7
    //   1160: goto -784 -> 376
    //   1163: ldc2_w 341
    //   1166: lstore 7
    //   1168: goto -792 -> 376
    //   1171: new 171	java/lang/String
    //   1174: dup
    //   1175: ldc -34
    //   1177: invokespecial 343	java/lang/String:<init>	(Ljava/lang/String;)V
    //   1180: astore 13
    //   1182: goto -773 -> 409
    //   1185: new 171	java/lang/String
    //   1188: dup
    //   1189: ldc -18
    //   1191: invokespecial 343	java/lang/String:<init>	(Ljava/lang/String;)V
    //   1194: astore 13
    //   1196: goto -697 -> 499
    //   1199: iconst_0
    //   1200: istore 6
    //   1202: goto -469 -> 733
    //   1205: astore 9
    //   1207: aload 10
    //   1209: invokevirtual 348	gse:a	()Ljava/io/InputStream;
    //   1212: astore 10
    //   1214: aload 10
    //   1216: ifnull +8 -> 1224
    //   1219: aload 10
    //   1221: invokevirtual 353	java/io/InputStream:close	()V
    //   1224: aload 9
    //   1226: athrow
    //   1227: astore 10
    //   1229: aload_0
    //   1230: getfield 74	grs:v	Z
    //   1233: ifne +28 -> 1261
    //   1236: aload_0
    //   1237: getfield 355	grs:l	Lgrq;
    //   1240: ifnull +18 -> 1258
    //   1243: aload_0
    //   1244: getfield 355	grs:l	Lgrq;
    //   1247: aload_0
    //   1248: iload 6
    //   1250: invokeinterface 360 3 0
    //   1255: ifne +6 -> 1261
    //   1258: aload 10
    //   1260: athrow
    //   1261: aload 15
    //   1263: getstatic 363	java/util/logging/Level:WARNING	Ljava/util/logging/Level;
    //   1266: ldc_w 365
    //   1269: aload 10
    //   1271: invokevirtual 369	java/util/logging/Logger:log	(Ljava/util/logging/Level;Ljava/lang/String;Ljava/lang/Throwable;)V
    //   1274: aconst_null
    //   1275: astore 9
    //   1277: goto -508 -> 769
    //   1280: iconst_1
    //   1281: istore_2
    //   1282: goto -394 -> 888
    //   1285: iconst_0
    //   1286: istore_2
    //   1287: goto +209 -> 1496
    //   1290: iload 4
    //   1292: istore 5
    //   1294: iload 6
    //   1296: ifeq -292 -> 1004
    //   1299: iload 4
    //   1301: istore 5
    //   1303: aload_0
    //   1304: getfield 371	grs:t	Lgrd;
    //   1307: ifnull -303 -> 1004
    //   1310: iload 4
    //   1312: istore 5
    //   1314: aload_0
    //   1315: getfield 371	grs:t	Lgrd;
    //   1318: invokeinterface 375 1 0
    //   1323: ifeq -319 -> 1004
    //   1326: aload_0
    //   1327: getfield 371	grs:t	Lgrd;
    //   1330: invokeinterface 377 1 0
    //   1335: lstore 7
    //   1337: iload 4
    //   1339: istore 5
    //   1341: lload 7
    //   1343: ldc2_w 341
    //   1346: lcmp
    //   1347: ifeq -343 -> 1004
    //   1350: aload_0
    //   1351: getfield 80	grs:x	Lguo;
    //   1354: lload 7
    //   1356: invokeinterface 380 3 0
    //   1361: iconst_1
    //   1362: istore 5
    //   1364: goto -360 -> 1004
    //   1367: aload 9
    //   1369: ifnonnull +13 -> 1382
    //   1372: iconst_1
    //   1373: istore_2
    //   1374: iload 6
    //   1376: iload_2
    //   1377: iand
    //   1378: istore_2
    //   1379: goto -356 -> 1023
    //   1382: iconst_0
    //   1383: istore_2
    //   1384: goto -10 -> 1374
    //   1387: astore 10
    //   1389: aload 9
    //   1391: ifnull +8 -> 1399
    //   1394: aload 9
    //   1396: invokevirtual 382	grv:c	()V
    //   1399: aload 10
    //   1401: athrow
    //   1402: aload_0
    //   1403: getfield 384	grs:m	Lgry;
    //   1406: ifnull +14 -> 1420
    //   1409: aload_0
    //   1410: getfield 384	grs:m	Lgry;
    //   1413: aload 9
    //   1415: invokeinterface 389 2 0
    //   1420: aload_0
    //   1421: getfield 72	grs:p	Z
    //   1424: ifeq +34 -> 1458
    //   1427: aload 9
    //   1429: getfield 281	grv:c	I
    //   1432: invokestatic 286	grz:a	(I)Z
    //   1435: ifne +23 -> 1458
    //   1438: new 391	grw
    //   1441: dup
    //   1442: aload 9
    //   1444: invokespecial 393	grw:<init>	(Lgrv;)V
    //   1447: athrow
    //   1448: astore 10
    //   1450: aload 9
    //   1452: invokevirtual 382	grv:c	()V
    //   1455: aload 10
    //   1457: athrow
    //   1458: aload 9
    //   1460: areturn
    //   1461: astore 11
    //   1463: goto -102 -> 1361
    //   1466: iload_1
    //   1467: iconst_1
    //   1468: isub
    //   1469: istore_1
    //   1470: goto -1431 -> 39
    //   1473: goto -1118 -> 355
    //   1476: aconst_null
    //   1477: astore 10
    //   1479: goto -1263 -> 216
    //   1482: aconst_null
    //   1483: astore 11
    //   1485: aconst_null
    //   1486: astore 10
    //   1488: goto -1272 -> 216
    //   1491: iconst_0
    //   1492: istore_2
    //   1493: goto -605 -> 888
    //   1496: iload_2
    //   1497: ifeq -207 -> 1290
    //   1500: iconst_1
    //   1501: istore 5
    //   1503: goto -499 -> 1004
    // Local variable table:
    //   start	length	slot	name	signature
    //   0	1506	0	this	grs
    //   19	1451	1	i1	int
    //   117	1380	2	bool1	boolean
    //   309	841	3	i2	int
    //   8	1330	4	bool2	boolean
    //   813	689	5	bool3	boolean
    //   731	647	6	bool4	boolean
    //   371	984	7	l1	long
    //   21	1133	9	localObject1	Object
    //   1205	20	9	localObject2	Object
    //   1275	184	9	localgrv	grv
    //   187	1033	10	localObject3	Object
    //   1227	43	10	localIOException	java.io.IOException
    //   1387	13	10	localObject4	Object
    //   1448	8	10	localObject5	Object
    //   1477	10	10	localObject6	Object
    //   129	778	11	localObject7	Object
    //   1461	1	11	localInterruptedException	InterruptedException
    //   1483	1	11	localObject8	Object
    //   312	821	12	localObject9	Object
    //   390	805	13	str1	String
    //   50	716	14	localObject10	Object
    //   96	1166	15	localLogger	java.util.logging.Logger
    //   76	601	16	str2	String
    //   91	656	17	localgsd	gsd
    //   328	289	18	str3	String
    // Exception table:
    //   from	to	target	type
    //   753	765	1205	finally
    //   746	753	1227	java/io/IOException
    //   1207	1214	1227	java/io/IOException
    //   1219	1224	1227	java/io/IOException
    //   1224	1227	1227	java/io/IOException
    //   774	785	1387	finally
    //   788	811	1387	finally
    //   820	846	1387	finally
    //   897	918	1387	finally
    //   925	937	1387	finally
    //   937	999	1387	finally
    //   1016	1021	1387	finally
    //   1303	1310	1387	finally
    //   1314	1337	1387	finally
    //   1350	1361	1387	finally
    //   1438	1448	1448	finally
    //   1350	1361	1461	java/lang/InterruptedException
  }
  
  public final grs b(int paramInt)
  {
    if (paramInt >= 0) {}
    for (boolean bool = true;; bool = false)
    {
      hbe.a(bool);
      s = paramInt;
      return this;
    }
  }
}

/* Location:
 * Qualified Name:     grs
 * Java Class Version: 6 (50.0)
 * JD-Core Version:    0.7.1
 */