import java.net.URL;
import java.security.PrivilegedAction;

public final class idr
  implements PrivilegedAction
{
  private final URL a;
  
  public idr(URL paramURL)
  {
    a = paramURL;
  }
  
  /* Error */
  public final Object run()
  {
    // Byte code:
    //   0: aload_0
    //   1: getfield 15	idr:a	Ljava/net/URL;
    //   4: invokevirtual 26	java/net/URL:openConnection	()Ljava/net/URLConnection;
    //   7: astore_1
    //   8: aload_1
    //   9: iconst_0
    //   10: invokevirtual 32	java/net/URLConnection:setUseCaches	(Z)V
    //   13: aload_1
    //   14: invokevirtual 36	java/net/URLConnection:getInputStream	()Ljava/io/InputStream;
    //   17: astore_1
    //   18: aload_1
    //   19: ifnull +22 -> 41
    //   22: new 38	java/util/Properties
    //   25: dup
    //   26: invokespecial 39	java/util/Properties:<init>	()V
    //   29: astore_2
    //   30: aload_2
    //   31: aload_1
    //   32: invokevirtual 43	java/util/Properties:load	(Ljava/io/InputStream;)V
    //   35: aload_1
    //   36: invokevirtual 48	java/io/InputStream:close	()V
    //   39: aload_2
    //   40: areturn
    //   41: aload_1
    //   42: ifnull +7 -> 49
    //   45: aload_1
    //   46: invokevirtual 48	java/io/InputStream:close	()V
    //   49: aconst_null
    //   50: areturn
    //   51: astore_1
    //   52: invokestatic 54	org/apache/commons/logging/LogFactory:isDiagnosticsEnabled	()Z
    //   55: ifeq -6 -> 49
    //   58: new 56	java/lang/StringBuffer
    //   61: dup
    //   62: ldc 58
    //   64: invokespecial 61	java/lang/StringBuffer:<init>	(Ljava/lang/String;)V
    //   67: aload_0
    //   68: getfield 15	idr:a	Ljava/net/URL;
    //   71: invokevirtual 65	java/lang/StringBuffer:append	(Ljava/lang/Object;)Ljava/lang/StringBuffer;
    //   74: invokevirtual 69	java/lang/StringBuffer:toString	()Ljava/lang/String;
    //   77: invokestatic 72	org/apache/commons/logging/LogFactory:access$000	(Ljava/lang/String;)V
    //   80: goto -31 -> 49
    //   83: astore_1
    //   84: aconst_null
    //   85: astore_1
    //   86: invokestatic 54	org/apache/commons/logging/LogFactory:isDiagnosticsEnabled	()Z
    //   89: ifeq +25 -> 114
    //   92: new 56	java/lang/StringBuffer
    //   95: dup
    //   96: ldc 74
    //   98: invokespecial 61	java/lang/StringBuffer:<init>	(Ljava/lang/String;)V
    //   101: aload_0
    //   102: getfield 15	idr:a	Ljava/net/URL;
    //   105: invokevirtual 65	java/lang/StringBuffer:append	(Ljava/lang/Object;)Ljava/lang/StringBuffer;
    //   108: invokevirtual 69	java/lang/StringBuffer:toString	()Ljava/lang/String;
    //   111: invokestatic 72	org/apache/commons/logging/LogFactory:access$000	(Ljava/lang/String;)V
    //   114: aload_1
    //   115: ifnull -66 -> 49
    //   118: aload_1
    //   119: invokevirtual 48	java/io/InputStream:close	()V
    //   122: goto -73 -> 49
    //   125: astore_1
    //   126: invokestatic 54	org/apache/commons/logging/LogFactory:isDiagnosticsEnabled	()Z
    //   129: ifeq -80 -> 49
    //   132: new 56	java/lang/StringBuffer
    //   135: dup
    //   136: ldc 58
    //   138: invokespecial 61	java/lang/StringBuffer:<init>	(Ljava/lang/String;)V
    //   141: aload_0
    //   142: getfield 15	idr:a	Ljava/net/URL;
    //   145: invokevirtual 65	java/lang/StringBuffer:append	(Ljava/lang/Object;)Ljava/lang/StringBuffer;
    //   148: invokevirtual 69	java/lang/StringBuffer:toString	()Ljava/lang/String;
    //   151: invokestatic 72	org/apache/commons/logging/LogFactory:access$000	(Ljava/lang/String;)V
    //   154: goto -105 -> 49
    //   157: astore_2
    //   158: aconst_null
    //   159: astore_1
    //   160: aload_1
    //   161: ifnull +7 -> 168
    //   164: aload_1
    //   165: invokevirtual 48	java/io/InputStream:close	()V
    //   168: aload_2
    //   169: athrow
    //   170: astore_1
    //   171: invokestatic 54	org/apache/commons/logging/LogFactory:isDiagnosticsEnabled	()Z
    //   174: ifeq -6 -> 168
    //   177: new 56	java/lang/StringBuffer
    //   180: dup
    //   181: ldc 58
    //   183: invokespecial 61	java/lang/StringBuffer:<init>	(Ljava/lang/String;)V
    //   186: aload_0
    //   187: getfield 15	idr:a	Ljava/net/URL;
    //   190: invokevirtual 65	java/lang/StringBuffer:append	(Ljava/lang/Object;)Ljava/lang/StringBuffer;
    //   193: invokevirtual 69	java/lang/StringBuffer:toString	()Ljava/lang/String;
    //   196: invokestatic 72	org/apache/commons/logging/LogFactory:access$000	(Ljava/lang/String;)V
    //   199: goto -31 -> 168
    //   202: astore_2
    //   203: goto -43 -> 160
    //   206: astore_2
    //   207: goto -47 -> 160
    //   210: astore_2
    //   211: goto -125 -> 86
    // Local variable table:
    //   start	length	slot	name	signature
    //   0	214	0	this	idr
    //   7	39	1	localObject1	Object
    //   51	1	1	localIOException1	java.io.IOException
    //   83	1	1	localIOException2	java.io.IOException
    //   85	34	1	localObject2	Object
    //   125	1	1	localIOException3	java.io.IOException
    //   159	6	1	localObject3	Object
    //   170	1	1	localIOException4	java.io.IOException
    //   29	11	2	localProperties	java.util.Properties
    //   157	12	2	localObject4	Object
    //   202	1	2	localObject5	Object
    //   206	1	2	localObject6	Object
    //   210	1	2	localIOException5	java.io.IOException
    // Exception table:
    //   from	to	target	type
    //   45	49	51	java/io/IOException
    //   0	18	83	java/io/IOException
    //   118	122	125	java/io/IOException
    //   0	18	157	finally
    //   164	168	170	java/io/IOException
    //   22	39	202	finally
    //   86	114	206	finally
    //   22	39	210	java/io/IOException
  }
}

/* Location:
 * Qualified Name:     idr
 * Java Class Version: 6 (50.0)
 * JD-Core Version:    0.7.1
 */